Workbook
Name SegmentaçãodeDados_Oficina: #N/A
Name SegmentaçãodeDados_Status: #N/A

Sheet Peças
A1: DATA | B1: FILTRO DE COMBUSTIVEL | C1: FILTRO DE AR | D1: FILTRO DE OLEO | E1: OLEO MOTOR 5W30 | F1: PASTILHA DE FREIO D/ | G1: FILTRO DE COMBUSTIVEL MASTER 2023 | H1: PASTILHA DE FREIO TRASEIRA | I1: DISCO DE FREIO D/ | J1: DISCO DE FREIO T/ | K1: FLUIDO DE FREIO DT 4 | L1: KIT CORRERIA ALTERNADOR 2.3 | M1: KIT CORRERIA ALTERNADOR 2023 | N1: OLEO HIDRAULICO | O1: PINÇA TRASEIRA | P1: PINÇA DIANTEIRA | Q1: COPO FILTRO MASTER ANTIGA 2.3 | R1: LAMPADA H7 | S1: LAMPADAS 1 POLO | T1: LAMPADA 2 POLO | U1: LAMPADA PINGUINHO | V1: SEMI EIXO D 2 | W1: SEMI EIXO E | X1: HOMOCINETICA | Y1: PIVO D/ | Z1: PIVO E/ | AA1: BIELETA | AB1: PULIA DO VIRA | AC1: SENSOR MAF | AD1: TERMINAL D/ | AE1: TERMINAL E/ | AF1: KIT AMORTECEDR D/E | AG1: KIT AMORTECEDOR | AH1: BOMBA DO TANQUE | AI1: BOMBA DE ALTA RECONDICIONADA | AJ1: BOMBA DIREÇÃO | AK1: MANGUEIRA DE PRESSAO DA CIAXA | AL1: AGUA DESTILADA | AM1: ATUADOR PEDAL | AN1: CILINDRO MESTRE | AO1: ATUADOR CAMBIO | AP1: TAMPA RESERVATORIO | AQ1: CAIXA DE DIREÇÃO | AR1: TUBO TBI | AS1: MANGUEIRA INFERIOR DO RADIADOR | AT1: RECONDICIONAMENTO TURBINA | AU1: INTERCOOLER | AV1: RETROVISOR | AW1: RADIADOR | AX1: OLEO CAMBIO 75 W 80 | AY1: EMBREAGEM
A2: 45727 | B2: 25 | C2: 25 | D2: 25 | E2: 100 | F2: 20 | G2: 7 | H2: 20 | I2: 10 | J2: 10 | K2: 28 | L2: 4 | M2: 2 | N2: 15 | O2: 2 | P2: 0 | Q2: 2 | R2: 20 | S2: 20 | T2: 20 | U2: 20 | V2: 2 | W2: 2 | X2: 6 | Y2: 6 | Z2: 6 | AA2: 6 | AB2: 3 | AC2: 2 | AD2: 2 | AE2: 2 | AF2: 2 | AG2: 0 | AH2: 1 | AI2: 0 | AJ2: 5 | AK2: 4 | AL2: 6 | AM2: 5 | AN2: 0 | AO2: 2 | AP2: 3 | AQ2: 3 | AR2: 3 | AS2: 3 | AT2: 0 | AU2: 2 | AV2: 0 | AW2: 0 | AX2: 24 | AY2: 0
A3: 45727 | B3: 1 | C3: 1 | D3: 1 | E3: 8 | F3: 0 | G3: 0 | H3: 1 | I3: 0 | J3: 0 | K3: 1 | L3: 1 | M3: 0 | N3: 0 | O3: 1 | P3: 0 | Q3: 1 | R3: 0 | S3: 0 | T3: 0 | U3: 0 | V3: 0 | W3: 0 | X3: 0 | Y3: 0 | Z3: 0 | AA3: 0 | AB3: 0 | AC3: 0 | AD3: 0 | AE3: 0 | AF3: 0 | AG3: 0 | AH3: 0 | AI3: 0 | AJ3: 0 | AK3: 0 | AL3: 0 | AM3: 0 | AN3: 0 | AO3: 0 | AP3: 0 | AQ3: 0 | AR3: 0 | AS3: 0 | AT3: 0 | AU3: 0 | AV3: 0 | AW3: 0 | AX3: 0 | AY3: 0
A4: 45728 | B4: 0 | C4: 1 | D4: 1 | E4: 8 | F4: 0 | G4: 1 | H4: 0 | I4: 0 | J4: 0 | K4: 0 | L4: 0 | M4: 0 | N4: 0 | O4: 0 | P4: 0 | Q4: 0 | R4: 0 | S4: 0 | T4: 0 | U4: 0 | V4: 0 | W4: 0 | X4: 0 | Y4: 0 | Z4: 0 | AA4: 0 | AB4: 0 | AC4: 0 | AD4: 0 | AE4: 0 | AF4: 0 | AG4: 0 | AH4: 0 | AI4: 0 | AJ4: 0 | AK4: 0 | AL4: 0 | AM4: 0 | AN4: 0 | AO4: 0 | AP4: 0 | AQ4: 0 | AR4: 0 | AS4: 0 | AT4: 0 | AU4: 0 | AV4: 0 | AW4: 0 | AX4: 0 | AY4: 0
A5: 45729 | B5: 0 | C5: 0 | D5: 0 | E5: 0 | F5: 1 | G5: 0 | H5: 1 | I5: 0 | J5: 0 | K5: 0 | L5: 0 | M5: 0 | N5: 1 | O5: 0 | P5: 0 | Q5: 0 | R5: 0 | V5: 0 | W5: 0 | X5: 0 | Y5: 0 | Z5: 0 | AA5: 0 | AB5: 0 | AC5: 0 | AD5: 0 | AE5: 0 | AF5: 0 | AG5: 0 | AH5: 0 | AI5: 0 | AJ5: 2 | AK5: 0 | AL5: 2 | AM5: 0 | AN5: 0 | AO5: 0 | AP5: 0 | AQ5: 0 | AR5: 0 | AS5: 0 | AT5: 0 | AU5: 0 | AV5: 0 | AW5: 0 | AX5: 0 | AY5: 0
A6: 45730 | B6: 1 | C6: 0 | D6: 0 | E6: 4 | F6: 0 | G6: 0 | H6: 0 | I6: 0 | J6: 0 | K6: 0 | L6: 0 | M6: 0 | N6: 0 | O6: 0 | P6: 0 | Q6: 0 | R6: 0 | S6: 0 | T6: 0 | U6: 0 | V6: 0 | W6: 0 | X6: 0 | Y6: 0 | Z6: 0 | AA6: 0 | AB6: 0 | AC6: 1 | AE6: 0 | AF6: 0 | AG6: 0 | AH6: 0 | AI6: 0 | AJ6: 0 | AK6: 0 | AL6: 0 | AM6: 0 | AN6: 0 | AO6: 0 | AP6: 0 | AQ6: 0 | AR6: 0 | AS6: 0 | AT6: 0 | AU6: 0 | AV6: 0 | AW6: 0 | AX6: 0 | AY6: 0
A7: 45733 | B7: 0 | C7: 0 | D7: 0 | E7: 0 | F7: 0 | G7: 0 | H7: 0 | I7: 0 | J7: 0 | K7: 0 | L7: 0 | M7: 0 | N7: 0 | O7: 0 | P7: 0 | Q7: 0 | R7: 0 | S7: 0 | T7: 0 | U7: 0 | V7: 0 | W7: 0 | X7: 0 | Y7: 0 | Z7: 0 | AA7: 0 | AB7: 0 | AC7: 0 | AD7: 0 | AE7: 0 | AF7: 0 | AG7: 0 | AH7: 0 | AI7: 0 | AJ7: 0 | AK7: 0 | AL7: 0 | AM7: 0 | AN7: 0 | AO7: 0 | AP7: 1 | AQ7: 0 | AR7: 0 | AS7: 0 | AT7: 0 | AU7: 0 | AV7: 0 | AW7: 0 | AX7: 0 | AY7: 0
A8: 45733 | B8: 0 | C8: 0 | E8: 0 | F8: 0 | G8: 0 | H8: 1 | I8: 0 | J8: 1 | K8: 1 | L8: 0 | M8: 0 | N8: 2 | O8: 0 | P8: 0 | Q8: 0 | R8: 0 | S8: 0 | T8: 0 | U8: 0 | V8: 0 | W8: 0 | X8: 1 | Y8: 1 | Z8: 1 | AA8: 2 | AB8: 0 | AC8: 0 | AD8: 1 | AE8: 1 | AF8: 0 | AG8: 0 | AH8: 0 | AI8: 0 | AJ8: 0 | AK8: 0 | AL8: 0 | AM8: 0 | AN8: 0 | AO8: 0 | AP8: 0 | AQ8: 1 | AR8: 1 | AS8: 0 | AT8: 0 | AU8: 1 | AV8: 0 | AW8: 0 | AX8: 0 | AY8: 0
A9: 45733 | B9: 0 | C9: 0 | D9: 0 | E9: 0 | F9: 0 | G9: 0 | H9: 0 | I9: 0 | J9: 0 | K9: 0 | L9: 0 | M9: 0 | N9: 0 | O9: 0 | P9: 0 | Q9: 0 | R9: 0 | S9: 0 | T9: 0 | U9: 0 | V9: 0 | W9: 0 | X9: 0 | Y9: 0 | Z9: 0 | AA9: 0 | AB9: 0 | AC9: 0 | AD9: 0 | AE9: 0 | AF9: 0 | AG9: 0 | AH9: 0 | AI9: 0 | AJ9: 0 | AK9: 0 | AL9: 0 | AM9: 0 | AN9: 0 | AO9: 0 | AP9: 0 | AR9: 1 | AS9: 0 | AT9: 1 | AU9: 0 | AV9: 0 | AX9: 0 | AY9: 0
A10: 45735 | B10: 0 | C10: 0 | D10: 0 | E10: 0 | F10: 0 | G10: 0 | H10: 0 | I10: 0 | J10: 0 | K10: 0 | L10: 0 | M10: 0 | N10: 0 | O10: 0 | P10: 0 | Q10: 0 | R10: 0 | S10: 0 | T10: 0 | U10: 0 | V10: 0 | W10: 0 | X10: 0 | Y10: 0 | Z10: 0 | AA10: 0 | AB10: 0 | AC10: 0 | AD10: 0 | AE10: 0 | AF10: 0 | AG10: 0 | AH10: 0 | AI10: 0 | AJ10: 0 | AK10: 0 | AL10: 0 | AM10: 0 | AN10: 0 | AO10: 0 | AP10: 0 | AQ10: 0 | AR10: 1 | AS10: 0 | AT10: 0 | AU10: 0 | AV10: 0 | AW10: 0 | AX10: 0 | AY10: 0
A11: 45736 | B11: 1 | C11: 1 | D11: 1 | E11: 8 | F11: 0 | G11: 0 | H11: 1 | I11: 2 | J11: 2 | K11: 0 | L11: 0 | M11: 0 | N11: 2 | O11: 0 | P11: 0 | Q11: 1 | R11: 0 | S11: 0 | T11: 0 | U11: 0 | V11: 0 | W11: 0 | X11: 2 | Y11: 0 | Z11: 0 | AA11: 0 | AB11: 0 | AC11: 0 | AD11: 0 | AE11: 0 | AF11: 0 | AG11: 2 | AH11: 0 | AI11: 0 | AJ11: 0 | AK11: 0 | AL11: 0 | AM11: 0 | AN11: 0 | AO11: 0 | AP11: 0 | AQ11: 0 | AR11: 0 | AS11: 1 | AT11: 0 | AU11: 1 | AV11: 0 | AW11: 0 | AX11: 0 | AY11: 0
A12: 45736 | B12: 1 | C12: 1 | D12: 1 | E12: 8 | F12: 0 | G12: 1 | H12: 1 | I12: 0 | J12: 1 | K12: 0 | L12: 0 | M12: 0 | N12: 0 | O12: 0 | P12: 0 | Q12: 0 | R12: 0 | S12: 0 | T12: 0 | U12: 0 | V12: 1 | W12: 1 | X12: 0 | Y12: 0 | Z12: 0 | AA12: 0 | AB12: 0 | AC12: 0 | AD12: 0 | AE12: 0 | AF12: 0 | AG12: 0 | AH12: 0 | AI12: 0 | AJ12: 1 | AK12: 0 | AL12: 0 | AM12: 0 | AN12: 0 | AO12: 0 | AP12: 0 | AQ12: 0 | AR12: 0 | AS12: 0 | AT12: 0 | AU12: 0 | AV12: 0 | AW12: 0 | AX12: 0 | AY12: 0
A13: 45737 | B13: 1 | C13: 1 | D13: 1 | E13: 8 | F13: 1 | G13: 0 | H13: 1 | I13: 0 | J13: 0 | K13: 0 | L13: 0 | M13: 0 | N13: 0 | O13: 0 | P13: 0 | Q13: 0 | R13: 0 | S13: 0 | T13: 0 | U13: 0 | V13: 0 | W13: 0 | X13: 0 | Y13: 0 | Z13: 0+ | AA13: 0 | AB13: 0 | AC13: 0 | AD13: 0 | AE13: 0 | AF13: 0 | AG13: 0 | AH13: 1 | AI13: 0 | AJ13: 0 | AK13: 0 | AL13: 0 | AM13: 0 | AN13: 0 | AO13: 0 | AP13: 0 | AQ13: 0 | AR13: 0 | AS13: 0 | AT13: 0 | AU13: 0 | AV13: 0 | AW13: 0 | AX13: 0 | AY13: 0
A14: 45737 | B14: 1 | C14: 1 | D14: 1 | E14: 8 | F14: 1 | G14: 0 | H14: 1 | I14: 1 | J14: 1 | K14: 0 | L14: 0 | M14: 0 | N14: 0 | O14: 0 | P14: 0 | Q14: 0 | R14: 0 | S14: 0 | T14: 0 | U14: 0 | V14: 0 | W14: 0 | X14: 0 | Y14: 0 | Z14: 0 | AA14: 0 | AB14: 0 | AC14: 0 | AD14: 0 | AE14: 0 | AF14: 0 | AG14: 0 | AH14: 0 | AI14: 0 | AJ14: 0 | AK14: 0 | AL14: 0 | AM14: 0 | AN14: 0 | AO14: 0 | AP14: 0 | AQ14: 0 | AR14: 0 | AS14: 0 | AT14: 0 | AU14: 0 | AV14: 0 | AW14: 0 | AX14: 0 | AY14: 0
A15: 45740 | B15: 0 | C15: 0 | D15: 0 | E15: 0 | F15: 0 | G15: 0 | H15: 0 | I15: 0 | J15: 0 | K15: 0 | L15: 0 | M15: 0 | N15: 0 | O15: 0 | P15: 0 | Q15: 0 | R15: 0 | S15: 0 | T15: 0 | U15: 0 | V15: 0 | W15: 0 | X15: 1 | Y15: 0 | Z15: 0 | AA15: 0 | AB15: 0 | AC15: 0 | AD15: 0 | AE15: 0 | AF15: 0 | AG15: 0 | AH15: 0 | AI15: 0 | AJ15: 0 | AK15: 0 | AL15: 0 | AM15: 0 | AN15: 0 | AP15: 0 | AQ15: 0 | AR15: 0 | AS15: 0 | AT15: 0 | AV15: 0 | AW15: 0 | AX15: 0 | AY15: 0
A16: 45740 | B16: 0 | C16: 0 | D16: 0 | E16: 0 | F16: 0 | G16: 0 | H16: 0 | I16: 0 | J16: 0 | K16: 0 | L16: 1 | M16: 0 | N16: 0 | O16: 0 | P16: 0 | Q16: 0 | R16: 0 | S16: 0 | T16: 0 | U16: 0 | V16: 0 | W16: 0 | X16: 0 | Y16: 0 | Z16: 0 | AA16: 0 | AB16: 1 | AC16: 0 | AD16: 0 | AE16: 0 | AF16: 0 | AG16: 0 | AH16: 0 | AI16: 0 | AJ16: 0 | AK16: 0 | AL16: 0 | AM16: 0 | AN16: 0 | AO16: 0 | AP16: 0 | AQ16: 0 | AR16: 0 | AS16: 0 | AT16: 0 | AU16: 0 | AV16: 0 | AW16: 0 | AX16: 0 | AY16: 0
A17: 45740 | B17: 0 | C17: 0 | D17: 0 | E17: 0 | F17: 0 | G17: 0 | H17: 0 | I17: 0 | J17: 0 | K17: 0 | L17: 0 | M17: 0 | N17: 0 | O17: 0 | P17: 0 | Q17: 0 | R17: 0 | S17: 0 | T17: 0 | U17: 0 | V17: 0 | W17: 0 | X17: 0 | Y17: 0 | Z17: 0 | AA17: 0 | AB17: 0 | AC17: 0 | AD17: 0 | AE17: 0 | AF17: 0 | AG17: 0 | AH17: 0 | AI17: 1 | AJ17: 0 | AK17: 0 | AL17: 0 | AM17: 0 | AN17: 0 | AO17: 0 | AP17: 0 | AQ17: 0 | AR17: 0 | AS17: 0 | AT17: 0 | AU17: 0 | AV17: 0 | AW17: 0 | AX17: 0 | AY17: 0
A18: 45742 | B18: 0 | C18: 1 | D18: 1 | E18: 8 | F18: 0 | G18: 1 | H18: 1 | I18: 0 | J18: 0 | K18: 0 | L18: 0 | M18: 0 | N18: 0 | O18: 0 | P18: 0 | Q18: 0 | R18: 0 | S18: 0 | T18: 0 | U18: 0 | V18: 1 | W18: 0 | X18: 1 | Y18: 0 | Z18: 0 | AA18: 0 | AB18: 0 | AC18: 0 | AD18: 0 | AE18: 0 | AF18: 0 | AG18: 0 | AH18: 0 | AI18: 0 | AJ18: 0 | AK18: 0 | AL18: 0 | AM18: 0 | AN18: 0 | AO18: 0 | AP18: 0 | AQ18: 0 | AR18: 0 | AS18: 0 | AT18: 0 | AU18: 0 | AV18: 0 | AW18: 0 | AX18: 3 | AY18: 0
A19: 45743 | B19: 0 | C19: 0 | D19: 0 | E19: 0 | F19: 0 | G19: 0 | H19: 0 | I19: 0 | J19: 0 | K19: 0 | L19: 0 | M19: 0 | N19: 0 | O19: 1 | P19: 0 | Q19: 0 | R19: 0 | S19: 0 | T19: 0 | U19: 0 | V19: 0 | W19: 0 | X19: 0 | Y19: 0 | Z19: 0 | AA19: 0 | AB19: 0 | AC19: 0 | AD19: 0 | AE19: 0 | AF19: 0 | AG19: 0 | AH19: 0 | AI19: 0 | AJ19: 0 | AK19: 0 | AL19: 0 | AM19: 0 | AN19: 0 | AO19: 0 | AP19: 0 | AQ19: 0 | AR19: 0 | AS19: 0 | AT19: 0 | AU19: 0 | AV19: 0 | AW19: 0 | AX19: 0 | AY19: 0
A20: 45744 | B20: 1 | C20: 1 | D20: 1 | E20: 8 | F20: 0 | G20: 0 | H20: 0 | I20: 0 | J20: 0 | K20: 0 | L20: 0 | M20: 0 | N20: 0 | O20: 0 | P20: 0 | Q20: 0 | R20: 0 | S20: 0 | T20: 0 | U20: 0 | V20: 0 | W20: 0 | X20: 0 | Y20: 0 | Z20: 0 | AA20: 0 | AB20: 0 | AC20: 0 | AD20: 0 | AE20: 0 | AF20: 0 | AG20: 0 | AH20: 0 | AI20: 0 | AJ20: 0 | AK20: 0 | AL20: 0 | AM20: 0 | AN20: 0 | AO20: 0 | AP20: 0 | AQ20: 0 | AR20: 0 | AS20: 0 | AT20: 0 | AU20: 0 | AV20: 0 | AW20: 0 | AX20: 0 | AY20: 0
A21: 45744 | B21: 1 | C21: 1 | D21: 1 | E21: 8 | F21: 1 | G21: 0 | H21: 1 | I21: 0 | J21: 1 | K21: 0 | L21: 0 | M21: 0 | N21: 0 | O21: 0 | P21: 0 | Q21: 0 | R21: 0 | S21: 0 | T21: 0 | U21: 0 | V21: 0 | W21: 0 | X21: 0 | Y21: 0 | Z21: 0 | AA21: 0 | AB21: 0 | AC21: 0 | AD21: 0 | AE21: 0 | AF21: 0 | AG21: 0 | AH21: 0 | AI21: 0 | AJ21: 0 | AK21: 0 | AL21: 0 | AM21: 0 | AN21: 0 | AO21: 0 | AP21: 0 | AQ21: 0 | AR21: 0 | AS21: 0 | AT21: 0 | AU21: 0 | AV21: 0 | AW21: 0 | AX21: 0 | AY21: 0
A22: 45744 | B22: 0 | C22: 0 | D22: 0 | E22: 0 | F22: 0 | G22: 0 | H22: 0 | I22: 0 | J22: 0 | K22: 0 | L22: 0 | M22: 0 | N22: 0 | O22: 0 | P22: 0 | Q22: 0 | R22: 0 | S22: 0 | T22: 0 | U22: 0 | V22: 0 | W22: 0 | X22: 0 | Y22: 0 | Z22: 0 | AA22: 0 | AB22: 1 | AC22: 0 | AD22: 0 | AE22: 0 | AF22: 0 | AG22: 0 | AH22: 0 | AI22: 0 | AJ22: 0 | AK22: 0 | AL22: 0 | AM22: 0 | AN22: 0 | AO22: 0 | AP22: 0 | AQ22: 0 | AR22: 0 | AS22: 0 | AT22: 0 | AU22: 0 | AV22: 0 | AW22: 0 | AX22: 0 | AY22: 0
A23: 45748 | B23: 0 | C23: 1 | D23: 1 | E23: 8 | F23: 0 | G23: 1 | H23: 0 | I23: 0 | J23: 0 | K23: 0 | L23: 0 | M23: 0 | N23: 0 | O23: 0 | P23: 0 | Q23: 0 | R23: 0 | S23: 0 | T23: 0 | U23: 0 | V23: 0 | W23: 0 | X23: 0 | Y23: 1 | Z23: 0 | AA23: 0 | AB23: 0 | AC23: 0 | AD23: 0 | AE23: 0 | AF23: 0 | AG23: 0 | AI23: 0 | AJ23: 0 | AK23: 0 | AL23: 0 | AM23: 0 | AN23: 0 | AO23: 0 | AP23: 0 | AQ23: 0 | AR23: 0 | AS23: 0 | AT23: 0 | AU23: 0 | AV23: 0 | AW23: 0 | AX23: 0 | AY23: 0
A24: 45749 | B24: 0 | C24: 0 | D24: 0 | E24: 0 | F24: 0 | G24: 0 | H24: 0 | I24: 0 | J24: 0 | K24: 0 | L24: 1 | M24: 0 | N24: 0 | O24: 0 | P24: 0 | Q24: 0 | R24: 0 | S24: 0 | T24: 0 | U24: 0 | V24: 0 | W24: 0 | X24: 0 | Y24: 0 | Z24: 0 | AA24: 0 | AB24: 0 | AC24: 0 | AD24: 0 | AE24: 0 | AF24: 1 | AG24: 1 | AH24: 0 | AI24: 0 | AJ24: 0 | AK24: 0 | AL24: 0 | AM24: 0 | AN24: 0 | AO24: 0 | AP24: 0 | AQ24: 0 | AR24: 0 | AS24: 0 | AT24: 0 | AU24: 0 | AV24: 1 | AW24: 0 | AX24: 0 | AY24: 1
A25: 45749 | B25: 0 | C25: 0 | D25: 0 | E25: 0 | F25: 0 | G25: 0 | H25: 0 | I25: 0 | J25: 0 | K25: 0 | L25: 0 | M25: 0 | N25: 0 | O25: 0 | P25: 0 | Q25: 0 | R25: 0 | S25: 0 | T25: 0 | U25: 0 | V25: 0 | W25: 0 | X25: 0 | Y25: 0 | Z25: 0 | AA25: 0 | AB25: 0 | AC25: 0 | AD25: 0 | AE25: 0 | AF25: 0 | AG25: 0 | AH25: 0 | AI25: 0 | AJ25: 0 | AK25: 0 | AL25: 0 | AM25: 0 | AN25: 1 | AO25: 1 | AP25: 0 | AQ25: 0 | AR25: 0 | AS25: 0 | AT25: 0 | AU25: 0 | AV25: 0 | AW25: 0 | AX25: 0 | AY25: 0
A26: 45749 | B26: 0 | C26: 0 | D26: 0 | E26: 0 | F26: 1 | G26: 0 | H26: 1 | I26: 1 | J26: 1 | K26: 0 | L26: 0 | M26: 0 | N26: 0 | O26: 0 | P26: 0 | Q26: 0 | R26: 0 | S26: 0 | T26: 0 | U26: 0 | V26: 1 | W26: 0 | X26: 0 | Y26: 0 | Z26: 0 | AA26: 0 | AB26: 0 | AC26: 0 | AD26: 0 | AE26: 0 | AF26: 0 | AG26: 0 | AH26: 0 | AI26: 0 | AJ26: 0 | AK26: 0 | AL26: 0 | AM26: 0 | AN26: 0 | AO26: 0 | AP26: 0 | AQ26: 0 | AR26: 0 | AS26: 0 | AT26: 0 | AU26: 0 | AV26: 0 | AW26: 0 | AX26: 0 | AY26: 0
A27: 45751 | B27: 1 | C27: 0 | D27: 0 | E27: 0 | F27: 0 | G27: 0 | H27: 0 | I27: 0 | J27: 0 | K27: 0 | L27: 0 | M27: 0 | N27: 0 | O27: 0 | P27: 0 | Q27: 0 | R27: 0 | S27: 0 | T27: 0 | U27: 0 | V27: 0 | W27: 0 | X27: 0 | Y27: 0 | Z27: 0 | AA27: 0 | AB27: 0 | AC27: 0 | AD27: 0 | AE27: 0 | AF27: 0 | AG27: 0 | AH27: 0 | AI27: 0 | AJ27: 0 | AK27: 0 | AL27: 0 | AM27: 0 | AN27: 0 | AO27: 0 | AP27: 0 | AQ27: 0 | AR27: 0 | AS27: 0 | AT27: 0 | AU27: 0 | AV27: 0 | AW27: 0 | AX27: 0 | AY27: 0
A28: 45754 | B28: 0 | C28: 1 | D28: 1 | E28: 8 | F28: 0 | G28: 1 | H28: 0 | I28: 0 | J28: 0 | K28: 0 | L28: 0 | M28: 0 | N28: 0 | O28: 0 | P28: 0 | Q28: 0 | R28: 0 | S28: 0 | T28: 0 | U28: 0 | V28: 0 | W28: 0 | X28: 0 | Y28: 0 | Z28: 0 | AA28: 0 | AB28: 0 | AC28: 0 | AD28: 0 | AE28: 0 | AF28: 0 | AG28: 0 | AH28: 0 | AI28: 0 | AJ28: 0 | AK28: 0 | AL28: 0 | AM28: 0 | AN28: 0 | AO28: 0 | AP28: 0 | AQ28: 0 | AR28: 0 | AS28: 0 | AT28: 0 | AU28: 0 | AV28: 0 | AW28: 0 | AX28: 0 | AY28: 0
A29: 45754 | B29: 0 | C29: 0 | D29: 0 | E29: 0 | F29: 1 | G29: 0 | H29: 1 | I29: 1 | J29: 1 | K29: 0 | L29: 0 | M29: 0 | N29: 0 | O29: 0 | P29: 0 | Q29: 0 | R29: 0 | S29: 0 | T29: 0 | U29: 0 | V29: 0 | W29: 0 | X29: 0 | Y29: 0 | Z29: 0 | AA29: 0 | AB29: 0 | AC29: 0 | AD29: 0 | AE29: 0 | AF29: 0 | AG29: 0 | AH29: 0 | AI29: 0 | AJ29: 1 | AK29: 1 | AL29: 0 | AM29: 0 | AN29: 0 | AO29: 0 | AP29: 0 | AQ29: 0 | AR29: 0 | AS29: 0 | AT29: 1 | AU29: 0 | AV29: 0 | AW29: 0 | AX29: 0 | AY29: 0
A30: 45761 | B30: 1 | C30: 1 | D30: 1 | E30: 8 | F30: 0 | G30: 0 | H30: 0 | I30: 0 | J30: 0 | K30: 0 | L30: 0 | M30: 0 | N30: 0 | O30: 0 | P30: 0 | Q30: 0 | R30: 0 | S30: 0 | T30: 0 | U30: 0 | V30: 0 | W30: 0 | X30: 0 | Y30: 0 | Z30: 0 | AA30: 0 | AB30: 0 | AC30: 0 | AD30: 0 | AE30: 0 | AF30: 0 | AG30: 0 | AH30: 0 | AI30: 0 | AJ30: 0 | AK30: 0 | AL30: 0 | AM30: 0 | AN30: 0 | AO30: 0 | AP30: 0 | AQ30: 0 | AR30: 0 | AS30: 0 | AT30: 0 | AU30: 0 | AV30: 0 | AW30: 0 | AX30: 0 | AY30: 0
A31: 45761 | B31: 1 | C31: 1 | D31: 1 | E31: 8 | F31: 0 | G31: 0 | H31: 0 | I31: 0 | J31: 0 | K31: 0 | L31: 0 | M31: 0 | N31: 0 | O31: 0 | P31: 0 | Q31: 0 | R31: 0 | S31: 0 | T31: 0 | U31: 0 | V31: 0 | W31: 0 | X31: 0 | Y31: 0 | Z31: 0 | AA31: 0 | AB31: 0 | AC31: 0 | AD31: 0 | AE31: 0 | AF31: 0 | AG31: 0 | AH31: 0 | AI31: 0 | AJ31: 0 | AK31: 0 | AL31: 0 | AM31: 0 | AN31: 0 | AO31: 0 | AP31: 0 | AQ31: 0 | AR31: 0 | AS31: 0 | AT31: 0 | AU31: 0 | AV31: 0 | AW31: 0 | AX31: 0 | AY31: 0
A32: 45761 | B32: 0 | C32: 0 | D32: 0 | E32: 0 | F32: 0 | G32: 1 | H32: 0 | I32: 0 | J32: 0 | K32: 0 | L32: 0 | M32: 0 | N32: 0 | O32: 0 | P32: 0 | Q32: 0 | R32: 0 | T32: 0 | U32: 0 | V32: 0 | W32: 0 | X32: 0 | Y32: 0 | Z32: 0 | AA32: 0 | AB32: 0 | AC32: 0 | AD32: 0 | AE32: 0 | AF32: 0 | AG32: 0 | AH32: 0 | AI32: 0 | AJ32: 0 | AK32: 0 | AL32: 0 | AM32: 0 | AN32: 0 | AO32: 0 | AP32: 0 | AQ32: 0 | AR32: 0 | AS32: 0 | AT32: 0 | AU32: 0 | AV32: 0 | AW32: 0 | AX32: 0 | AY32: 0
A33: 45761 | B33: 1 | C33: 1 | D33: 1 | E33: 8 | F33: 0 | G33: 0 | H33: 0 | I33: 0 | J33: 0 | K33: 0 | L33: 0 | M33: 0 | N33: 0 | O33: 0 | P33: 0 | Q33: 0 | R33: 0 | S33: 0 | T33: 0 | U33: 0 | V33: 0 | W33: 0 | X33: 0 | Y33: 0 | Z33: 0 | AA33: 0 | AB33: 0 | AC33: 0 | AD33: 0 | AE33: 0 | AF33: 0 | AG33: 0 | AH33: 0 | AI33: 0 | AJ33: 0 | AK33: 0 | AL33: 0 | AM33: 0 | AN33: 0 | AO33: 0 | AP33: 0 | AQ33: 0 | AR33: 0 | AS33: 0 | AT33: 0 | AU33: 0 | AV33: 0 | AW33: 0 | AX33: 0 | AY33: 0
A34: 45761 | B34: 0 | C34: 0 | D34: 0 | E34: 0 | F34: 0 | G34: 0 | H34: 0 | I34: 0 | J34: 0 | K34: 0 | L34: 0 | N34: 0 | O34: 0 | P34: 0 | Q34: 0 | R34: 0 | S34: 0 | T34: 0 | V34: 0 | W34: 0 | X34: 0 | Y34: 0 | Z34: 0 | AA34: 0 | AB34: 0 | AC34: 0 | AD34: 0 | AE34: 0 | AF34: 0 | AG34: 0 | AH34: 0 | AI34: 0 | AJ34: 0 | AK34: 0 | AL34: 0 | AM34: 0 | AN34: 0 | AO34: 0 | AP34: 0 | AQ34: 0 | AR34: 0 | AS34: 0 | AT34: 1 | AU34: 0 | AV34: 0 | AW34: 0 | AX34: 0 | AY34: 0
A35: 45761 | B35: 1 | C35: 1 | D35: 0 | E35: 0 | F35: 0 | G35: 0 | H35: 0 | I35: 0 | J35: 0 | K35: 0 | L35: 0 | M35: 0 | N35: 0 | O35: 0 | P35: 0 | Q35: 0 | R35: 0 | S35: 0 | T35: 0 | U35: 0 | V35: 0 | W35: 0 | X35: 0 | Y35: 0 | Z35: 0 | AA35: 0 | AB35: 0 | AC35: 0 | AD35: 0 | AE35: 0 | AF35: 0 | AG35: 0 | AH35: 0 | AI35: 0 | AJ35: 0 | AK35: 0 | AL35: 0 | AM35: 0 | AN35: 0 | AO35: 0 | AP35: 0 | AQ35: 0 | AR35: 0 | AS35: 1 | AT35: 0 | AU35: 0 | AV35: 0 | AW35: 0 | AX35: 0 | AY35: 0
A36: 45762 | B36: 0 | C36: 1 | D36: 1 | E36: 8 | F36: 1 | G36: 1 | H36: 1 | I36: 1 | J36: 0 | K36: 0 | L36: 0 | M36: 0 | N36: 0 | O36: 0 | P36: 0 | Q36: 0 | R36: 0 | S36: 0 | T36: 0 | U36: 0 | V36: 0 | W36: 0 | X36: 0 | Y36: 0 | Z36: 0 | AA36: 0 | AB36: 0 | AC36: 0 | AD36: 0 | AE36: 0 | AF36: 0 | AG36: 0 | AH36: 0 | AI36: 0 | AJ36: 0 | AK36: 0 | AL36: 0 | AM36: 0 | AN36: 0 | AO36: 0 | AP36: 0 | AQ36: 0 | AR36: 0 | AS36: 0 | AT36: 0 | AU36: 0 | AV36: 0 | AW36: 0 | AX36: 0 | AY36: 0

Sheet Dados
A1: Coluna1
C3: oficina em debito | D3: Atendimento | E3: Placa | F3: Modelo | G3: km | H3: Relato | I3: Data Agenda | J3: Focal | K3: Reparo | L3: Tipo de Manutenção | M3: Aprovação | N3: Valor do Orçamento | O3: Valor Negociado | P3: Centro de Custo | Q3: Operação | R3: Status | S3: Previsão | T3: Liberado | U3: D+Manut | V3: Status2 | W3: Oficina | X3: Lider Base | Y3: Mês | Z3: Base
E4: SGK7D70 | F4: =IFERROR(VLOOKUP(Tabela1[[#This Row],[Placa]],'Base Cadastro '!A:B,2,FALSE),"Correção de cadastro") -> TRANSIT FURGÃO | H4: Funilaria dianteira total | I4: 45708 | J4: Vinicius | K4: Sinistro | L4: Corretiva | M4: Aprovado | N4: 22000 | O4: 22000 | P4: =VLOOKUP(Tabela1[[#This Row],[Placa]],'Base Cadastro '!A:M,13,FALSE) -> SSP8 | Q4: MERCADO LIVRE | R4: Sinistro | S4: 45974 | U4: =IFERROR(DATEDIF(Tabela1[[#This Row],[Data Agenda]],Tabela1[[#This Row],[Liberado]],"D"),DATEDIF(Tabela1[[#This Row],[Data Agenda]],TODAY(),"D")) -> 270 | V4: =IF(Tabela1[[#This Row],[D+Manut]]<=2,"Dentro do Prazo","Fora do Prazo") -> Fora do Prazo | W4: GR Car | X4: Gabriela | Y4: Fev | Z4: =VLOOKUP(Tabela1[[#This Row],[Placa]],DadosViagem5[[Placa]:[Base]],11,FALSE) -> SC (SAO JOSE DOS CAMPOS) SSP8
E5: SDT9G04 | F5: =IFERROR(VLOOKUP(Tabela1[[#This Row],[Placa]],'Base Cadastro '!A:B,2,FALSE),"Correção de cadastro") -> E-Jumpy Furgão 2P | G5: 34254 | H5: Funilaria lateral esquerda traseira. | I5: 45736 | J5: Vinicius | K5: Sinistro | L5: Corretiva | M5: Aprovado | N5: 19364.98 | O5: 19364.98 | P5: =VLOOKUP(Tabela1[[#This Row],[Placa]],'Base Cadastro '!A:M,13,FALSE) -> SRS1 | Q5: MERCADO LIVRE | R5: Sinistro | S5: 45974 | U5: 197 | V5: =IF(Tabela1[[#This Row],[D+Manut]]<=2,"Dentro do Prazo","Fora do Prazo") -> Fora do Prazo | W5: Safety Car | X5: ALESSANDRA | Y5: Set | Z5: =VLOOKUP(Tabela1[[#This Row],[Placa]],DadosViagem5[[Placa]:[Base]],11,FALSE) -> SC (PORTO ALEGRE) SRS1
A6: 0 | E6: RTM6B63 | F6: =IFERROR(VLOOKUP(Tabela1[[#This Row],[Placa]],'Base Cadastro '!A:B,2,FALSE),"Correção de cadastro") -> Master Furgão 8m³ | G6: N/E | H6: Veículo sofreu uma colisão no baú | I6: 45848 | J6: Vinicius | K6: Sinistro | L6: Corretiva | M6: Aprovado | P6: =VLOOKUP(Tabela1[[#This Row],[Placa]],'Base Cadastro '!A:M,13,FALSE) -> SRS1 | Q6: MERCADO LIVRE | R6: Sinistro | S6: Aguardando aprovação | U6: =IFERROR(DATEDIF(Tabela1[[#This Row],[Data Agenda]],Tabela1[[#This Row],[Liberado]],"D"),DATEDIF(Tabela1[[#This Row],[Data Agenda]],TODAY(),"D")) -> 130 | V6: =IF(Tabela1[[#This Row],[D+Manut]]<=2,"Dentro do Prazo","Fora do Prazo") -> Fora do Prazo | W6: Safety Car | Y6: Set | Z6: =VLOOKUP(Tabela1[[#This Row],[Placa]],DadosViagem5[[Placa]:[Base]],11,FALSE) -> SC (PORTO ALEGRE) SRS1
E7: FMO8E22 | F7: =IFERROR(VLOOKUP(Tabela1[[#This Row],[Placa]],'Base Cadastro '!A:B,2,FALSE),"Correção de cadastro") -> Partner Rapid Business Pack 1.4 2P | H7: Colisão não informada da base | J7: Vinicius | K7: Sinistro | L7: Corretiva | P7: =VLOOKUP(Tabela1[[#This Row],[Placa]],'Base Cadastro '!A:M,13,FALSE) -> SGO1 | Q7: MERCADO LIVRE | R7: Sinistro | S7: 45980 | U7: =IFERROR(DATEDIF(Tabela1[[#This Row],[Data Agenda]],Tabela1[[#This Row],[Liberado]],"D"),DATEDIF(Tabela1[[#This Row],[Data Agenda]],TODAY(),"D")) -> 0 | V7: =IF(Tabela1[[#This Row],[D+Manut]]<=2,"Dentro do Prazo","Fora do Prazo") -> Dentro do Prazo | W7: Auto reformadora Santos | Y7: Nov | Z7: =VLOOKUP(Tabela1[[#This Row],[Placa]],DadosViagem5[[Placa]:[Base]],11,FALSE) -> #N/A
E8: RUX2J10 | F8: =IFERROR(VLOOKUP(Tabela1[[#This Row],[Placa]],'Base Cadastro '!A:B,2,FALSE),"Correção de cadastro") -> Partner Rapid Business Pack 1.4 2P | G8: 160659 | H8: Veículo sofreu uma colisão e capotamento. | I8: 45879 | J8: Isabelli | K8: Sinistro | L8: Corretiva | M8: Aprovado | N8: 13750 | O8: 13750 | P8: =VLOOKUP(Tabela1[[#This Row],[Placa]],'Base Cadastro '!A:M,13,FALSE) -> SMG5 | Q8: MERCADO LIVRE | R8: Sinistro | S8: Em diagnóstico | U8: =IFERROR(DATEDIF(Tabela1[[#This Row],[Data Agenda]],Tabela1[[#This Row],[Liberado]],"D"),DATEDIF(Tabela1[[#This Row],[Data Agenda]],TODAY(),"D")) -> 99 | V8: =IF(Tabela1[[#This Row],[D+Manut]]<=2,"Dentro do Prazo","Fora do Prazo") -> Fora do Prazo | W8: GR Car | X8: CAMILA | Y8: Ago | Z8: =VLOOKUP(Tabela1[[#This Row],[Placa]],DadosViagem5[[Placa]:[Base]],11,FALSE) -> SC (POÇOS DE CALDAS) SMG5
E9: RVQ2D86 | F9: =IFERROR(VLOOKUP(Tabela1[[#This Row],[Placa]],'Base Cadastro '!A:B,2,FALSE),"Correção de cadastro") -> MASTER FURGAO L1 | G9: N/E | H9: Motor | I9: 45677 | J9: Carla I. | K9: Manutenção | L9: Corretiva | M9: Aprovado | P9: =VLOOKUP(Tabela1[[#This Row],[Placa]],'Base Cadastro '!A:M,13,FALSE) -> SSP16 | Q9: MERCADO LIVRE | R9: Motor | S9: 45978 | U9: =IFERROR(DATEDIF(Tabela1[[#This Row],[Data Agenda]],Tabela1[[#This Row],[Liberado]],"D"),DATEDIF(Tabela1[[#This Row],[Data Agenda]],TODAY(),"D")) -> 301 | V9: =IF(Tabela1[[#This Row],[D+Manut]]<=2,"Dentro do Prazo","Fora do Prazo") -> Fora do Prazo | W9: Estacionamento da Coca/MuriTruck | X9: CAMILA | Y9: Jan | Z9: =VLOOKUP(Tabela1[[#This Row],[Placa]],DadosViagem5[[Placa]:[Base]],11,FALSE) -> SC (CARAGUATATUBA) SSP16
C10: Sim | E10: QPC5I33 | F10: =IFERROR(VLOOKUP(Tabela1[[#This Row],[Placa]],'Base Cadastro '!A:B,2,FALSE),"Correção de cadastro") -> MASTER FURGAO L1 | G10: N/E | H10: Veículo sofreu uma colisão frontal, montando já libera hoje. | I10: 45793 | J10: Isabelli | K10: Sinistro | L10: Corretiva | M10: Aprovado | N10: 5304.2 | O10: 5304.2 | P10: =VLOOKUP(Tabela1[[#This Row],[Placa]],'Base Cadastro '!A:M,13,FALSE) -> SSC3 | Q10: MERCADO LIVRE | R10: Sinistro | S10: 45982 | U10: =IFERROR(DATEDIF(Tabela1[[#This Row],[Data Agenda]],Tabela1[[#This Row],[Liberado]],"D"),DATEDIF(Tabela1[[#This Row],[Data Agenda]],TODAY(),"D")) -> 185 | V10: =IF(Tabela1[[#This Row],[D+Manut]]<=2,"Dentro do Prazo","Fora do Prazo") -> Fora do Prazo | W10: FSP | X10: GABRIELI | Y10: Set | Z10: =VLOOKUP(Tabela1[[#This Row],[Placa]],DadosViagem5[[Placa]:[Base]],11,FALSE) -> SC (BLUMENAU) SSC3
C11: Sim | E11: SVT9G70 | F11: =IFERROR(VLOOKUP(Tabela1[[#This Row],[Placa]],'Base Cadastro '!A:B,2,FALSE),"Correção de cadastro") -> MASTER FURGAO L1 | G11: 47465 | H11: Colisão dianteira grave. Aguardando peça já solicitadas, que chegrarão dia 15/10/2025 | I11: 45820 | J11: Isabelli | K11: Sinistro | L11: Corretiva | M11: Aprovado | N11: 46000 | O11: 29429 | P11: =VLOOKUP(Tabela1[[#This Row],[Placa]],'Base Cadastro '!A:M,13,FALSE) -> EPR6 | Q11: MERCADO LIVRE | R11: Sinistro | S11: 45980 | U11: =IFERROR(DATEDIF(Tabela1[[#This Row],[Data Agenda]],Tabela1[[#This Row],[Liberado]],"D"),DATEDIF(Tabela1[[#This Row],[Data Agenda]],TODAY(),"D")) -> 158 | V11: =IF(Tabela1[[#This Row],[D+Manut]]<=2,"Dentro do Prazo","Fora do Prazo") -> Fora do Prazo | W11: FSP | X11: ALINE | Y11: Set | Z11: =VLOOKUP(Tabela1[[#This Row],[Placa]],DadosViagem5[[Placa]:[Base]],11,FALSE) -> XPT (SAO MATEUS DO SUL) EPR6/SPR7
E12: SGI8I22 | F12: =IFERROR(VLOOKUP(Tabela1[[#This Row],[Placa]],'Base Cadastro '!A:B,2,FALSE),"Correção de cadastro") -> TRANSIT FURGÃO | G12: 24826 | H12: Colisão frontal, efetuando nova cotação na RRW. | I12: 45836 | J12: Vinicius | K12: Sinistro | L12: Corretiva | M12: Aprovado | N12: 5000 | O12: 5000 | P12: =VLOOKUP(Tabela1[[#This Row],[Placa]],'Base Cadastro '!A:M,13,FALSE) -> SSP30 | Q12: MERCADO LIVRE | R12: Sinistro | S12: 45980 | U12: =IFERROR(DATEDIF(Tabela1[[#This Row],[Data Agenda]],Tabela1[[#This Row],[Liberado]],"D"),DATEDIF(Tabela1[[#This Row],[Data Agenda]],TODAY(),"D")) -> 142 | V12: =IF(Tabela1[[#This Row],[D+Manut]]<=2,"Dentro do Prazo","Fora do Prazo") -> Fora do Prazo | W12: Helena Maria | X12: Claudia | Y12: Jun | Z12: =VLOOKUP(Tabela1[[#This Row],[Placa]],DadosViagem5[[Placa]:[Base]],11,FALSE) -> SC (MEGA GUARULHOS) SSP30
E13: SFW2B76 | F13: =IFERROR(VLOOKUP(Tabela1[[#This Row],[Placa]],'Base Cadastro '!A:B,2,FALSE),"Correção de cadastro") -> TRANSIT FURGÃO | G13: 17296 | H13: Colisão traseira, coluna do baú. | I13: 45789 | J13: Vinicius | K13: Sinistro | L13: Corretiva | M13: Aprovado | P13: =VLOOKUP(Tabela1[[#This Row],[Placa]],'Base Cadastro '!A:M,13,FALSE) -> SSC5 | Q13: MERCADO LIVRE | R13: Sinistro | S13: 46019 | U13: =IFERROR(DATEDIF(Tabela1[[#This Row],[Data Agenda]],Tabela1[[#This Row],[Liberado]],"D"),DATEDIF(Tabela1[[#This Row],[Data Agenda]],TODAY(),"D")) -> 189 | V13: =IF(Tabela1[[#This Row],[D+Manut]]<=2,"Dentro do Prazo","Fora do Prazo") -> Fora do Prazo | W13: Safety Car | X13: Alessandra | Y13: Set | Z13: =VLOOKUP(Tabela1[[#This Row],[Placa]],DadosViagem5[[Placa]:[Base]],11,FALSE) -> SC (CRICIUMA) SSC5
C14: Sim | E14: GFB0H75 | F14: =IFERROR(VLOOKUP(Tabela1[[#This Row],[Placa]],'Base Cadastro '!A:B,2,FALSE),"Correção de cadastro") -> Sprinter 313 | G14: 79000 | H14: Aguardando Aprovação serviço de bico injetores | I14: 45681 | J14: Luana | K14: Manutenção | L14: Corretiva | M14: Aprovado | N14: 23000 | O14: 17000 | P14: =VLOOKUP(Tabela1[[#This Row],[Placa]],'Base Cadastro '!A:M,13,FALSE) -> SSP28 | Q14: MERCADO LIVRE | R14: Em Manutenção | S14: 45982 | U14: =IFERROR(DATEDIF(Tabela1[[#This Row],[Data Agenda]],Tabela1[[#This Row],[Liberado]],"D"),DATEDIF(Tabela1[[#This Row],[Data Agenda]],TODAY(),"D")) -> 297 | V14: =IF(Tabela1[[#This Row],[D+Manut]]<=2,"Dentro do Prazo","Fora do Prazo") -> Fora do Prazo | W14: Injemec | X14: JOAO VITOR | Y14: Jan | Z14: =VLOOKUP(Tabela1[[#This Row],[Placa]],DadosViagem5[[Placa]:[Base]],11,FALSE) -> SC (JALES) SSP28
E15: SGH0H20 | F15: =IFERROR(VLOOKUP(Tabela1[[#This Row],[Placa]],'Base Cadastro '!A:B,2,FALSE),"Correção de cadastro") -> TRANSIT FURGÃO | G15: 66248 | H15: Bomba e Bico Injetor | I15: 45943 | J15: Hillary | K15: Manutenção | L15: Corretiva | M15: Aprovado | P15: =VLOOKUP(Tabela1[[#This Row],[Placa]],'Base Cadastro '!A:M,13,FALSE) -> SRS10 | Q15: MERCADO LIVRE | R15: Em Manutenção | S15: 45978 | U15: =IFERROR(DATEDIF(Tabela1[[#This Row],[Data Agenda]],Tabela1[[#This Row],[Liberado]],"D"),DATEDIF(Tabela1[[#This Row],[Data Agenda]],TODAY(),"D")) -> 35 | V15: =IF(Tabela1[[#This Row],[D+Manut]]<=2,"Dentro do Prazo","Fora do Prazo") -> Fora do Prazo | W15: Ford Amazon Novo Hamburgo | X15: FERNANDA | Y15: Out | Z15: =VLOOKUP(Tabela1[[#This Row],[Placa]],DadosViagem5[[Placa]:[Base]],11,FALSE) -> SC (LAJEADO) SRS10
E16: SGH8H56 | F16: =IFERROR(VLOOKUP(Tabela1[[#This Row],[Placa]],'Base Cadastro '!A:B,2,FALSE),"Correção de cadastro") -> TRANSIT FURGÃO | G16: 97608 | H16: Bomba e Bico Injetor | I16: 45943 | J16: Hillary | K16: Manutenção | L16: Corretiva | M16: Aprovado | P16: =VLOOKUP(Tabela1[[#This Row],[Placa]],'Base Cadastro '!A:M,13,FALSE) -> SRS10 | Q16: MERCADO LIVRE | R16: Em Manutenção | S16: 45978 | U16: =IFERROR(DATEDIF(Tabela1[[#This Row],[Data Agenda]],Tabela1[[#This Row],[Liberado]],"D"),DATEDIF(Tabela1[[#This Row],[Data Agenda]],TODAY(),"D")) -> 35 | V16: =IF(Tabela1[[#This Row],[D+Manut]]<=2,"Dentro do Prazo","Fora do Prazo") -> Fora do Prazo | W16: Ford Lajeado | X16: FERNANDA | Y16: Out | Z16: =VLOOKUP(Tabela1[[#This Row],[Placa]],DadosViagem5[[Placa]:[Base]],11,FALSE) -> SC (LAJEADO) SRS10
E17: SFT5A73 | F17: =IFERROR(VLOOKUP(Tabela1[[#This Row],[Placa]],'Base Cadastro '!A:B,2,FALSE),"Correção de cadastro") -> TRANSIT FURGÃO | G17: 55792 | H17: Motorista colidiu a nossa Van em um poste por desatenção | I17: 45933 | J17: Isabelli | K17: Sinistro | L17: Corretiva | M17: Aprovado | N17: 2400 | O17: 2400 | P17: =VLOOKUP(Tabela1[[#This Row],[Placa]],'Base Cadastro '!A:M,13,FALSE) -> SSP22 | Q17: MERCADO LIVRE | R17: Sinistro | S17: 45982 | U17: =IFERROR(DATEDIF(Tabela1[[#This Row],[Data Agenda]],Tabela1[[#This Row],[Liberado]],"D"),DATEDIF(Tabela1[[#This Row],[Data Agenda]],TODAY(),"D")) -> 45 | V17: =IF(Tabela1[[#This Row],[D+Manut]]<=2,"Dentro do Prazo","Fora do Prazo") -> Fora do Prazo | W17: Funilaria Athaide | X17: MAURICIO | Y17: Out | Z17: =VLOOKUP(Tabela1[[#This Row],[Placa]],DadosViagem5[[Placa]:[Base]],11,FALSE) -> SC (SAO CARLOS) SSP22
E18: RNP6E45 | F18: =IFERROR(VLOOKUP(Tabela1[[#This Row],[Placa]],'Base Cadastro '!A:B,2,FALSE),"Correção de cadastro") -> Master Furgão 8m³ | G18: 120931 | H18: Motor | I18: 45825 | J18: Natallia | K18: Manutenção | L18: Corretiva | M18: Aprovado | P18: =VLOOKUP(Tabela1[[#This Row],[Placa]],'Base Cadastro '!A:M,13,FALSE) -> SRS8 | Q18: MERCADO LIVRE | R18: Motor | S18: Aguardando pagamento | U18: =IFERROR(DATEDIF(Tabela1[[#This Row],[Data Agenda]],Tabela1[[#This Row],[Liberado]],"D"),DATEDIF(Tabela1[[#This Row],[Data Agenda]],TODAY(),"D")) -> 153 | V18: =IF(Tabela1[[#This Row],[D+Manut]]<=2,"Dentro do Prazo","Fora do Prazo") -> Fora do Prazo | W18: Safety Car | X18: ALESSANDRA | Y18: Jun | Z18: =VLOOKUP(Tabela1[[#This Row],[Placa]],DadosViagem5[[Placa]:[Base]],11,FALSE) -> SC (SAPUCAIA) SRS8
E19: GJG8C81 | F19: =IFERROR(VLOOKUP(Tabela1[[#This Row],[Placa]],'Base Cadastro '!A:B,2,FALSE),"Correção de cadastro") -> Sprinter 313 | G19: N/D | H19: 2° via de chave, motorista passou por cima da mesma. | I19: 45958 | J19: Vinicius | K19: Sinistro | L19: Corretiva | M19: Aprovado | N19: 0 | O19: 0 | P19: =VLOOKUP(Tabela1[[#This Row],[Placa]],'Base Cadastro '!A:M,13,FALSE) -> FMS09 | Q19: SHOPEE | R19: Sinistro | S19: 45982 | U19: =IFERROR(DATEDIF(Tabela1[[#This Row],[Data Agenda]],Tabela1[[#This Row],[Liberado]],"D"),DATEDIF(Tabela1[[#This Row],[Data Agenda]],TODAY(),"D")) -> 20 | V19: =IF(Tabela1[[#This Row],[D+Manut]]<=2,"Dentro do Prazo","Fora do Prazo") -> Fora do Prazo | W19: Denigris (São Bernardo do Campo) | X19: Kimberlly | Y19: Out | Z19: =VLOOKUP(Tabela1[[#This Row],[Placa]],DadosViagem5[[Placa]:[Base]],11,FALSE) -> FMS09 SÃO PAULO (SP)
E20: RUM2B60 | F20: =IFERROR(VLOOKUP(Tabela1[[#This Row],[Placa]],'Base Cadastro '!A:B,2,FALSE),"Correção de cadastro") -> Fiorino Endurance Evo 1.4 2P | G20: 206871 | H20: Suspensão, Freio dianteiro | I20: 45972 | J20: Luana | K20: Manutenção | L20: Corretiva | M20: Aprovado | P20: =VLOOKUP(Tabela1[[#This Row],[Placa]],'Base Cadastro '!A:M,13,FALSE) -> SSP28 | Q20: MERCADO LIVRE | R20: Em Manutenção | S20: 45979 | U20: =IFERROR(DATEDIF(Tabela1[[#This Row],[Data Agenda]],Tabela1[[#This Row],[Liberado]],"D"),DATEDIF(Tabela1[[#This Row],[Data Agenda]],TODAY(),"D")) -> 6 | V20: =IF(Tabela1[[#This Row],[D+Manut]]<=2,"Dentro do Prazo","Fora do Prazo") -> Fora do Prazo | W20: Injemec | X20: JOAO VITOR | Y20: Nov | Z20: =VLOOKUP(Tabela1[[#This Row],[Placa]],DadosViagem5[[Placa]:[Base]],11,FALSE) -> SC (JALES) SSP28
D21: 6797882 | E21: SDQ2A43 | F21: =IFERROR(VLOOKUP(Tabela1[[#This Row],[Placa]],'Base Cadastro '!A:B,2,FALSE),"Correção de cadastro") -> Kangoo Z.E. MAXI 5 Lugares 2P | G21: 78322 | H21: Alinhamento / Balanceamento, suspensão e pneus | I21: 45964 | J21: Carla I. | K21: Manutenção | L21: Corretiva | M21: Negociando | P21: =VLOOKUP(Tabela1[[#This Row],[Placa]],'Base Cadastro '!A:M,13,FALSE) -> SSP15 | Q21: MERCADO LIVRE | R21: Em Manutenção | S21: 45979 | U21: =IFERROR(DATEDIF(Tabela1[[#This Row],[Data Agenda]],Tabela1[[#This Row],[Liberado]],"D"),DATEDIF(Tabela1[[#This Row],[Data Agenda]],TODAY(),"D")) -> 14 | V21: =IF(Tabela1[[#This Row],[D+Manut]]<=2,"Dentro do Prazo","Fora do Prazo") -> Fora do Prazo | W21: WM RENOVADORA (Localiza) | X21: NATANAEL | Y21: Out. | Z21: =VLOOKUP(Tabela1[[#This Row],[Placa]],DadosViagem5[[Placa]:[Base]],11,FALSE) -> SC (SANTOS) SSP15
D22: 6795801 | E22: SDQ3A32 | F22: =IFERROR(VLOOKUP(Tabela1[[#This Row],[Placa]],'Base Cadastro '!A:B,2,FALSE),"Correção de cadastro") -> Kangoo Z.E. MAXI 5 Lugares 2P | G22: 60490 | H22: Manunteção de rotina, preventiva | I22: 45968 | J22: Carla I. | K22: Manutenção | L22: Preventiva | M22: Aprovado | P22: =VLOOKUP(Tabela1[[#This Row],[Placa]],'Base Cadastro '!A:M,13,FALSE) -> SSP4 | Q22: MERCADO LIVRE | R22: Em Manutenção | S22: 45979 | U22: =IFERROR(DATEDIF(Tabela1[[#This Row],[Data Agenda]],Tabela1[[#This Row],[Liberado]],"D"),DATEDIF(Tabela1[[#This Row],[Data Agenda]],TODAY(),"D")) -> 10 | V22: =IF(Tabela1[[#This Row],[D+Manut]]<=2,"Dentro do Prazo","Fora do Prazo") -> Fora do Prazo | W22: OFICINA DO BETO (Localiza) | X22: Marcio | Y22: Nov | Z22: =VLOOKUP(Tabela1[[#This Row],[Placa]],DadosViagem5[[Placa]:[Base]],11,FALSE) -> SC (RIBEIRAO PRETO) SSP4
E23: SGF8I65 | F23: =IFERROR(VLOOKUP(Tabela1[[#This Row],[Placa]],'Base Cadastro '!A:B,2,FALSE),"Correção de cadastro") -> TRANSIT CHASSI | G23: 32452 | H23: "Vai pra VIAFOR hoje, aguardando o guincho para levar, veículo para troca de pneus, freios, troca de óleo, está com alguma coisa fazendo muito barulho na roda dianteira, só no guincho para seguir. " | I23: 45911 | J23: Hillary | K23: Manutenção | L23: Corretiva | M23: Negociando | P23: =VLOOKUP(Tabela1[[#This Row],[Placa]],'Base Cadastro '!A:M,13,FALSE) -> SES1 | Q23: MERCADO LIVRE | R23: Em Manutenção | S23: 45979 | U23: =IFERROR(DATEDIF(Tabela1[[#This Row],[Data Agenda]],Tabela1[[#This Row],[Liberado]],"D"),DATEDIF(Tabela1[[#This Row],[Data Agenda]],TODAY(),"D")) -> 67 | V23: =IF(Tabela1[[#This Row],[D+Manut]]<=2,"Dentro do Prazo","Fora do Prazo") -> Fora do Prazo | W23: KM Auto Center | X23: JOÃO | Y23: Set | Z23: =VLOOKUP(Tabela1[[#This Row],[Placa]],DadosViagem5[[Placa]:[Base]],11,FALSE) -> SC (VITORIA) SES1
E24: SGF9B05 | F24: =IFERROR(VLOOKUP(Tabela1[[#This Row],[Placa]],'Base Cadastro '!A:B,2,FALSE),"Correção de cadastro") -> TRANSIT CHASSI | G24: 39260 | H24: Veículo vai para a concessionaria na data 06/10 vai fazer Pneu, óleo, filtros, freios... | I24: 45897 | J24: Hillary | K24: Manutenção | L24: Corretiva | M24: Negociando | N24: 5590.14 | P24: =VLOOKUP(Tabela1[[#This Row],[Placa]],'Base Cadastro '!A:M,13,FALSE) -> SES1 | Q24: MERCADO LIVRE | R24: Em Manutenção | S24: 45979 | U24: =IFERROR(DATEDIF(Tabela1[[#This Row],[Data Agenda]],Tabela1[[#This Row],[Liberado]],"D"),DATEDIF(Tabela1[[#This Row],[Data Agenda]],TODAY(),"D")) -> 81 | V24: =IF(Tabela1[[#This Row],[D+Manut]]<=2,"Dentro do Prazo","Fora do Prazo") -> Fora do Prazo | W24: KM Auto Center | X24: JOÃO | Y24: Ago | Z24: =VLOOKUP(Tabela1[[#This Row],[Placa]],DadosViagem5[[Placa]:[Base]],11,FALSE) -> SC (VITORIA) SES1
E25: RNF2B91 | F25: =IFERROR(VLOOKUP(Tabela1[[#This Row],[Placa]],'Base Cadastro '!A:B,2,FALSE),"Correção de cadastro") -> MASTER FURGAO L1 | G25: 130018 | H25: Funilaria traseira | I25: 45898 | J25: Isabelli | K25: Sinistro | L25: Corretiva | M25: Aprovado | N25: 3000 | O25: 2600 | P25: =VLOOKUP(Tabela1[[#This Row],[Placa]],'Base Cadastro '!A:M,13,FALSE) -> SSP5 | Q25: MERCADO LIVRE | R25: Sinistro | S25: 45980 | U25: =IFERROR(DATEDIF(Tabela1[[#This Row],[Data Agenda]],Tabela1[[#This Row],[Liberado]],"D"),DATEDIF(Tabela1[[#This Row],[Data Agenda]],TODAY(),"D")) -> 80 | V25: =IF(Tabela1[[#This Row],[D+Manut]]<=2,"Dentro do Prazo","Fora do Prazo") -> Fora do Prazo | W25: Oficina Vieira | X25: MARCELO/ISLENE/ERIVELTON | Y25: Ago | Z25: =VLOOKUP(Tabela1[[#This Row],[Placa]],DadosViagem5[[Placa]:[Base]],11,FALSE) -> SC (ARENA BARUERI) SSP5
E26: RUX2B50 | F26: =IFERROR(VLOOKUP(Tabela1[[#This Row],[Placa]],'Base Cadastro '!A:B,2,FALSE),"Correção de cadastro") -> Partner Rapid Business Pack 1.4 2P | G26: 54096 | H26: Veículo realizando o reparo no Cambio- Apos processo de manutenção a mesma vai ser desmobilizada 13/11 | I26: 45730 | J26: Julia | K26: Manutenção | L26: Corretiva | M26: Aprovado | P26: =VLOOKUP(Tabela1[[#This Row],[Placa]],'Base Cadastro '!A:M,13,FALSE) -> SMR1 | Q26: MERCADO LIVRE | R26: Em Manutenção | S26: 45980 | U26: =IFERROR(DATEDIF(Tabela1[[#This Row],[Data Agenda]],Tabela1[[#This Row],[Liberado]],"D"),DATEDIF(Tabela1[[#This Row],[Data Agenda]],TODAY(),"D")) -> 248 | V26: =IF(Tabela1[[#This Row],[D+Manut]]<=2,"Dentro do Prazo","Fora do Prazo") -> Fora do Prazo | W26: GP Auto Center | X26: MICAEL MARCOS | Y26: Mar | Z26: =VLOOKUP(Tabela1[[#This Row],[Placa]],DadosViagem5[[Placa]:[Base]],11,FALSE) -> SC (CUIABA) SMR1
D27: 6795781 | E27: RHU2D75 | F27: =IFERROR(VLOOKUP(Tabela1[[#This Row],[Placa]],'Base Cadastro '!A:B,2,FALSE),"Correção de cadastro") -> JAC iEV1200T AT 4x2 2P | G27: 49899 | H27: Pane Eletrica - Placa pesada - Este caminhão está em teste de módulos das bateiras, onde cada módulo tem diversas células (como se fosse um conjunto de pilhas 10/11/2025 | I27: 45959 | J27: Carla I. | K27: Manutenção | L27: Corretiva | M27: Aprovado | P27: =VLOOKUP(Tabela1[[#This Row],[Placa]],'Base Cadastro '!A:M,13,FALSE) -> SSP30 | Q27: MERCADO LIVRE | R27: Em Manutenção | S27: 45980 | U27: =IFERROR(DATEDIF(Tabela1[[#This Row],[Data Agenda]],Tabela1[[#This Row],[Liberado]],"D"),DATEDIF(Tabela1[[#This Row],[Data Agenda]],TODAY(),"D")) -> 19 | V27: =IF(Tabela1[[#This Row],[D+Manut]]<=2,"Dentro do Prazo","Fora do Prazo") -> Fora do Prazo | W27: TICKET LOG MANUTENCA (Localiza) | X27: Claudia | Y27: Out | Z27: =VLOOKUP(Tabela1[[#This Row],[Placa]],DadosViagem5[[Placa]:[Base]],11,FALSE) -> SC (MEGA GUARULHOS) SSP30
C28: Sim | E28: RUX2B54 | F28: =IFERROR(VLOOKUP(Tabela1[[#This Row],[Placa]],'Base Cadastro '!A:B,2,FALSE),"Correção de cadastro") -> Partner Rapid Business Pack 1.4 2P | G28: N/E | H28: 16/07-Motor Na Retifica 05/05 - Junta Cabeçote agaurdando aprovaçã andre 26/09- Apos processo de manutenção a mesma vai ser desmobilizada 13/11 | I28: 45704 | J28: Julia | K28: Manutenção | L28: Corretiva | M28: Aprovado | N28: 27000 | O28: 15000 | P28: =VLOOKUP(Tabela1[[#This Row],[Placa]],'Base Cadastro '!A:M,13,FALSE) -> SMR1 | Q28: MERCADO LIVRE | R28: Motor | S28: 45980 | U28: =IFERROR(DATEDIF(Tabela1[[#This Row],[Data Agenda]],Tabela1[[#This Row],[Liberado]],"D"),DATEDIF(Tabela1[[#This Row],[Data Agenda]],TODAY(),"D")) -> 274 | V28: =IF(Tabela1[[#This Row],[D+Manut]]<=2,"Dentro do Prazo","Fora do Prazo") -> Fora do Prazo | W28: GP Auto Center | X28: MICAEL MARCOS | Y28: Fev | Z28: =VLOOKUP(Tabela1[[#This Row],[Placa]],DadosViagem5[[Placa]:[Base]],11,FALSE) -> SC (CUIABA) SMR1
D29: 6794461 | E29: RHW0D75 | F29: =IFERROR(VLOOKUP(Tabela1[[#This Row],[Placa]],'Base Cadastro '!A:B,2,FALSE),"Correção de cadastro") -> E-Jumpy Furgão 2P | G29: 57896 | H29: Pane eletrica; Bateria; | I29: 45944 | J29: Julia | K29: Manutenção | L29: Corretiva | M29: Aprovado | P29: =VLOOKUP(Tabela1[[#This Row],[Placa]],'Base Cadastro '!A:M,13,FALSE) -> SBA1 | Q29: MERCADO LIVRE | R29: C/Reserva | S29: 45980 | U29: =IFERROR(DATEDIF(Tabela1[[#This Row],[Data Agenda]],Tabela1[[#This Row],[Liberado]],"D"),DATEDIF(Tabela1[[#This Row],[Data Agenda]],TODAY(),"D")) -> 34 | V29: =IF(Tabela1[[#This Row],[D+Manut]]<=2,"Dentro do Prazo","Fora do Prazo") -> Fora do Prazo | W29: Gaulesa Iguatemi (Localiza) | X29: UEBERT | Y29: Out | Z29: =VLOOKUP(Tabela1[[#This Row],[Placa]],DadosViagem5[[Placa]:[Base]],11,FALSE) -> SC (BAHIA SALVADOR) SBA1
D30: 6789331 | E30: SDT9F97 | F30: =IFERROR(VLOOKUP(Tabela1[[#This Row],[Placa]],'Base Cadastro '!A:B,2,FALSE),"Correção de cadastro") -> E-Jumpy Furgão 2P | G30: 22935 | H30: Pane elétrica | I30: 45940 | J30: Natallia | K30: Manutenção | L30: Corretiva | M30: Aprovado | P30: =VLOOKUP(Tabela1[[#This Row],[Placa]],'Base Cadastro '!A:M,13,FALSE) -> SRS1 | Q30: MERCADO LIVRE | R30: C/Reserva | S30: 45980 | U30: =IFERROR(DATEDIF(Tabela1[[#This Row],[Data Agenda]],Tabela1[[#This Row],[Liberado]],"D"),DATEDIF(Tabela1[[#This Row],[Data Agenda]],TODAY(),"D")) -> 38 | V30: =IF(Tabela1[[#This Row],[D+Manut]]<=2,"Dentro do Prazo","Fora do Prazo") -> Fora do Prazo | W30: PEUGEOT LYON (Localiza) | X30: EVAILTON | Y30: Out | Z30: =VLOOKUP(Tabela1[[#This Row],[Placa]],DadosViagem5[[Placa]:[Base]],11,FALSE) -> SC (PORTO ALEGRE) SRS1
D31: 6794451 | E31: SDP9I99 | F31: =IFERROR(VLOOKUP(Tabela1[[#This Row],[Placa]],'Base Cadastro '!A:B,2,FALSE),"Correção de cadastro") -> E-Jumpy Furgão 2P | G31: 10202 | H31: Pane Eletrica; bateria | I31: 45953 | J31: Julia | K31: Manutenção | L31: Corretiva | M31: Aprovado | P31: =VLOOKUP(Tabela1[[#This Row],[Placa]],'Base Cadastro '!A:M,13,FALSE) -> SBA1 | Q31: MERCADO LIVRE | R31: C/Reserva | S31: 45980 | U31: =IFERROR(DATEDIF(Tabela1[[#This Row],[Data Agenda]],Tabela1[[#This Row],[Liberado]],"D"),DATEDIF(Tabela1[[#This Row],[Data Agenda]],TODAY(),"D")) -> 25 | V31: =IF(Tabela1[[#This Row],[D+Manut]]<=2,"Dentro do Prazo","Fora do Prazo") -> Fora do Prazo | W31: Gaulesa Iguatemi (Localiza) | X31: TIAGO | Y31: Out | Z31: =VLOOKUP(Tabela1[[#This Row],[Placa]],DadosViagem5[[Placa]:[Base]],11,FALSE) -> SC (BAHIA SALVADOR) SBA1
D32: 6794202 | E32: RHW0D47 | F32: =IFERROR(VLOOKUP(Tabela1[[#This Row],[Placa]],'Base Cadastro '!A:B,2,FALSE),"Correção de cadastro") -> E-Jumpy Furgão 2P | G32: 88701 | H32: Pane Eletrica; bateria | I32: 45953 | J32: Julia | K32: Manutenção | L32: Corretiva | M32: Aprovado | P32: =VLOOKUP(Tabela1[[#This Row],[Placa]],'Base Cadastro '!A:M,13,FALSE) -> SBA1 | Q32: MERCADO LIVRE | R32: C/Reserva | S32: 45980 | U32: =IFERROR(DATEDIF(Tabela1[[#This Row],[Data Agenda]],Tabela1[[#This Row],[Liberado]],"D"),DATEDIF(Tabela1[[#This Row],[Data Agenda]],TODAY(),"D")) -> 25 | V32: =IF(Tabela1[[#This Row],[D+Manut]]<=2,"Dentro do Prazo","Fora do Prazo") -> Fora do Prazo | W32: Gaulesa Iguatemi (Localiza) | X32: TIAGO | Y32: Out | Z32: =VLOOKUP(Tabela1[[#This Row],[Placa]],DadosViagem5[[Placa]:[Base]],11,FALSE) -> SC (BAHIA SALVADOR) SBA1
D33: 6794458 | E33: RHW0D84 | F33: =IFERROR(VLOOKUP(Tabela1[[#This Row],[Placa]],'Base Cadastro '!A:B,2,FALSE),"Correção de cadastro") -> E-Jumpy Furgão 2P | G33: 55810 | H33: Pane Eletrica; bateria | I33: 45953 | J33: Julia | K33: Manutenção | L33: Corretiva | M33: Aprovado | P33: =VLOOKUP(Tabela1[[#This Row],[Placa]],'Base Cadastro '!A:M,13,FALSE) -> SBA1 | Q33: MERCADO LIVRE | R33: C/Reserva | S33: 45980 | U33: =IFERROR(DATEDIF(Tabela1[[#This Row],[Data Agenda]],Tabela1[[#This Row],[Liberado]],"D"),DATEDIF(Tabela1[[#This Row],[Data Agenda]],TODAY(),"D")) -> 25 | V33: =IF(Tabela1[[#This Row],[D+Manut]]<=2,"Dentro do Prazo","Fora do Prazo") -> Fora do Prazo | W33: Gaulesa Iguatemi (Localiza) | X33: TIAGO | Y33: Out | Z33: =VLOOKUP(Tabela1[[#This Row],[Placa]],DadosViagem5[[Placa]:[Base]],11,FALSE) -> SC (BAHIA SALVADOR) SBA1
D34: 6794199 | E34: SDP9J01 | F34: =IFERROR(VLOOKUP(Tabela1[[#This Row],[Placa]],'Base Cadastro '!A:B,2,FALSE),"Correção de cadastro") -> E-Jumpy Furgão 2P | G34: 73518 | H34: Pane Eletrica; bateria | I34: 45953 | J34: Julia | K34: Manutenção | L34: Corretiva | M34: Aprovado | P34: =VLOOKUP(Tabela1[[#This Row],[Placa]],'Base Cadastro '!A:M,13,FALSE) -> SBA1 | Q34: MERCADO LIVRE | R34: C/Reserva | S34: 45980 | U34: =IFERROR(DATEDIF(Tabela1[[#This Row],[Data Agenda]],Tabela1[[#This Row],[Liberado]],"D"),DATEDIF(Tabela1[[#This Row],[Data Agenda]],TODAY(),"D")) -> 25 | V34: =IF(Tabela1[[#This Row],[D+Manut]]<=2,"Dentro do Prazo","Fora do Prazo") -> Fora do Prazo | W34: Gaulesa Iguatemi (Localiza) | X34: TIAGO | Y34: Out | Z34: =VLOOKUP(Tabela1[[#This Row],[Placa]],DadosViagem5[[Placa]:[Base]],11,FALSE) -> SC (BAHIA SALVADOR) SBA1
D35: 6794200 | E35: RHW0D37 | F35: =IFERROR(VLOOKUP(Tabela1[[#This Row],[Placa]],'Base Cadastro '!A:B,2,FALSE),"Correção de cadastro") -> E-Jumpy Furgão 2P | G35: 63500 | H35: Pane Eletrica; bateria | I35: 45953 | J35: Julia | K35: Manutenção | L35: Corretiva | M35: Aprovado | P35: =VLOOKUP(Tabela1[[#This Row],[Placa]],'Base Cadastro '!A:M,13,FALSE) -> SBA1 | Q35: MERCADO LIVRE | R35: C/Reserva | S35: 45980 | U35: =IFERROR(DATEDIF(Tabela1[[#This Row],[Data Agenda]],Tabela1[[#This Row],[Liberado]],"D"),DATEDIF(Tabela1[[#This Row],[Data Agenda]],TODAY(),"D")) -> 25 | V35: =IF(Tabela1[[#This Row],[D+Manut]]<=2,"Dentro do Prazo","Fora do Prazo") -> Fora do Prazo | W35: Gaulesa Iguatemi (Localiza) | X35: TIAGO | Y35: Out | Z35: =VLOOKUP(Tabela1[[#This Row],[Placa]],DadosViagem5[[Placa]:[Base]],11,FALSE) -> SC (BAHIA SALVADOR) SBA1
D36: 6792618 | E36: SDQ2A99 | F36: =IFERROR(VLOOKUP(Tabela1[[#This Row],[Placa]],'Base Cadastro '!A:B,2,FALSE),"Correção de cadastro") -> Kangoo Z.E. MAXI 5 Lugares 2P | G36: 66899 | H36: Bateria de rodagem | I36: 45937 | J36: Natallia | K36: Manutenção | L36: Corretiva | M36: Aprovado | P36: =VLOOKUP(Tabela1[[#This Row],[Placa]],'Base Cadastro '!A:M,13,FALSE) -> SSC2 | Q36: MERCADO LIVRE | R36: C/Reserva | S36: 45982 | U36: =IFERROR(DATEDIF(Tabela1[[#This Row],[Data Agenda]],Tabela1[[#This Row],[Liberado]],"D"),DATEDIF(Tabela1[[#This Row],[Data Agenda]],TODAY(),"D")) -> 41 | V36: =IF(Tabela1[[#This Row],[D+Manut]]<=2,"Dentro do Prazo","Fora do Prazo") -> Fora do Prazo | W36: AUTOMEGA (Localiza) | X36: CARLOS SELL | Y36: Out | Z36: =VLOOKUP(Tabela1[[#This Row],[Placa]],DadosViagem5[[Placa]:[Base]],11,FALSE) -> SC (FLORIANOPOLIS) SSC2
E37: SGH8H53 | F37: =IFERROR(VLOOKUP(Tabela1[[#This Row],[Placa]],'Base Cadastro '!A:B,2,FALSE),"Correção de cadastro") -> TRANSIT FURGÃO | G37: 50744 | H37: Revisão(Pastilha de Freio) | I37: 45965 | J37: Hillary | K37: Manutenção | L37: Corretiva | M37: Negociando | P37: =VLOOKUP(Tabela1[[#This Row],[Placa]],'Base Cadastro '!A:M,13,FALSE) -> SSC3 | Q37: MERCADO LIVRE | R37: Em Manutenção | S37: 45980 | U37: =IFERROR(DATEDIF(Tabela1[[#This Row],[Data Agenda]],Tabela1[[#This Row],[Liberado]],"D"),DATEDIF(Tabela1[[#This Row],[Data Agenda]],TODAY(),"D")) -> 13 | V37: =IF(Tabela1[[#This Row],[D+Manut]]<=2,"Dentro do Prazo","Fora do Prazo") -> Fora do Prazo | W37: Ford AutoPlus | X37: Gabrieli | Y37: Nov | Z37: SC (BLUMENAU) SSC3
E38: SGH6H62 | F38: =IFERROR(VLOOKUP(Tabela1[[#This Row],[Placa]],'Base Cadastro '!A:B,2,FALSE),"Correção de cadastro") -> TRANSIT FURGÃO | G38: 59751 | H38: Revisão(Pastilha de Freio) | I38: 45965 | J38: Hillary | K38: Manutenção | L38: Corretiva | M38: Negociando | P38: =VLOOKUP(Tabela1[[#This Row],[Placa]],'Base Cadastro '!A:M,13,FALSE) -> SSC3 | Q38: MERCADO LIVRE | R38: Em Manutenção | S38: 45980 | U38: =IFERROR(DATEDIF(Tabela1[[#This Row],[Data Agenda]],Tabela1[[#This Row],[Liberado]],"D"),DATEDIF(Tabela1[[#This Row],[Data Agenda]],TODAY(),"D")) -> 13 | V38: =IF(Tabela1[[#This Row],[D+Manut]]<=2,"Dentro do Prazo","Fora do Prazo") -> Fora do Prazo | W38: Ford AutoPlus | X38: Gabrieli | Y38: Nov | Z38: =VLOOKUP(Tabela1[[#This Row],[Placa]],DadosViagem5[[Placa]:[Base]],11,FALSE) -> SC (BLUMENAU) SSC3
C39: Sim | E39: RUX9G54 | F39: =IFERROR(VLOOKUP(Tabela1[[#This Row],[Placa]],'Base Cadastro '!A:B,2,FALSE),"Correção de cadastro") -> Fiorino Endurance Evo 1.4 2P | G39: N/E | H39: ASCENDEU LUZ DA INJEÇÃO EM SEGUIDA PERDEU FORÇA E PAROU DE FUNCIONAR | I39: 45968 | J39: Julia | K39: Manutenção | L39: Corretiva | M39: Negociando | P39: =VLOOKUP(Tabela1[[#This Row],[Placa]],'Base Cadastro '!A:M,13,FALSE) -> LMS36 | Q39: MERCADO LIVRE | R39: Em Manutenção | S39: 45980 | U39: =IFERROR(DATEDIF(Tabela1[[#This Row],[Data Agenda]],Tabela1[[#This Row],[Liberado]],"D"),DATEDIF(Tabela1[[#This Row],[Data Agenda]],TODAY(),"D")) -> 10 | V39: =IF(Tabela1[[#This Row],[D+Manut]]<=2,"Dentro do Prazo","Fora do Prazo") -> Fora do Prazo | W39: Wellington Gideoes Oficina | X39: TIAGO | Y39: Nov | Z39: SC (BAHIA SALVADOR) SBA1
E40: SGH6H64 | F40: =IFERROR(VLOOKUP(Tabela1[[#This Row],[Placa]],'Base Cadastro '!A:B,2,FALSE),"Correção de cadastro") -> TRANSIT FURGÃO | G40: N/E | H40: Pastilha de Freio | I40: 45971 | J40: Hillary | K40: Manutenção | L40: Corretiva | M40: Negociando | P40: =VLOOKUP(Tabela1[[#This Row],[Placa]],'Base Cadastro '!A:M,13,FALSE) -> SSC1 | Q40: MERCADO LIVRE | R40: Em Manutenção | S40: 45980 | U40: =IFERROR(DATEDIF(Tabela1[[#This Row],[Data Agenda]],Tabela1[[#This Row],[Liberado]],"D"),DATEDIF(Tabela1[[#This Row],[Data Agenda]],TODAY(),"D")) -> 7 | V40: =IF(Tabela1[[#This Row],[D+Manut]]<=2,"Dentro do Prazo","Fora do Prazo") -> Fora do Prazo | W40: Ford Globo | X40: Juliano | Y40: Nov. | Z40: =VLOOKUP(Tabela1[[#This Row],[Placa]],DadosViagem5[[Placa]:[Base]],11,FALSE) -> SC (JOINVILLE) SSC1
E41: RVB8A67 | F41: =IFERROR(VLOOKUP(Tabela1[[#This Row],[Placa]],'Base Cadastro '!A:B,2,FALSE),"Correção de cadastro") -> MASTER FURGAO L1 | G41: 92.338.0 | H41: Turbina | I41: 45971 | J41: Sara | K41: Manutenção | L41: Corretiva | M41: Negociando | P41: =VLOOKUP(Tabela1[[#This Row],[Placa]],'Base Cadastro '!A:M,13,FALSE) -> SPR2 | Q41: MERCADO LIVRE | R41: Em Manutenção | S41: 45981 | U41: =IFERROR(DATEDIF(Tabela1[[#This Row],[Data Agenda]],Tabela1[[#This Row],[Liberado]],"D"),DATEDIF(Tabela1[[#This Row],[Data Agenda]],TODAY(),"D")) -> 7 | V41: =IF(Tabela1[[#This Row],[D+Manut]]<=2,"Dentro do Prazo","Fora do Prazo") -> Fora do Prazo | W41: Cometa Car | X41: ANA | Y41: Nov. | Z41: =VLOOKUP(Tabela1[[#This Row],[Placa]],DadosViagem5[[Placa]:[Base]],11,FALSE) -> SC (LONDRINA) SPR2
E42: RVB7H99 | F42: =IFERROR(VLOOKUP(Tabela1[[#This Row],[Placa]],'Base Cadastro '!A:B,2,FALSE),"Correção de cadastro") -> TRANSIT FURGÃO | G42: 151494 | H42: Veículo realizando funilaria na oficina Vieria | I42: 45656 | J42: Isabelli | K42: Sinistro | L42: Corretiva | M42: Aprovado | N42: 3700 | O42: 3700 | P42: =VLOOKUP(Tabela1[[#This Row],[Placa]],'Base Cadastro '!A:M,13,FALSE) -> SSP38 | Q42: MERCADO LIVRE | R42: Sinistro | S42: 45982 | U42: =IFERROR(DATEDIF(Tabela1[[#This Row],[Data Agenda]],Tabela1[[#This Row],[Liberado]],"D"),DATEDIF(Tabela1[[#This Row],[Data Agenda]],TODAY(),"D")) -> 322 | V42: =IF(Tabela1[[#This Row],[D+Manut]]<=2,"Dentro do Prazo","Fora do Prazo") -> Fora do Prazo | W42: Oficina Vieira | X42: ANA FLAVIA | Y42: Dez | Z42: =VLOOKUP(Tabela1[[#This Row],[Placa]],DadosViagem5[[Placa]:[Base]],11,FALSE) -> SC (ITUPEVA) SSP38
E43: SGF9A21 | F43: =IFERROR(VLOOKUP(Tabela1[[#This Row],[Placa]],'Base Cadastro '!A:B,2,FALSE),"Correção de cadastro") -> TRANSIT CHASSI | G43: 39612 | H43: Colisão grave dianteira | I43: 45851 | J43: Vinicius | K43: Sinistro | L43: Corretiva | M43: Aprovado | N43: 27000 | O43: 27000 | P43: =VLOOKUP(Tabela1[[#This Row],[Placa]],'Base Cadastro '!A:M,13,FALSE) -> SES1 | Q43: MERCADO LIVRE | R43: Sinistro | S43: 45982 | U43: =IFERROR(DATEDIF(Tabela1[[#This Row],[Data Agenda]],Tabela1[[#This Row],[Liberado]],"D"),DATEDIF(Tabela1[[#This Row],[Data Agenda]],TODAY(),"D")) -> 127 | V43: =IF(Tabela1[[#This Row],[D+Manut]]<=2,"Dentro do Prazo","Fora do Prazo") -> Fora do Prazo | W43: KM Auto Center | X43: João | Y43: Set | Z43: =VLOOKUP(Tabela1[[#This Row],[Placa]],DadosViagem5[[Placa]:[Base]],11,FALSE) -> SC (VITORIA) SES1
E44: RVD8H69 | F44: =IFERROR(VLOOKUP(Tabela1[[#This Row],[Placa]],'Base Cadastro '!A:B,2,FALSE),"Correção de cadastro") -> Fiorino Endurance Evo 1.4 2P | G44: 24352 | H44: Colisão traseira. | I44: 45943 | J44: Vinicius | K44: Sinistro | L44: Corretiva | M44: Negociando | P44: =VLOOKUP(Tabela1[[#This Row],[Placa]],'Base Cadastro '!A:M,13,FALSE) -> EMS4 | Q44: MERCADO LIVRE | R44: Sinistro | S44: 45982 | U44: =IFERROR(DATEDIF(Tabela1[[#This Row],[Data Agenda]],Tabela1[[#This Row],[Liberado]],"D"),DATEDIF(Tabela1[[#This Row],[Data Agenda]],TODAY(),"D")) -> 35 | V44: =IF(Tabela1[[#This Row],[D+Manut]]<=2,"Dentro do Prazo","Fora do Prazo") -> Fora do Prazo | W44: Impacto funilaria | X44: Mariana | Y44: Out | Z44: =VLOOKUP(Tabela1[[#This Row],[Placa]],DadosViagem5[[Placa]:[Base]],11,FALSE) -> XPT (TRES LAGOAS ) EMS4/SSP10
E45: SGL4D16 | F45: =IFERROR(VLOOKUP(Tabela1[[#This Row],[Placa]],'Base Cadastro '!A:B,2,FALSE),"Correção de cadastro") -> TRANSIT FURGÃO | G45: 45.749.0 | H45: Vazando óleo | I45: 45953 | J45: Hillary | K45: Manutenção | L45: Corretiva | M45: Negociando | P45: =VLOOKUP(Tabela1[[#This Row],[Placa]],'Base Cadastro '!A:M,13,FALSE) -> #N/A | Q45: MADEIRA MADEIRA | R45: Em Manutenção | S45: 45982 | U45: =IFERROR(DATEDIF(Tabela1[[#This Row],[Data Agenda]],Tabela1[[#This Row],[Liberado]],"D"),DATEDIF(Tabela1[[#This Row],[Data Agenda]],TODAY(),"D")) -> 25 | V45: =IF(Tabela1[[#This Row],[D+Manut]]<=2,"Dentro do Prazo","Fora do Prazo") -> Fora do Prazo | W45: Vip Pneus | X45: KETHLEEN | Y45: Out | Z45: =VLOOKUP(Tabela1[[#This Row],[Placa]],DadosViagem5[[Placa]:[Base]],11,FALSE) -> MM03 (ARUJA)
E46: RUX6F65 | F46: =IFERROR(VLOOKUP(Tabela1[[#This Row],[Placa]],'Base Cadastro '!A:B,2,FALSE),"Correção de cadastro") -> Fiorino Endurance Evo 1.4 2P | G46: N/E | H46: Não da partida | I46: 45959 | J46: Sara | K46: Manutenção | L46: Corretiva | M46: Aprovado | P46: =VLOOKUP(Tabela1[[#This Row],[Placa]],'Base Cadastro '!A:M,13,FALSE) -> SPR1 | Q46: MERCADO LIVRE | R46: Em Manutenção | S46: 45982 | U46: =IFERROR(DATEDIF(Tabela1[[#This Row],[Data Agenda]],Tabela1[[#This Row],[Liberado]],"D"),DATEDIF(Tabela1[[#This Row],[Data Agenda]],TODAY(),"D")) -> 19 | V46: =IF(Tabela1[[#This Row],[D+Manut]]<=2,"Dentro do Prazo","Fora do Prazo") -> Fora do Prazo | W46: FSP | X46: RENATA | Y46: Out | Z46: =VLOOKUP(Tabela1[[#This Row],[Placa]],DadosViagem5[[Placa]:[Base]],11,FALSE) -> SC (CURITIBA) SPR1
E47: SFW0A67 | F47: =IFERROR(VLOOKUP(Tabela1[[#This Row],[Placa]],'Base Cadastro '!A:B,2,FALSE),"Correção de cadastro") -> TRANSIT FURGÃO | G47: 39067 | H47: Colisão traseira de um terceiro. | I47: 45883 | J47: Vinicius | K47: Sinistro | L47: Corretiva | M47: Aprovado | N47: 8088 | O47: 8088 | P47: =VLOOKUP(Tabela1[[#This Row],[Placa]],'Base Cadastro '!A:M,13,FALSE) -> SBA1 | Q47: MERCADO LIVRE | R47: Sinistro | S47: 45983 | U47: =IFERROR(DATEDIF(Tabela1[[#This Row],[Data Agenda]],Tabela1[[#This Row],[Liberado]],"D"),DATEDIF(Tabela1[[#This Row],[Data Agenda]],TODAY(),"D")) -> 95 | V47: =IF(Tabela1[[#This Row],[D+Manut]]<=2,"Dentro do Prazo","Fora do Prazo") -> Fora do Prazo | W47: RT Caminhoes | X47: Tiago | Y47: Ago | Z47: =VLOOKUP(Tabela1[[#This Row],[Placa]],DadosViagem5[[Placa]:[Base]],11,FALSE) -> SC (BAHIA SALVADOR) SBA1
E48: RVD9A43 | F48: =IFERROR(VLOOKUP(Tabela1[[#This Row],[Placa]],'Base Cadastro '!A:B,2,FALSE),"Correção de cadastro") -> Fiorino Endurance Evo 1.4 2P | G48: 126462 | H48: Pane elétrica | I48: 45875 | J48: Natallia | K48: Manutenção | L48: Corretiva | M48: Aprovado | P48: =VLOOKUP(Tabela1[[#This Row],[Placa]],'Base Cadastro '!A:M,13,FALSE) -> SRS10 | Q48: MERCADO LIVRE | R48: Em Manutenção | S48: 45985 | U48: =IFERROR(DATEDIF(Tabela1[[#This Row],[Data Agenda]],Tabela1[[#This Row],[Liberado]],"D"),DATEDIF(Tabela1[[#This Row],[Data Agenda]],TODAY(),"D")) -> 103 | V48: =IF(Tabela1[[#This Row],[D+Manut]]<=2,"Dentro do Prazo","Fora do Prazo") -> Fora do Prazo | W48: Safety Car | X48: FERNANDA | Y48: Ago | Z48: =VLOOKUP(Tabela1[[#This Row],[Placa]],DadosViagem5[[Placa]:[Base]],11,FALSE) -> SC (LAJEADO) SRS10
E49: RUX2C24 | F49: =IFERROR(VLOOKUP(Tabela1[[#This Row],[Placa]],'Base Cadastro '!A:B,2,FALSE),"Correção de cadastro") -> Partner Rapid Business Pack 1.4 2P | G49: 60222 | H49: Colisão lateral direita, fiorino rasgada. | I49: 45766 | J49: Isabelli | K49: Sinistro | L49: Corretiva | M49: Aprovado | N49: 17000 | O49: 17000 | P49: =VLOOKUP(Tabela1[[#This Row],[Placa]],'Base Cadastro '!A:M,13,FALSE) -> SPR3 | Q49: MERCADO LIVRE | R49: Sinistro | S49: 45986 | U49: =IFERROR(DATEDIF(Tabela1[[#This Row],[Data Agenda]],Tabela1[[#This Row],[Liberado]],"D"),DATEDIF(Tabela1[[#This Row],[Data Agenda]],TODAY(),"D")) -> 212 | V49: =IF(Tabela1[[#This Row],[D+Manut]]<=2,"Dentro do Prazo","Fora do Prazo") -> Fora do Prazo | W49: Autentica | X49: CLEITON | Y49: Abr | Z49: =VLOOKUP(Tabela1[[#This Row],[Placa]],DadosViagem5[[Placa]:[Base]],11,FALSE) -> SC (CASCAVEL) SPR3
E50: RNF2B98 | F50: =IFERROR(VLOOKUP(Tabela1[[#This Row],[Placa]],'Base Cadastro '!A:B,2,FALSE),"Correção de cadastro") -> Master Furgão 8m³ | G50: 173662 | H50: Oficina está alegando que a placa, Placa não funciona, placa está sem o sensor e provavel que seja por falta de sensor do pedal, oficina fazendo analize detalhada do defeito. - Cabeçote foi para a retifica 06/11/2025 | I50: 45938 | J50: Carla I. | K50: Manutenção | L50: Corretiva | M50: Aprovado | P50: =VLOOKUP(Tabela1[[#This Row],[Placa]],'Base Cadastro '!A:M,13,FALSE) -> SSP4 | Q50: MERCADO LIVRE | R50: Motor | S50: 45986 | U50: =IFERROR(DATEDIF(Tabela1[[#This Row],[Data Agenda]],Tabela1[[#This Row],[Liberado]],"D"),DATEDIF(Tabela1[[#This Row],[Data Agenda]],TODAY(),"D")) -> 40 | V50: =IF(Tabela1[[#This Row],[D+Manut]]<=2,"Dentro do Prazo","Fora do Prazo") -> Fora do Prazo | W50: RPA OFICINA | X50: Marcio | Y50: Out | Z50: =VLOOKUP(Tabela1[[#This Row],[Placa]],DadosViagem5[[Placa]:[Base]],11,FALSE) -> SC (RIBEIRAO PRETO) SSP4
E51: RNC9E73 | F51: =IFERROR(VLOOKUP(Tabela1[[#This Row],[Placa]],'Base Cadastro '!A:B,2,FALSE),"Correção de cadastro") -> Master Furgão 8m³ | G51: 203959 | H51: Cabeçote - Cabeçote na Retifica 06/11/2025 | I51: 45916 | J51: Carla I. | K51: Manutenção | L51: Corretiva | M51: Aprovado | P51: =VLOOKUP(Tabela1[[#This Row],[Placa]],'Base Cadastro '!A:M,13,FALSE) -> SSP4 | Q51: MERCADO LIVRE | R51: Motor | S51: 45986 | U51: =IFERROR(DATEDIF(Tabela1[[#This Row],[Data Agenda]],Tabela1[[#This Row],[Liberado]],"D"),DATEDIF(Tabela1[[#This Row],[Data Agenda]],TODAY(),"D")) -> 62 | V51: =IF(Tabela1[[#This Row],[D+Manut]]<=2,"Dentro do Prazo","Fora do Prazo") -> Fora do Prazo | W51: RPA OFICINA | X51: Marcio | Y51: Out | Z51: =VLOOKUP(Tabela1[[#This Row],[Placa]],DadosViagem5[[Placa]:[Base]],11,FALSE) -> SC (RIBEIRAO PRETO) SSP4
E52: SGI8J06 | F52: =IFERROR(VLOOKUP(Tabela1[[#This Row],[Placa]],'Base Cadastro '!A:B,2,FALSE),"Correção de cadastro") -> TRANSIT FURGÃO | G52: 68103 | H52: Veículo está realizando a funilaria do teto | I52: 45875 | J52: Vinicius | K52: Sinistro | L52: Corretiva | M52: Aprovado | N52: 6562.32 | O52: 5900 | P52: =VLOOKUP(Tabela1[[#This Row],[Placa]],'Base Cadastro '!A:M,13,FALSE) -> SRS10 | Q52: MERCADO LIVRE | R52: Sinistro | S52: 45986 | U52: =IFERROR(DATEDIF(Tabela1[[#This Row],[Data Agenda]],Tabela1[[#This Row],[Liberado]],"D"),DATEDIF(Tabela1[[#This Row],[Data Agenda]],TODAY(),"D")) -> 103 | V52: =IF(Tabela1[[#This Row],[D+Manut]]<=2,"Dentro do Prazo","Fora do Prazo") -> Fora do Prazo | W52: Safety Car | X52: Fernanda | Y52: Ago | Z52: =VLOOKUP(Tabela1[[#This Row],[Placa]],DadosViagem5[[Placa]:[Base]],11,FALSE) -> SC (LAJEADO) SRS10
C53: Sim | E53: GHM9C04 | F53: =IFERROR(VLOOKUP(Tabela1[[#This Row],[Placa]],'Base Cadastro '!A:B,2,FALSE),"Correção de cadastro") -> Sprinter 313 | G53: N/E | H53: Liga , anda e em algum dado momento ela corta | I53: 45794 | J53: Natallia | K53: Manutenção | L53: Corretiva | M53: Aprovado | P53: =VLOOKUP(Tabela1[[#This Row],[Placa]],'Base Cadastro '!A:M,13,FALSE) -> SSC5 | Q53: MERCADO LIVRE | R53: Em Manutenção | S53: 45986 | U53: =IFERROR(DATEDIF(Tabela1[[#This Row],[Data Agenda]],Tabela1[[#This Row],[Liberado]],"D"),DATEDIF(Tabela1[[#This Row],[Data Agenda]],TODAY(),"D")) -> 184 | V53: =IF(Tabela1[[#This Row],[D+Manut]]<=2,"Dentro do Prazo","Fora do Prazo") -> Fora do Prazo | W53: FSP | X53: REGIANE | Y53: Mai | Z53: =VLOOKUP(Tabela1[[#This Row],[Placa]],DadosViagem5[[Placa]:[Base]],11,FALSE) -> SC (CRICIUMA) SSC5
D54: 6771633 | E54: SDP9J10 | F54: =IFERROR(VLOOKUP(Tabela1[[#This Row],[Placa]],'Base Cadastro '!A:B,2,FALSE),"Correção de cadastro") -> E-Jumpy Furgão 2P | G54: 38538 | H54: Manutenção eletrica automotiva, bomba de agua, cabo da trava da bateria 01/09/2025 | I54: 45901 | J54: Julia | K54: Manutenção | L54: Corretiva | M54: Aprovado | P54: =VLOOKUP(Tabela1[[#This Row],[Placa]],'Base Cadastro '!A:M,13,FALSE) -> SCE1 | Q54: MERCADO LIVRE | R54: C/Reserva | S54: 45987 | U54: =IFERROR(DATEDIF(Tabela1[[#This Row],[Data Agenda]],Tabela1[[#This Row],[Liberado]],"D"),DATEDIF(Tabela1[[#This Row],[Data Agenda]],TODAY(),"D")) -> 77 | V54: =IF(Tabela1[[#This Row],[D+Manut]]<=2,"Dentro do Prazo","Fora do Prazo") -> Fora do Prazo | W54: PEUGEOT LYON (Localiza) | X54: GLEUMA | Y54: Set | Z54: =VLOOKUP(Tabela1[[#This Row],[Placa]],DadosViagem5[[Placa]:[Base]],11,FALSE) -> SC (FORTALEZA) SCE1
D55: 6800311 | E55: SDQ2J50 | F55: =IFERROR(VLOOKUP(Tabela1[[#This Row],[Placa]],'Base Cadastro '!A:B,2,FALSE),"Correção de cadastro") -> Kangoo Z.E. MAXI 5 Lugares 2P | G55: N/E | H55: Homocinética | I55: 45969 | J55: Khetlyn | K55: Manutenção | L55: Corretiva | M55: Negociando | P55: =VLOOKUP(Tabela1[[#This Row],[Placa]],'Base Cadastro '!A:M,13,FALSE) -> SSP20 | Q55: MERCADO LIVRE | R55: Em Manutenção | S55: 45988 | U55: =IFERROR(DATEDIF(Tabela1[[#This Row],[Data Agenda]],Tabela1[[#This Row],[Liberado]],"D"),DATEDIF(Tabela1[[#This Row],[Data Agenda]],TODAY(),"D")) -> 9 | V55: =IF(Tabela1[[#This Row],[D+Manut]]<=2,"Dentro do Prazo","Fora do Prazo") -> Fora do Prazo | W55: Della via (Localiza) | X55: LARIENE | Y55: Nov | Z55: =VLOOKUP(Tabela1[[#This Row],[Placa]],DadosViagem5[[Placa]:[Base]],11,FALSE) -> SC (SOROCABA) SSP20
E56: RVA2J52 | F56: =IFERROR(VLOOKUP(Tabela1[[#This Row],[Placa]],'Base Cadastro '!A:B,2,FALSE),"Correção de cadastro") -> MASTER FURGAO L1 | G56: 111662 | H56: Motor- negociando novo parceiro 29/09 - carro na base e motor na oficina aqui em sp - 08/10/2025 | I56: 45709 | J56: Carla I. | K56: Manutenção | L56: Corretiva | M56: Aprovado | P56: =VLOOKUP(Tabela1[[#This Row],[Placa]],'Base Cadastro '!A:M,13,FALSE) -> SSP4 | Q56: MERCADO LIVRE | R56: Motor | S56: 45989 | U56: =IFERROR(DATEDIF(Tabela1[[#This Row],[Data Agenda]],Tabela1[[#This Row],[Liberado]],"D"),DATEDIF(Tabela1[[#This Row],[Data Agenda]],TODAY(),"D")) -> 269 | V56: =IF(Tabela1[[#This Row],[D+Manut]]<=2,"Dentro do Prazo","Fora do Prazo") -> Fora do Prazo | W56: Mecatrônica Ganso | X56: DEBORAH | Y56: Fev | Z56: =VLOOKUP(Tabela1[[#This Row],[Placa]],DadosViagem5[[Placa]:[Base]],11,FALSE) -> SC (RIBEIRAO PRETO) SSP4
E57: SGH8H52 | F57: =IFERROR(VLOOKUP(Tabela1[[#This Row],[Placa]],'Base Cadastro '!A:B,2,FALSE),"Correção de cadastro") -> TRANSIT FURGÃO | G57: N/E | H57: Veículo deu parada para realizar funilaria do teto. | I57: 45943 | J57: Vinicius | K57: Sinistro | L57: Corretiva | M57: Aprovado | N57: 6450 | O57: 6450 | P57: =VLOOKUP(Tabela1[[#This Row],[Placa]],'Base Cadastro '!A:M,13,FALSE) -> SRS8 | Q57: MERCADO LIVRE | R57: Sinistro | S57: 45989 | U57: =IFERROR(DATEDIF(Tabela1[[#This Row],[Data Agenda]],Tabela1[[#This Row],[Liberado]],"D"),DATEDIF(Tabela1[[#This Row],[Data Agenda]],TODAY(),"D")) -> 35 | V57: =IF(Tabela1[[#This Row],[D+Manut]]<=2,"Dentro do Prazo","Fora do Prazo") -> Fora do Prazo | W57: Safety Car | X57: Marlon | Y57: Out | Z57: =VLOOKUP(Tabela1[[#This Row],[Placa]],DadosViagem5[[Placa]:[Base]],11,FALSE) -> SC (SAPUCAIA) SRS8
D58: 6796341 | E58: SDP9J05 | F58: =IFERROR(VLOOKUP(Tabela1[[#This Row],[Placa]],'Base Cadastro '!A:B,2,FALSE),"Correção de cadastro") -> E-Jumpy Furgão 2P | G58: 49329 | H58: Bateria; carregador; Pane eletrica: | I58: 45945 | J58: Julia | K58: Manutenção | L58: Corretiva | M58: Aprovado | P58: =VLOOKUP(Tabela1[[#This Row],[Placa]],'Base Cadastro '!A:M,13,FALSE) -> SCE1 | Q58: MERCADO LIVRE | R58: C/Reserva | S58: 45989 | U58: =IFERROR(DATEDIF(Tabela1[[#This Row],[Data Agenda]],Tabela1[[#This Row],[Liberado]],"D"),DATEDIF(Tabela1[[#This Row],[Data Agenda]],TODAY(),"D")) -> 33 | V58: =IF(Tabela1[[#This Row],[D+Manut]]<=2,"Dentro do Prazo","Fora do Prazo") -> Fora do Prazo | W58: Pigalle Veículos ( localiza) | X58: GLEUMA | Y58: Out | Z58: =VLOOKUP(Tabela1[[#This Row],[Placa]],DadosViagem5[[Placa]:[Base]],11,FALSE) -> SC (FORTALEZA) SCE1
E59: QPC0J27 | F59: =IFERROR(VLOOKUP(Tabela1[[#This Row],[Placa]],'Base Cadastro '!A:B,2,FALSE),"Correção de cadastro") -> MASTER FURGAO L1 | G59: 160250 | H59: veiculo levado para oficina do alair 28/10 para fazer motor e turbina, Vazamento na turbina | I59: 45950 | J59: Sara | K59: Manutenção | L59: Corretiva | M59: Aprovado | N59: R$ 10442,85,00 | P59: =VLOOKUP(Tabela1[[#This Row],[Placa]],'Base Cadastro '!A:M,13,FALSE) -> SPR5 | Q59: MERCADO LIVRE | R59: Motor | S59: 45989 | U59: =IFERROR(DATEDIF(Tabela1[[#This Row],[Data Agenda]],Tabela1[[#This Row],[Liberado]],"D"),DATEDIF(Tabela1[[#This Row],[Data Agenda]],TODAY(),"D")) -> 28 | V59: =IF(Tabela1[[#This Row],[D+Manut]]<=2,"Dentro do Prazo","Fora do Prazo") -> Fora do Prazo | W59: Oficina do Alair | X59: MATHEUS | Y59: Out | Z59: =VLOOKUP(Tabela1[[#This Row],[Placa]],DadosViagem5[[Placa]:[Base]],11,FALSE) -> SC (GUARAPUAVA) SPR5
D60: 6787233 | E60: RFV4G68 | F60: =IFERROR(VLOOKUP(Tabela1[[#This Row],[Placa]],'Base Cadastro '!A:B,2,FALSE),"Correção de cadastro") -> Kangoo Z.E. MAXI 2 L | G60: 38598 | H60: Caixa de marcha completa, parachoque, friso, painel, farol | I60: 45811 | J60: Julia | K60: Manutenção | L60: Corretiva | M60: Aprovado | P60: =VLOOKUP(Tabela1[[#This Row],[Placa]],'Base Cadastro '!A:M,13,FALSE) -> SSP1 | Q60: MERCADO LIVRE | R60: C/Reserva | S60: 45990 | U60: =IFERROR(DATEDIF(Tabela1[[#This Row],[Data Agenda]],Tabela1[[#This Row],[Liberado]],"D"),DATEDIF(Tabela1[[#This Row],[Data Agenda]],TODAY(),"D")) -> 167 | V60: =IF(Tabela1[[#This Row],[D+Manut]]<=2,"Dentro do Prazo","Fora do Prazo") -> Fora do Prazo | W60: MONTANAS CAR (Localiza) | X60: DOMENICO | Y60: Jun | Z60: =VLOOKUP(Tabela1[[#This Row],[Placa]],DadosViagem5[[Placa]:[Base]],11,FALSE) -> SC (MOOCA CENTRO) SSP21
E61: IUM0320 | F61: =IFERROR(VLOOKUP(Tabela1[[#This Row],[Placa]],'Base Cadastro '!A:B,2,FALSE),"Correção de cadastro") -> Fiorino Endurance Evo 1.4 2P | H61: Veículo sofreu um capotamento | I61: 45883 | J61: Vinicius | K61: Sinistro | L61: Corretiva | M61: Negociando | P61: SRS1 | Q61: MERCADO LIVRE | R61: Sinistro | S61: 45990 | U61: =IFERROR(DATEDIF(Tabela1[[#This Row],[Data Agenda]],Tabela1[[#This Row],[Liberado]],"D"),DATEDIF(Tabela1[[#This Row],[Data Agenda]],TODAY(),"D")) -> 95 | V61: =IF(Tabela1[[#This Row],[D+Manut]]<=2,"Dentro do Prazo","Fora do Prazo") -> Fora do Prazo | W61: Safety Car | X61: Mateus Rodrigues | Y61: Out | Z61: =VLOOKUP(Tabela1[[#This Row],[Placa]],DadosViagem5[[Placa]:[Base]],11,FALSE) -> SC (PORTO ALEGRE) SRS1
E62: SGF8J33 | F62: =IFERROR(VLOOKUP(Tabela1[[#This Row],[Placa]],'Base Cadastro '!A:B,2,FALSE),"Correção de cadastro") -> TRANSIT CHASSI | G62: 46272 | H62: Veículo apreendido. | I62: 45884 | J62: Vinicius | K62: Sinistro | L62: Corretiva | M62: Aprovado | N62: 6971.86 | O62: 6971.86 | P62: =VLOOKUP(Tabela1[[#This Row],[Placa]],'Base Cadastro '!A:M,13,FALSE) -> SSP4 | Q62: MERCADO LIVRE | R62: Sinistro | S62: 45991 | U62: =IFERROR(DATEDIF(Tabela1[[#This Row],[Data Agenda]],Tabela1[[#This Row],[Liberado]],"D"),DATEDIF(Tabela1[[#This Row],[Data Agenda]],TODAY(),"D")) -> 94 | V62: =IF(Tabela1[[#This Row],[D+Manut]]<=2,"Dentro do Prazo","Fora do Prazo") -> Fora do Prazo | W62: Pátio da D.E.R (Departamento de estradas e rodagens) | X62: Deborah | Y62: Ago | Z62: =VLOOKUP(Tabela1[[#This Row],[Placa]],DadosViagem5[[Placa]:[Base]],11,FALSE) -> SC (RIBEIRAO PRETO) SSP4
E63: SDQ2C01 | F63: =IFERROR(VLOOKUP(Tabela1[[#This Row],[Placa]],'Base Cadastro '!A:B,2,FALSE),"Correção de cadastro") -> Kangoo Z.E. MAXI 5 Lugares 2P | G63: 59194 | H63: Funilaria na porta lateral. | I63: 45867 | J63: Isabelli | K63: Sinistro | L63: Corretiva | M63: Aprovado | N63: 5600 | O63: 5600 | P63: =VLOOKUP(Tabela1[[#This Row],[Placa]],'Base Cadastro '!A:M,13,FALSE) -> SSC2 | Q63: MERCADO LIVRE | R63: Sinistro | U63: =IFERROR(DATEDIF(Tabela1[[#This Row],[Data Agenda]],Tabela1[[#This Row],[Liberado]],"D"),DATEDIF(Tabela1[[#This Row],[Data Agenda]],TODAY(),"D")) -> 111 | V63: =IF(Tabela1[[#This Row],[D+Manut]]<=2,"Dentro do Prazo","Fora do Prazo") -> Fora do Prazo | W63: França pneus | X63: CARLOS SELL | Y63: Set | Z63: =VLOOKUP(Tabela1[[#This Row],[Placa]],DadosViagem5[[Placa]:[Base]],11,FALSE) -> SC (FLORIANOPOLIS) SSC2
E64: SFW0A40 | F64: =IFERROR(VLOOKUP(Tabela1[[#This Row],[Placa]],'Base Cadastro '!A:B,2,FALSE),"Correção de cadastro") -> TRANSIT FURGÃO | G64: N/E | H64: Colisão dianteira grave / Colisão Frontal | I64: 45587 | J64: Isabelli | K64: Sinistro | L64: Corretiva | M64: Aprovado | N64: 28030 | O64: 28030 | P64: =VLOOKUP(Tabela1[[#This Row],[Placa]],'Base Cadastro '!A:M,13,FALSE) -> SSC4 | Q64: MERCADO LIVRE | R64: Sinistro | S64: 45992 | U64: =IFERROR(DATEDIF(Tabela1[[#This Row],[Data Agenda]],Tabela1[[#This Row],[Liberado]],"D"),DATEDIF(Tabela1[[#This Row],[Data Agenda]],TODAY(),"D")) -> 391 | V64: =IF(Tabela1[[#This Row],[D+Manut]]<=2,"Dentro do Prazo","Fora do Prazo") -> Fora do Prazo | W64: Duti Reparações Automotivos | X64: JULIANO | Y64: Set | Z64: =VLOOKUP(Tabela1[[#This Row],[Placa]],DadosViagem5[[Placa]:[Base]],11,FALSE) -> SC (CHAPECO) SSC4
E65: GFV1C44 | F65: =IFERROR(VLOOKUP(Tabela1[[#This Row],[Placa]],'Base Cadastro '!A:B,2,FALSE),"Correção de cadastro") -> Sprinter 313 | G65: 117838 | H65: Veículo está realizando a funilaria do teto | I65: 45847 | J65: Vinicius | K65: Sinistro | L65: Corretiva | M65: Aprovado | N65: 18635 | O65: 16000 | P65: =VLOOKUP(Tabela1[[#This Row],[Placa]],'Base Cadastro '!A:M,13,FALSE) -> GP02 | Q65: GRUPO PEREIRA | R65: Sinistro | S65: 45992 | U65: =IFERROR(DATEDIF(Tabela1[[#This Row],[Data Agenda]],Tabela1[[#This Row],[Liberado]],"D"),DATEDIF(Tabela1[[#This Row],[Data Agenda]],TODAY(),"D")) -> 131 | V65: =IF(Tabela1[[#This Row],[D+Manut]]<=2,"Dentro do Prazo","Fora do Prazo") -> Fora do Prazo | W65: GR Car | X65: Renato | Y65: Set | Z65: =VLOOKUP(Tabela1[[#This Row],[Placa]],DadosViagem5[[Placa]:[Base]],11,FALSE) -> GP02 JACAREI (GRUPO PEREIRA)
E66: SGH6H71 | F66: =IFERROR(VLOOKUP(Tabela1[[#This Row],[Placa]],'Base Cadastro '!A:B,2,FALSE),"Correção de cadastro") -> TRANSIT FURGÃO | G66: N/E | H66: Colisão lateral | I66: 45587 | J66: Isabelli | K66: Sinistro | L66: Corretiva | M66: Aprovado | N66: 5294.81 | O66: 5294.81 | P66: =VLOOKUP(Tabela1[[#This Row],[Placa]],'Base Cadastro '!A:M,13,FALSE) -> SRS10 | Q66: MERCADO LIVRE | R66: Sinistro | S66: 46006 | U66: =IFERROR(DATEDIF(Tabela1[[#This Row],[Data Agenda]],Tabela1[[#This Row],[Liberado]],"D"),DATEDIF(Tabela1[[#This Row],[Data Agenda]],TODAY(),"D")) -> 391 | V66: =IF(Tabela1[[#This Row],[D+Manut]]<=2,"Dentro do Prazo","Fora do Prazo") -> Fora do Prazo | W66: Safety Car | X66: FERNANDA | Y66: Set | Z66: =VLOOKUP(Tabela1[[#This Row],[Placa]],DadosViagem5[[Placa]:[Base]],11,FALSE) -> SC (LAJEADO) SRS10
E67: RVC0J81 | F67: =IFERROR(VLOOKUP(Tabela1[[#This Row],[Placa]],'Base Cadastro '!A:B,2,FALSE),"Correção de cadastro") -> MB Accelo 815 MT 4x2 4.8 2P | H67: Veículo sofreu um capotamento | I67: 45944 | J67: Vinicius | K67: Sinistro | L67: Corretiva | M67: Aprovado | N67: 27655 | O67: 27655 | P67: =VLOOKUP(Tabela1[[#This Row],[Placa]],'Base Cadastro '!A:M,13,FALSE) -> BRRC01 | Q67: MERCADO LIVRE | R67: Sinistro | S67: 46006 | U67: =IFERROR(DATEDIF(Tabela1[[#This Row],[Data Agenda]],Tabela1[[#This Row],[Liberado]],"D"),DATEDIF(Tabela1[[#This Row],[Data Agenda]],TODAY(),"D")) -> 34 | V67: =IF(Tabela1[[#This Row],[D+Manut]]<=2,"Dentro do Prazo","Fora do Prazo") -> Fora do Prazo | W67: Central Truck | X67: Bruno | Y67: Out | Z67: =VLOOKUP(Tabela1[[#This Row],[Placa]],DadosViagem5[[Placa]:[Base]],11,FALSE) -> SC (FULL FILMENTE) FULL
E68: SGH8C34 | F68: =IFERROR(VLOOKUP(Tabela1[[#This Row],[Placa]],'Base Cadastro '!A:B,2,FALSE),"Correção de cadastro") -> TRANSIT FURGÃO | G68: N/E | H68: Embreagem | I68: 45938 | J68: Hillary | K68: Manutenção | L68: Corretiva | M68: Aprovado | P68: =VLOOKUP(Tabela1[[#This Row],[Placa]],'Base Cadastro '!A:M,13,FALSE) -> SRS8 | Q68: MERCADO LIVRE | R68: Em Manutenção | S68: 18/112025 | U68: =IFERROR(DATEDIF(Tabela1[[#This Row],[Data Agenda]],Tabela1[[#This Row],[Liberado]],"D"),DATEDIF(Tabela1[[#This Row],[Data Agenda]],TODAY(),"D")) -> 40 | V68: =IF(Tabela1[[#This Row],[D+Manut]]<=2,"Dentro do Prazo","Fora do Prazo") -> Fora do Prazo | W68: Safety Car | X68: Alessandra | Y68: Out | Z68: =VLOOKUP(Tabela1[[#This Row],[Placa]],DadosViagem5[[Placa]:[Base]],11,FALSE) -> SC (SAPUCAIA) SRS8
E69: SUV1C98 | F69: =IFERROR(VLOOKUP(Tabela1[[#This Row],[Placa]],'Base Cadastro '!A:B,2,FALSE),"Correção de cadastro") -> MASTER FURGAO L1 | G69: N/E | H69: Placa parada para fazer o freio e semi eixo - Placa vai descer para o Rafa guincho no dia de hj pois a oficina anterior não faz Cambio 06/11/2025 - Em contato com a oficina, o mesmo me informou que tem um orçamento para abrir a semi eixo - Aguardando orçamento para levantar e-mail 13/11/2025 | I69: 45959 | J69: Carla I. | K69: Manutenção | L69: Corretiva | M69: Negociando | N69: 2600 | O69: 2300 | P69: =VLOOKUP(Tabela1[[#This Row],[Placa]],'Base Cadastro '!A:M,13,FALSE) -> SSP16 | Q69: MERCADO LIVRE | R69: Em Manutenção | S69: Aguardando Aprovação | U69: =IFERROR(DATEDIF(Tabela1[[#This Row],[Data Agenda]],Tabela1[[#This Row],[Liberado]],"D"),DATEDIF(Tabela1[[#This Row],[Data Agenda]],TODAY(),"D")) -> 19 | V69: =IF(Tabela1[[#This Row],[D+Manut]]<=2,"Dentro do Prazo","Fora do Prazo") -> Fora do Prazo | W69: Rafa Guincho | X69: CAMILA | Y69: Out | Z69: =VLOOKUP(Tabela1[[#This Row],[Placa]],DadosViagem5[[Placa]:[Base]],11,FALSE) -> SC (CARAGUATATUBA) SSP16
D70: 6838378 | E70: RUX6F61 | F70: =IFERROR(VLOOKUP(Tabela1[[#This Row],[Placa]],'Base Cadastro '!A:B,2,FALSE),"Correção de cadastro") -> Fiorino Endurance Evo 1.4 2P | G70: 130989 | H70: Colisão Frontal com poste | I70: 45848 | J70: Vinicius | K70: Sinistro | L70: Corretiva | M70: Negociando | P70: =VLOOKUP(Tabela1[[#This Row],[Placa]],'Base Cadastro '!A:M,13,FALSE) -> SPR3 | Q70: MERCADO LIVRE | R70: Sinistro | S70: Aguardando Aprovação | U70: =IFERROR(DATEDIF(Tabela1[[#This Row],[Data Agenda]],Tabela1[[#This Row],[Liberado]],"D"),DATEDIF(Tabela1[[#This Row],[Data Agenda]],TODAY(),"D")) -> 130 | V70: =IF(Tabela1[[#This Row],[D+Manut]]<=2,"Dentro do Prazo","Fora do Prazo") -> Fora do Prazo | W70: Oficina (MOVIDA) | X70: Carolina/Edgard | Y70: Jul | Z70: =VLOOKUP(Tabela1[[#This Row],[Placa]],DadosViagem5[[Placa]:[Base]],11,FALSE) -> SC (CASCAVEL) SPR3
E71: FOM3F69 | F71: =IFERROR(VLOOKUP(Tabela1[[#This Row],[Placa]],'Base Cadastro '!A:B,2,FALSE),"Correção de cadastro") -> CITROEN JUMPY | G71: 7706 | H71: Pane elétrica-foi da autovans pro alair dia 06/11 | I71: 45902 | J71: Sara | K71: Manutenção | L71: Corretiva | M71: Negociando | P71: =VLOOKUP(Tabela1[[#This Row],[Placa]],'Base Cadastro '!A:M,13,FALSE) -> SPR2 | Q71: MERCADO LIVRE | R71: Motor | S71: Aguardando Aprovação | U71: =IFERROR(DATEDIF(Tabela1[[#This Row],[Data Agenda]],Tabela1[[#This Row],[Liberado]],"D"),DATEDIF(Tabela1[[#This Row],[Data Agenda]],TODAY(),"D")) -> 76 | V71: =IF(Tabela1[[#This Row],[D+Manut]]<=2,"Dentro do Prazo","Fora do Prazo") -> Fora do Prazo | W71: Oficina do Alair | X71: EDGARD | Y71: Out | Z71: =VLOOKUP(Tabela1[[#This Row],[Placa]],DadosViagem5[[Placa]:[Base]],11,FALSE) -> SC (LONDRINA) SPR2
E72: SGK7E21 | F72: =IFERROR(VLOOKUP(Tabela1[[#This Row],[Placa]],'Base Cadastro '!A:B,2,FALSE),"Correção de cadastro") -> TRANSIT FURGÃO | G72: 32123 | H72: Embreagem | I72: 45945 | J72: Hillary | K72: Manutenção | L72: Corretiva | M72: Negociando | P72: =VLOOKUP(Tabela1[[#This Row],[Placa]],'Base Cadastro '!A:M,13,FALSE) -> SSP40 | Q72: MERCADO LIVRE | R72: Em Manutenção | S72: Aguardando Aprovação | U72: =IFERROR(DATEDIF(Tabela1[[#This Row],[Data Agenda]],Tabela1[[#This Row],[Liberado]],"D"),DATEDIF(Tabela1[[#This Row],[Data Agenda]],TODAY(),"D")) -> 33 | V72: =IF(Tabela1[[#This Row],[D+Manut]]<=2,"Dentro do Prazo","Fora do Prazo") -> Fora do Prazo | W72: Ford Studio Guarulhos | X72: KARINA | Y72: Out | Z72: =VLOOKUP(Tabela1[[#This Row],[Placa]],DadosViagem5[[Placa]:[Base]],11,FALSE) -> SC (PQ NOVO MUNDO) SSP40
E73: GDM4G44 | F73: =IFERROR(VLOOKUP(Tabela1[[#This Row],[Placa]],'Base Cadastro '!A:B,2,FALSE),"Correção de cadastro") -> Sprinter 313 | G73: 870000 | H73: Bomba e bico | I73: 45807 | J73: Natallia | K73: Manutenção | L73: Corretiva | M73: Negociando | P73: =VLOOKUP(Tabela1[[#This Row],[Placa]],'Base Cadastro '!A:M,13,FALSE) -> SSC5 | Q73: MERCADO LIVRE | R73: Em Manutenção | S73: Aguardando aprovação | U73: =IFERROR(DATEDIF(Tabela1[[#This Row],[Data Agenda]],Tabela1[[#This Row],[Liberado]],"D"),DATEDIF(Tabela1[[#This Row],[Data Agenda]],TODAY(),"D")) -> 171 | V73: =IF(Tabela1[[#This Row],[D+Manut]]<=2,"Dentro do Prazo","Fora do Prazo") -> Fora do Prazo | W73: Mecanitruck | X73: REGIANE | Y73: Mai | Z73: =VLOOKUP(Tabela1[[#This Row],[Placa]],DadosViagem5[[Placa]:[Base]],11,FALSE) -> SC (CRICIUMA) SSC5
E74: RUX2B70 | F74: =IFERROR(VLOOKUP(Tabela1[[#This Row],[Placa]],'Base Cadastro '!A:B,2,FALSE),"Correção de cadastro") -> Partner Rapid Business Pack 1.4 2P | G74: N/E | H74: Luz do oléo ascendeu e o carro ta oscilando | I74: 45966 | J74: Sara | K74: Manutenção | L74: Corretiva | M74: Negociando | P74: =VLOOKUP(Tabela1[[#This Row],[Placa]],'Base Cadastro '!A:M,13,FALSE) -> SPR1 | Q74: MERCADO LIVRE | R74: Motor | S74: Aguardando aprovação | U74: =IFERROR(DATEDIF(Tabela1[[#This Row],[Data Agenda]],Tabela1[[#This Row],[Liberado]],"D"),DATEDIF(Tabela1[[#This Row],[Data Agenda]],TODAY(),"D")) -> 12 | V74: =IF(Tabela1[[#This Row],[D+Manut]]<=2,"Dentro do Prazo","Fora do Prazo") -> Fora do Prazo | W74: FSP | X74: RENATA | Y74: Nov | Z74: =VLOOKUP(Tabela1[[#This Row],[Placa]],DadosViagem5[[Placa]:[Base]],11,FALSE) -> SC (CURITIBA) SPR1
E75: RUX2B91 | F75: =IFERROR(VLOOKUP(Tabela1[[#This Row],[Placa]],'Base Cadastro '!A:B,2,FALSE),"Correção de cadastro") -> Partner Rapid Business Pack 1.4 2P | G75: N/E | H75: Caixa de câmbio | I75: 45917 | J75: Sara | K75: Manutenção | L75: Corretiva | M75: Negociando | P75: =VLOOKUP(Tabela1[[#This Row],[Placa]],'Base Cadastro '!A:M,13,FALSE) -> SPR1 | Q75: MERCADO LIVRE | R75: Em Manutenção | S75: Aguardando aprovação | U75: =IFERROR(DATEDIF(Tabela1[[#This Row],[Data Agenda]],Tabela1[[#This Row],[Liberado]],"D"),DATEDIF(Tabela1[[#This Row],[Data Agenda]],TODAY(),"D")) -> 61 | V75: =IF(Tabela1[[#This Row],[D+Manut]]<=2,"Dentro do Prazo","Fora do Prazo") -> Fora do Prazo | W75: FSP | X75: RENATA | Y75: Set | Z75: =VLOOKUP(Tabela1[[#This Row],[Placa]],DadosViagem5[[Placa]:[Base]],11,FALSE) -> SC (CURITIBA) SPR1
E76: RNJ9C97 | F76: =IFERROR(VLOOKUP(Tabela1[[#This Row],[Placa]],'Base Cadastro '!A:B,2,FALSE),"Correção de cadastro") -> Master Furgão 8m³ | G76: N/E | H76: Pane Elétrica | I76: 45968 | J76: Sara | K76: Manutenção | L76: Corretiva | M76: Negociando | P76: =VLOOKUP(Tabela1[[#This Row],[Placa]],'Base Cadastro '!A:M,13,FALSE) -> SPR8 | Q76: MERCADO LIVRE | R76: Em Manutenção | S76: Aguardando aprovação | U76: =IFERROR(DATEDIF(Tabela1[[#This Row],[Data Agenda]],Tabela1[[#This Row],[Liberado]],"D"),DATEDIF(Tabela1[[#This Row],[Data Agenda]],TODAY(),"D")) -> 10 | V76: =IF(Tabela1[[#This Row],[D+Manut]]<=2,"Dentro do Prazo","Fora do Prazo") -> Fora do Prazo | W76: FSP | X76: TUANY | Y76: Nov | Z76: =VLOOKUP(Tabela1[[#This Row],[Placa]],DadosViagem5[[Placa]:[Base]],11,FALSE) -> SC (CAMPINA GRANDE DO SUL) SPR8
E77: RUW5D78 | F77: =IFERROR(VLOOKUP(Tabela1[[#This Row],[Placa]],'Base Cadastro '!A:B,2,FALSE),"Correção de cadastro") -> Partner Rapid Business Pack 1.4 2P | G77: 84039 | H77: Freio Homocinética Troca de óleo e filtro E paletas do para brisa | I77: 45971 | J77: Sara | K77: Manutenção | L77: Corretiva | M77: Negociando | P77: =VLOOKUP(Tabela1[[#This Row],[Placa]],'Base Cadastro '!A:M,13,FALSE) -> SPR7 | Q77: MERCADO LIVRE | R77: Em Manutenção | S77: Aguardando aprovação | U77: =IFERROR(DATEDIF(Tabela1[[#This Row],[Data Agenda]],Tabela1[[#This Row],[Liberado]],"D"),DATEDIF(Tabela1[[#This Row],[Data Agenda]],TODAY(),"D")) -> 7 | V77: =IF(Tabela1[[#This Row],[D+Manut]]<=2,"Dentro do Prazo","Fora do Prazo") -> Fora do Prazo | W77: comercial Automotiva S.a. (Movida) | X77: ADRIELLE | Y77: Nov | Z77: =VLOOKUP(Tabela1[[#This Row],[Placa]],DadosViagem5[[Placa]:[Base]],11,FALSE) -> SC (PONTA GROSSA) SPR7
E78: RNP6E41 | F78: =IFERROR(VLOOKUP(Tabela1[[#This Row],[Placa]],'Base Cadastro '!A:B,2,FALSE),"Correção de cadastro") -> Master Furgão 8m³ | G78: 107475 | H78: Bateria | I78: 45959 | J78: Sara | K78: Manutenção | L78: Corretiva | M78: Negociando | P78: =VLOOKUP(Tabela1[[#This Row],[Placa]],'Base Cadastro '!A:M,13,FALSE) -> SPR3 | Q78: MERCADO LIVRE | R78: Em Manutenção | S78: Aguardando Aprovação | U78: =IFERROR(DATEDIF(Tabela1[[#This Row],[Data Agenda]],Tabela1[[#This Row],[Liberado]],"D"),DATEDIF(Tabela1[[#This Row],[Data Agenda]],TODAY(),"D")) -> 19 | V78: =IF(Tabela1[[#This Row],[D+Manut]]<=2,"Dentro do Prazo","Fora do Prazo") -> Fora do Prazo | W78: Autentica | X78: CAROLINA | Y78: Nov | Z78: =VLOOKUP(Tabela1[[#This Row],[Placa]],DadosViagem5[[Placa]:[Base]],11,FALSE) -> SC (CASCAVEL) SPR3
E79: RVA2J57 | F79: =IFERROR(VLOOKUP(Tabela1[[#This Row],[Placa]],'Base Cadastro '!A:B,2,FALSE),"Correção de cadastro") -> MASTER FURGAO L1 | G79: 67990 | H79: Troca de bateria | I79: 45928 | J79: Sara | K79: Manutenção | L79: Corretiva | M79: Aprovado | P79: =VLOOKUP(Tabela1[[#This Row],[Placa]],'Base Cadastro '!A:M,13,FALSE) -> SPR1 | Q79: MERCADO LIVRE | R79: Em Manutenção | S79: Aguardando Aprovação | U79: =IFERROR(DATEDIF(Tabela1[[#This Row],[Data Agenda]],Tabela1[[#This Row],[Liberado]],"D"),DATEDIF(Tabela1[[#This Row],[Data Agenda]],TODAY(),"D")) -> 50 | V79: =IF(Tabela1[[#This Row],[D+Manut]]<=2,"Dentro do Prazo","Fora do Prazo") -> Fora do Prazo | W79: FSP | X79: RENATA | Y79: Out | Z79: =VLOOKUP(Tabela1[[#This Row],[Placa]],DadosViagem5[[Placa]:[Base]],11,FALSE) -> SC (CURITIBA) SPR1
E80: TOE7C71 | F80: =IFERROR(VLOOKUP(Tabela1[[#This Row],[Placa]],'Base Cadastro '!A:B,2,FALSE),"Correção de cadastro") -> TRANSIT FURGÃO | G80: 10203 | H80: Veículo foi encaminhado para a Ford por conta de pane elétrica | I80: 45924 | J80: Hillary | K80: Manutenção | L80: Corretiva | M80: Negociando | P80: =VLOOKUP(Tabela1[[#This Row],[Placa]],'Base Cadastro '!A:M,13,FALSE) -> SBA1 | Q80: MERCADO LIVRE | R80: Em Manutenção | S80: Aguardando Aprovação Ford | U80: =IFERROR(DATEDIF(Tabela1[[#This Row],[Data Agenda]],Tabela1[[#This Row],[Liberado]],"D"),DATEDIF(Tabela1[[#This Row],[Data Agenda]],TODAY(),"D")) -> 54 | V80: =IF(Tabela1[[#This Row],[D+Manut]]<=2,"Dentro do Prazo","Fora do Prazo") -> Fora do Prazo | W80: Ford indiana | X80: CORREIA | Y80: Set | Z80: =VLOOKUP(Tabela1[[#This Row],[Placa]],DadosViagem5[[Placa]:[Base]],11,FALSE) -> SC (BAHIA SALVADOR) SBA1
E81: SFT5A52 | F81: =IFERROR(VLOOKUP(Tabela1[[#This Row],[Placa]],'Base Cadastro '!A:B,2,FALSE),"Correção de cadastro") -> TRANSIT FURGÃO | G81: 37260 | H81: Bomba e Bico Injetor | I81: 45926 | J81: Hillary | K81: Manutenção | L81: Corretiva | M81: Negociando | P81: =VLOOKUP(Tabela1[[#This Row],[Placa]],'Base Cadastro '!A:M,13,FALSE) -> SSP37 | Q81: MERCADO LIVRE | R81: Em Manutenção | S81: Aguardando aprovação Ford | U81: =IFERROR(DATEDIF(Tabela1[[#This Row],[Data Agenda]],Tabela1[[#This Row],[Liberado]],"D"),DATEDIF(Tabela1[[#This Row],[Data Agenda]],TODAY(),"D")) -> 52 | V81: =IF(Tabela1[[#This Row],[D+Manut]]<=2,"Dentro do Prazo","Fora do Prazo") -> Fora do Prazo | W81: Ford Caminho | X81: KAREN | Y81: Set | Z81: =VLOOKUP(Tabela1[[#This Row],[Placa]],DadosViagem5[[Placa]:[Base]],11,FALSE) -> SC (3 CAMPINAS ) SSP3
E82: SGF8I96 | F82: =IFERROR(VLOOKUP(Tabela1[[#This Row],[Placa]],'Base Cadastro '!A:B,2,FALSE),"Correção de cadastro") -> TRANSIT CHASSI | G82: N/E | H82: Embreagem | I82: 45959 | J82: Hillary | K82: Manutenção | L82: Corretiva | M82: Negociando | P82: =VLOOKUP(Tabela1[[#This Row],[Placa]],'Base Cadastro '!A:M,13,FALSE) -> MM03 | Q82: MERCADO LIVRE | R82: Em Manutenção | S82: Aguardando aprovação Ford | U82: =IFERROR(DATEDIF(Tabela1[[#This Row],[Data Agenda]],Tabela1[[#This Row],[Liberado]],"D"),DATEDIF(Tabela1[[#This Row],[Data Agenda]],TODAY(),"D")) -> 19 | V82: =IF(Tabela1[[#This Row],[D+Manut]]<=2,"Dentro do Prazo","Fora do Prazo") -> Fora do Prazo | W82: Ford Studio Guarulhos | X82: RODRIGO | Y82: Out | Z82: =VLOOKUP(Tabela1[[#This Row],[Placa]],DadosViagem5[[Placa]:[Base]],11,FALSE) -> MM03 (ARUJA)
E83: SFV0D53 | F83: =IFERROR(VLOOKUP(Tabela1[[#This Row],[Placa]],'Base Cadastro '!A:B,2,FALSE),"Correção de cadastro") -> TRANSIT FURGÃO | G83: 35620 | H83: Pane életrica | I83: 45960 | J83: Hillary | K83: Manutenção | L83: Corretiva | M83: Negociando | P83: =VLOOKUP(Tabela1[[#This Row],[Placa]],'Base Cadastro '!A:M,13,FALSE) -> SSP30 | Q83: MERCADO LIVRE | R83: Em Manutenção | S83: Aguardando aprovação Ford | U83: =IFERROR(DATEDIF(Tabela1[[#This Row],[Data Agenda]],Tabela1[[#This Row],[Liberado]],"D"),DATEDIF(Tabela1[[#This Row],[Data Agenda]],TODAY(),"D")) -> 18 | V83: =IF(Tabela1[[#This Row],[D+Manut]]<=2,"Dentro do Prazo","Fora do Prazo") -> Fora do Prazo | W83: Ford Studio Guarulhos | X83: KARINA | Y83: Out | Z83: =VLOOKUP(Tabela1[[#This Row],[Placa]],DadosViagem5[[Placa]:[Base]],11,FALSE) -> SC (MEGA GUARULHOS) SSP30
E84: SGF8J97 | F84: =IFERROR(VLOOKUP(Tabela1[[#This Row],[Placa]],'Base Cadastro '!A:B,2,FALSE),"Correção de cadastro") -> TRANSIT CHASSI | G84: N/E | H84: Embreagem | I84: 45971 | J84: Hillary | K84: Manutenção | L84: Corretiva | M84: Negociando | P84: =VLOOKUP(Tabela1[[#This Row],[Placa]],'Base Cadastro '!A:M,13,FALSE) -> MM03 | Q84: GRUPO PEREIRA | R84: Em Manutenção | S84: Aguardando aprovação Ford | U84: =IFERROR(DATEDIF(Tabela1[[#This Row],[Data Agenda]],Tabela1[[#This Row],[Liberado]],"D"),DATEDIF(Tabela1[[#This Row],[Data Agenda]],TODAY(),"D")) -> 7 | V84: =IF(Tabela1[[#This Row],[D+Manut]]<=2,"Dentro do Prazo","Fora do Prazo") -> Fora do Prazo | W84: Ford Sumare | X84: ALEXANDRE | Y84: Nov | Z84: =VLOOKUP(Tabela1[[#This Row],[Placa]],DadosViagem5[[Placa]:[Base]],11,FALSE) -> MM03 (ARUJA)
E85: SGF8I77 | F85: =IFERROR(VLOOKUP(Tabela1[[#This Row],[Placa]],'Base Cadastro '!A:B,2,FALSE),"Correção de cadastro") -> TRANSIT CHASSI | G85: N/E | H85: Embreagem | I85: 45971 | J85: Hillary | K85: Manutenção | L85: Corretiva | M85: Negociando | P85: =VLOOKUP(Tabela1[[#This Row],[Placa]],'Base Cadastro '!A:M,13,FALSE) -> MM03 | Q85: GRUPO PEREIRA | R85: Em Manutenção | S85: Aguardando aprovação Ford | U85: =IFERROR(DATEDIF(Tabela1[[#This Row],[Data Agenda]],Tabela1[[#This Row],[Liberado]],"D"),DATEDIF(Tabela1[[#This Row],[Data Agenda]],TODAY(),"D")) -> 7 | V85: =IF(Tabela1[[#This Row],[D+Manut]]<=2,"Dentro do Prazo","Fora do Prazo") -> Fora do Prazo | W85: Ford Studio Guarulhos | X85: ALEXANDRE | Y85: Nov | Z85: =VLOOKUP(Tabela1[[#This Row],[Placa]],DadosViagem5[[Placa]:[Base]],11,FALSE) -> MM03 (ARUJA)
E86: SGK7D53 | F86: =IFERROR(VLOOKUP(Tabela1[[#This Row],[Placa]],'Base Cadastro '!A:B,2,FALSE),"Correção de cadastro") -> TRANSIT FURGÃO | H86: REVISAO 40 MIL E TROCA DE PNEUS | I86: 45968 | J86: Hillary | K86: Manutenção | L86: Corretiva | M86: Negociando | P86: =VLOOKUP(Tabela1[[#This Row],[Placa]],'Base Cadastro '!A:M,13,FALSE) -> SSP42 | Q86: MERCADO LIVRE | R86: Em Manutenção | S86: Aguardando aprovação Ford | U86: =IFERROR(DATEDIF(Tabela1[[#This Row],[Data Agenda]],Tabela1[[#This Row],[Liberado]],"D"),DATEDIF(Tabela1[[#This Row],[Data Agenda]],TODAY(),"D")) -> 10 | V86: =IF(Tabela1[[#This Row],[D+Manut]]<=2,"Dentro do Prazo","Fora do Prazo") -> Fora do Prazo | W86: Ford Caoa Campinas | X86: Michele | Y86: Nov | Z86: =VLOOKUP(Tabela1[[#This Row],[Placa]],DadosViagem5[[Placa]:[Base]],11,FALSE) -> SC (ITUPEVA) SSP38
E87: SFW6D02 | F87: =IFERROR(VLOOKUP(Tabela1[[#This Row],[Placa]],'Base Cadastro '!A:B,2,FALSE),"Correção de cadastro") -> TRANSIT FURGÃO | H87: VEICULO GUINCHADO 10/11 BOMBA E BICO | I87: 45968 | J87: Hillary | K87: Manutenção | L87: Corretiva | M87: Negociando | P87: =VLOOKUP(Tabela1[[#This Row],[Placa]],'Base Cadastro '!A:M,13,FALSE) -> SSP42 | Q87: MERCADO LIVRE | R87: Em Manutenção | S87: Aguardando aprovação Ford | U87: =IFERROR(DATEDIF(Tabela1[[#This Row],[Data Agenda]],Tabela1[[#This Row],[Liberado]],"D"),DATEDIF(Tabela1[[#This Row],[Data Agenda]],TODAY(),"D")) -> 10 | V87: =IF(Tabela1[[#This Row],[D+Manut]]<=2,"Dentro do Prazo","Fora do Prazo") -> Fora do Prazo | W87: Ford Caoa Campinas | X87: Michele | Y87: Nov | Z87: =VLOOKUP(Tabela1[[#This Row],[Placa]],DadosViagem5[[Placa]:[Base]],11,FALSE) -> SC (ITUPEVA) SSP38
E88: SGK7A66 | F88: =IFERROR(VLOOKUP(Tabela1[[#This Row],[Placa]],'Base Cadastro '!A:B,2,FALSE),"Correção de cadastro") -> TRANSIT FURGÃO | H88: REVISAO 40 MIL E TROCA DE PNEUS | I88: 45968 | J88: Hillary | K88: Manutenção | L88: Corretiva | M88: Negociando | P88: =VLOOKUP(Tabela1[[#This Row],[Placa]],'Base Cadastro '!A:M,13,FALSE) -> SSP42 | Q88: MERCADO LIVRE | R88: Em Manutenção | S88: Aguardando aprovação Ford | U88: =IFERROR(DATEDIF(Tabela1[[#This Row],[Data Agenda]],Tabela1[[#This Row],[Liberado]],"D"),DATEDIF(Tabela1[[#This Row],[Data Agenda]],TODAY(),"D")) -> 10 | V88: =IF(Tabela1[[#This Row],[D+Manut]]<=2,"Dentro do Prazo","Fora do Prazo") -> Fora do Prazo | W88: Ford Caoa Campinas | X88: Michele | Y88: Nov | Z88: =VLOOKUP(Tabela1[[#This Row],[Placa]],DadosViagem5[[Placa]:[Base]],11,FALSE) -> SC (ITUPEVA) SSP38
E89: SGK7E17 | F89: I/FORD TRANSIT 350 FL | G89: N/E | H89: Pneus | I89: 45967 | J89: Hillary | K89: Manutenção | L89: Corretiva | M89: Negociando | P89: SSP13 | Q89: MERCADO LIVRE | R89: Em Manutenção | S89: Aguardando aprovação Ford | V89: =IF(Tabela1[[#This Row],[D+Manut]]<=2,"Dentro do Prazo","Fora do Prazo") -> Dentro do Prazo | W89: Ford caminho Bauru | X89: Nayara | Y89: Nov. | Z89: =VLOOKUP(Tabela1[[#This Row],[Placa]],DadosViagem5[[Placa]:[Base]],11,FALSE) -> SC (MARILIA) SSP13
E90: SGK7E92 | F90: I/FORD TRANSIT 350 FL | G90: N/E | H90: Pneus | I90: 45967 | J90: Hillary | K90: Manutenção | L90: Corretiva | M90: Negociando | P90: SSP13 | Q90: MERCADO LIVRE | R90: Em Manutenção | S90: Aguardando aprovação Ford | U90: =IFERROR(DATEDIF(Tabela1[[#This Row],[Data Agenda]],Tabela1[[#This Row],[Liberado]],"D"),DATEDIF(Tabela1[[#This Row],[Data Agenda]],TODAY(),"D")) -> 11 | V90: =IF(Tabela1[[#This Row],[D+Manut]]<=2,"Dentro do Prazo","Fora do Prazo") -> Fora do Prazo | W90: Ford caminho Bauru | X90: Nayara | Y90: Nov. | Z90: =VLOOKUP(Tabela1[[#This Row],[Placa]],DadosViagem5[[Placa]:[Base]],11,FALSE) -> #N/A
E91: SGF9B13 | F91: =IFERROR(VLOOKUP(Tabela1[[#This Row],[Placa]],'Base Cadastro '!A:B,2,FALSE),"Correção de cadastro") -> TRANSIT CHASSI | G91: 56555 | H91: Revisão 60 Mil KM | I91: 45970 | J91: Hillary | K91: Manutenção | L91: Corretiva | M91: Negociando | P91: =VLOOKUP(Tabela1[[#This Row],[Placa]],'Base Cadastro '!A:M,13,FALSE) -> SSP13 | Q91: MERCADO LIVRE | R91: Em Manutenção | S91: Aguardando aprovação Ford | U91: =IFERROR(DATEDIF(Tabela1[[#This Row],[Data Agenda]],Tabela1[[#This Row],[Liberado]],"D"),DATEDIF(Tabela1[[#This Row],[Data Agenda]],TODAY(),"D")) -> 8 | V91: =IF(Tabela1[[#This Row],[D+Manut]]<=2,"Dentro do Prazo","Fora do Prazo") -> Fora do Prazo | W91: Ford caminho Bauru | X91: Nayara | Y91: Nov. | Z91: =VLOOKUP(Tabela1[[#This Row],[Placa]],DadosViagem5[[Placa]:[Base]],11,FALSE) -> SC (MARILIA) SSP13
E92: SGH8H49 | F92: =IFERROR(VLOOKUP(Tabela1[[#This Row],[Placa]],'Base Cadastro '!A:B,2,FALSE),"Correção de cadastro") -> TRANSIT FURGÃO | G92: 23762 | H92: Colisão lateral | I92: 45730 | J92: Vinicius | K92: Sinistro | L92: Corretiva | M92: Não Aprovado | N92: 70863.31 | O92: 60000 | P92: =VLOOKUP(Tabela1[[#This Row],[Placa]],'Base Cadastro '!A:M,13,FALSE) -> SRS8 | Q92: MERCADO LIVRE | R92: Sinistro | S92: Aguardando Pagamento | U92: =IFERROR(DATEDIF(Tabela1[[#This Row],[Data Agenda]],Tabela1[[#This Row],[Liberado]],"D"),DATEDIF(Tabela1[[#This Row],[Data Agenda]],TODAY(),"D")) -> 248 | V92: =IF(Tabela1[[#This Row],[D+Manut]]<=2,"Dentro do Prazo","Fora do Prazo") -> Fora do Prazo | W92: Safety Car | X92: Alessandra | Y92: Mar | Z92: =VLOOKUP(Tabela1[[#This Row],[Placa]],DadosViagem5[[Placa]:[Base]],11,FALSE) -> SC (SAPUCAIA) SRS8
C93: Sim | E93: RVB7I22 | F93: =IFERROR(VLOOKUP(Tabela1[[#This Row],[Placa]],'Base Cadastro '!A:B,2,FALSE),"Correção de cadastro") -> TRANSIT FURGÃO | G93: 129678 | H93: Motor- negociando novo parceiro 29/09 | I93: 45643 | J93: Hillary | K93: Manutenção | L93: Corretiva | M93: Aprovado | P93: =VLOOKUP(Tabela1[[#This Row],[Placa]],'Base Cadastro '!A:M,13,FALSE) -> SSP14 | Q93: MERCADO LIVRE | R93: Motor | S93: Aguardando pagamento | U93: =IFERROR(DATEDIF(Tabela1[[#This Row],[Data Agenda]],Tabela1[[#This Row],[Liberado]],"D"),DATEDIF(Tabela1[[#This Row],[Data Agenda]],TODAY(),"D")) -> 335 | V93: =IF(Tabela1[[#This Row],[D+Manut]]<=2,"Dentro do Prazo","Fora do Prazo") -> Fora do Prazo | W93: Truck Center | X93: Leticia | Y93: Dez | Z93: =VLOOKUP(Tabela1[[#This Row],[Placa]],DadosViagem5[[Placa]:[Base]],11,FALSE) -> SC (BAURU) SSP14
C94: Sim | E94: GBT8G14 | F94: =IFERROR(VLOOKUP(Tabela1[[#This Row],[Placa]],'Base Cadastro '!A:B,2,FALSE),"Correção de cadastro") -> Sprinter 313 | G94: 25986 | H94: Motor-22/05 informação dada pela Amanda aguardando peça da mercedes a Murici ira fornecer/ aguardando peça | I94: 45762 | J94: Sara | K94: Manutenção | L94: Corretiva | M94: Negociando | P94: =VLOOKUP(Tabela1[[#This Row],[Placa]],'Base Cadastro '!A:M,13,FALSE) -> GP03 | Q94: GRUPO PEREIRA | R94: Motor | S94: Aguardando pagamento | U94: =IFERROR(DATEDIF(Tabela1[[#This Row],[Data Agenda]],Tabela1[[#This Row],[Liberado]],"D"),DATEDIF(Tabela1[[#This Row],[Data Agenda]],TODAY(),"D")) -> 216 | V94: =IF(Tabela1[[#This Row],[D+Manut]]<=2,"Dentro do Prazo","Fora do Prazo") -> Fora do Prazo | W94: Truck Center | X94: KETHLEEN | Y94: Abr | Z94: =VLOOKUP(Tabela1[[#This Row],[Placa]],DadosViagem5[[Placa]:[Base]],11,FALSE) -> GP03 HORTOLANDIA (GRUPO PEREIRA)
C95: Sim | E95: RUO6B67 | F95: =IFERROR(VLOOKUP(Tabela1[[#This Row],[Placa]],'Base Cadastro '!A:B,2,FALSE),"Correção de cadastro") -> MASTER FURGAO L1 | G95: 91457 | H95: 15/07 - Motor na retifica | I95: 45638 | J95: Khetlyn | K95: Manutenção | L95: Corretiva | M95: Negociando | P95: =VLOOKUP(Tabela1[[#This Row],[Placa]],'Base Cadastro '!A:M,13,FALSE) -> SSP3 | Q95: MERCADO LIVRE | R95: Motor | S95: Aguardando pagamento | U95: =IFERROR(DATEDIF(Tabela1[[#This Row],[Data Agenda]],Tabela1[[#This Row],[Liberado]],"D"),DATEDIF(Tabela1[[#This Row],[Data Agenda]],TODAY(),"D")) -> 340 | V95: =IF(Tabela1[[#This Row],[D+Manut]]<=2,"Dentro do Prazo","Fora do Prazo") -> Fora do Prazo | W95: Truck Center | X95: KAREN | Y95: Dez | Z95: =VLOOKUP(Tabela1[[#This Row],[Placa]],DadosViagem5[[Placa]:[Base]],11,FALSE) -> SC (1CAMPINAS) SSP3
E96: RUX2C67 | F96: =IFERROR(VLOOKUP(Tabela1[[#This Row],[Placa]],'Base Cadastro '!A:B,2,FALSE),"Correção de cadastro") -> Partner Rapid Business Pack 1.4 2P | G96: N/E | H96: Motor- Testando | I96: 45928 | J96: Natallia | K96: Manutenção | L96: Corretiva | M96: Aprovado | P96: =VLOOKUP(Tabela1[[#This Row],[Placa]],'Base Cadastro '!A:M,13,FALSE) -> SRS8 | Q96: MERCADO LIVRE | R96: Motor | S96: Aguardando pagamento | U96: =IFERROR(DATEDIF(Tabela1[[#This Row],[Data Agenda]],Tabela1[[#This Row],[Liberado]],"D"),DATEDIF(Tabela1[[#This Row],[Data Agenda]],TODAY(),"D")) -> 50 | V96: =IF(Tabela1[[#This Row],[D+Manut]]<=2,"Dentro do Prazo","Fora do Prazo") -> Fora do Prazo | W96: Safety Car | X96: LUCAS | Y96: Out | Z96: =VLOOKUP(Tabela1[[#This Row],[Placa]],DadosViagem5[[Placa]:[Base]],11,FALSE) -> SC (SAPUCAIA) SRS8
E97: RNJ9C39 | F97: =IFERROR(VLOOKUP(Tabela1[[#This Row],[Placa]],'Base Cadastro '!A:B,2,FALSE),"Correção de cadastro") -> Master Furgão 8m³ | G97: 10.000.0 | H97: Setor da direção | I97: 45953 | J97: Natallia | K97: Manutenção | L97: Corretiva | M97: Aprovado | P97: =VLOOKUP(Tabela1[[#This Row],[Placa]],'Base Cadastro '!A:M,13,FALSE) -> SRS1 | Q97: MERCADO LIVRE | R97: Em Manutenção | S97: Aguardando pagamento | U97: =IFERROR(DATEDIF(Tabela1[[#This Row],[Data Agenda]],Tabela1[[#This Row],[Liberado]],"D"),DATEDIF(Tabela1[[#This Row],[Data Agenda]],TODAY(),"D")) -> 25 | V97: =IF(Tabela1[[#This Row],[D+Manut]]<=2,"Dentro do Prazo","Fora do Prazo") -> Fora do Prazo | W97: Safety Car | X97: EVAILTON | Y97: Out | Z97: =VLOOKUP(Tabela1[[#This Row],[Placa]],DadosViagem5[[Placa]:[Base]],11,FALSE) -> SC (PORTO ALEGRE) SRS1
E98: RUX2C79 | F98: =IFERROR(VLOOKUP(Tabela1[[#This Row],[Placa]],'Base Cadastro '!A:B,2,FALSE),"Correção de cadastro") -> Partner Rapid Business Pack 1.4 2P | H98: Revisões gerais e suspensão | I98: 45967 | J98: Natallia | K98: Manutenção | L98: Corretiva | M98: Negociando | P98: =VLOOKUP(Tabela1[[#This Row],[Placa]],'Base Cadastro '!A:M,13,FALSE) -> SRS1 | Q98: MERCADO LIVRE | R98: Em Manutenção | S98: Aguardando pagamento | U98: =IFERROR(DATEDIF(Tabela1[[#This Row],[Data Agenda]],Tabela1[[#This Row],[Liberado]],"D"),DATEDIF(Tabela1[[#This Row],[Data Agenda]],TODAY(),"D")) -> 11 | V98: =IF(Tabela1[[#This Row],[D+Manut]]<=2,"Dentro do Prazo","Fora do Prazo") -> Fora do Prazo | W98: Safety Car | X98: EVAILTON | Y98: Nov | Z98: =VLOOKUP(Tabela1[[#This Row],[Placa]],DadosViagem5[[Placa]:[Base]],11,FALSE) -> SC (PORTO ALEGRE) SRS1
E99: RNC9E64 | F99: =IFERROR(VLOOKUP(Tabela1[[#This Row],[Placa]],'Base Cadastro '!A:B,2,FALSE),"Correção de cadastro") -> Master Furgão 8m³ | G99: 196707 | H99: Funilaria dianteira, colisão grave. | I99: 45576 | J99: Isabelli | K99: Sinistro | L99: Corretiva | M99: Aprovado | N99: 17613.71 | O99: 17613.71 | P99: =VLOOKUP(Tabela1[[#This Row],[Placa]],'Base Cadastro '!A:M,13,FALSE) -> SSP3 | Q99: MERCADO LIVRE | R99: Sinistro | S99: Aguardando peças | U99: =IFERROR(DATEDIF(Tabela1[[#This Row],[Data Agenda]],Tabela1[[#This Row],[Liberado]],"D"),DATEDIF(Tabela1[[#This Row],[Data Agenda]],TODAY(),"D")) -> 402 | V99: =IF(Tabela1[[#This Row],[D+Manut]]<=2,"Dentro do Prazo","Fora do Prazo") -> Fora do Prazo | W99: Vegas Truck | X99: KAREN | Y99: Set | Z99: =VLOOKUP(Tabela1[[#This Row],[Placa]],DadosViagem5[[Placa]:[Base]],11,FALSE) -> SC (1CAMPINAS) SSP3
E100: RVB0J97 | F100: =IFERROR(VLOOKUP(Tabela1[[#This Row],[Placa]],'Base Cadastro '!A:B,2,FALSE),"Correção de cadastro") -> MASTER FURGAO L1 | G100: 183000 | H100: Homocinetica/Maçaneta/Chave de Seta - Modulo vai ser enviado hoje, 07/11 - 11/11 Leandro vai olhar o modulo aqui em SP | I100: 45923 | J100: Luana | K100: Manutenção | L100: Corretiva | M100: Aprovado | P100: =VLOOKUP(Tabela1[[#This Row],[Placa]],'Base Cadastro '!A:M,13,FALSE) -> SSP24 | Q100: MERCADO LIVRE | R100: Em Manutenção | S100: Aguardando peças | U100: =IFERROR(DATEDIF(Tabela1[[#This Row],[Data Agenda]],Tabela1[[#This Row],[Liberado]],"D"),DATEDIF(Tabela1[[#This Row],[Data Agenda]],TODAY(),"D")) -> 55 | V100: =IF(Tabela1[[#This Row],[D+Manut]]<=2,"Dentro do Prazo","Fora do Prazo") -> Fora do Prazo | W100: Injemec | X100: EDUARDO | Y100: Set | Z100: =VLOOKUP(Tabela1[[#This Row],[Placa]],DadosViagem5[[Placa]:[Base]],11,FALSE) -> SC (AVARÉ) SSP24
C101: Sim | D101: 6760262 | E101: SDQ3J57 | F101: =IFERROR(VLOOKUP(Tabela1[[#This Row],[Placa]],'Base Cadastro '!A:B,2,FALSE),"Correção de cadastro") -> Kangoo Z.E. MAXI 5 Lugares 2P | G101: 12890 | H101: Bateria, Vidro, Cobertura chave seta superior e inferior, Chave de seta completa e grade dianteira | I101: 45945 | J101: Julia | K101: Manutenção | L101: Corretiva | M101: Negociando | P101: =VLOOKUP(Tabela1[[#This Row],[Placa]],'Base Cadastro '!A:M,13,FALSE) -> SSP21 | Q101: MERCADO LIVRE | R101: Em Manutenção | S101: 45994 | U101: =IFERROR(DATEDIF(Tabela1[[#This Row],[Data Agenda]],Tabela1[[#This Row],[Liberado]],"D"),DATEDIF(Tabela1[[#This Row],[Data Agenda]],TODAY(),"D")) -> 33 | V101: =IF(Tabela1[[#This Row],[D+Manut]]<=2,"Dentro do Prazo","Fora do Prazo") -> Fora do Prazo | W101: Passos | X101: Domenico | Y101: Out | Z101: =VLOOKUP(Tabela1[[#This Row],[Placa]],DadosViagem5[[Placa]:[Base]],11,FALSE) -> SC (MOOCA CENTRO) SSP21
...

Sheet Liberado
A1: Data Forms | B1: Atendimento | C1: Placa | D1: Modelo | E1: km | F1: Relato | G1: Data Agenda | H1: Focal | I1: Reparo | J1: Tipo de Manutenção | K1: Aprovação | L1: Valor do Orçamento | M1: Valor Negociado | N1: Centro de Custo | O1: Operação | P1: Status | Q1: Previsão de Entrega | R1: Liberado | S1: D+Manut | T1: Status2 | U1: Oficina | V1: Lider Base | W1: Mês | X1: Coluna1
C2: STU8B28 | D2: DELIVERY 9.180 | E2: 35410.421 | F2: 10/09/2025 Veiculo fazendo funilaria | G2: 45910 | H2: Miriam | I2: Manutenção | J2: Corretiva | K2: Aprovado | N2: =VLOOKUP(C2,'Base Cadastro '!A:M,13,FALSE) -> SSP5 | O2: MERCADO LIVRE | P2: Motor | Q2: 45924 | R2: 45919 | S2: 9 | T2: Fora do Prazo | U2: Central Truck | V2: MARCELO/ISLENE/ERIVELTON | W2: Set
A3: 0 | C3: RUM2B64 | D3: Fiorino Endurance Evo 1.4 2P | E3: 0 | F3: Motor/Junta do Cabeçote | G3: 45912 | H3: Hillary | I3: Manutenção | J3: Corretiva | K3: Aprovado | N3: =VLOOKUP(C3,'Base Cadastro '!A:M,13,FALSE) -> SSP20 | O3: MERCADO LIVRE | P3: Em Manutenção | Q3: 45924 | R3: 45922 | S3: 10 | T3: Fora do Prazo | U3: SM3 | V3: LARIANE | W3: Set
A4: 0 | C4: RVB8A68 | D4: MASTER FURGAO L1 | E4: 109052 | F4: 21/08 - Embreagem | G4: 45881 | H4: Miriam | I4: Manutenção | J4: Corretiva | K4: Aprovado | N4: =VLOOKUP(C4,'Base Cadastro '!A:M,13,FALSE) -> SPR2 | O4: MERCADO LIVRE | P4: Em Manutenção | Q4: 45924 | R4: 45919 | S4: 38 | T4: Fora do Prazo | U4: Auto Vans | V4: EDGARD | W4: Ago
C5: SDP9J20 | D5: E-Jumpy Furgão 2P | F5: Não é sinistro | G5: 45906 | H5: Hillary | I5: Sinistro | J5: Corretiva | K5: Aprovado | N5: =VLOOKUP(C5,'Base Cadastro '!A:M,13,FALSE) -> SSC2 | O5: MERCADO LIVRE | P5: Em Manutenção | Q5: 45924 | R5: 45919 | S5: 13 | T5: Fora do Prazo | U5: França pneus | V5: CARLOS SELL | W5: Set
B6: 6776496 | C6: RHV8D37 | D6: JAC iEV1200T AT 4x2 2P | E6: 38033 | F6: 28/08 Motor | G6: 45895 | H6: Miriam | I6: Manutenção | J6: Corretiva | K6: Aprovado | N6: =VLOOKUP(C6,'Base Cadastro '!A:M,13,FALSE) -> BRRC01 | O6: MERCADO LIVRE | P6: Em Manutenção | Q6: 45924 | R6: 45919 | S6: 24 | T6: Fora do Prazo | U6: NGN DISTRIBUIDORA DE VEICULOS LTDA (localiza) | V6: BRUNO/ERIVELTON | W6: Ago
C7: RUO6B02 | D7: Fiorino Endurance Evo 1.4 2P | F7: Vazamento de óleo/caixa de Direção | G7: 45908 | H7: Hillary | I7: Manutenção | J7: Corretiva | K7: Aprovado | N7: =VLOOKUP(C7,'Base Cadastro '!A:M,13,FALSE) -> PTL01 | O7: MERCADO LIVRE | P7: Em Manutenção | Q7: 45924 | R7: 45922 | S7: 14 | T7: Fora do Prazo | U7: RM | V7: CAMILA | W7: Set
C8: SDT9F97 | D8: E-Jumpy Furgão 2P | E8: 29453 | F8: Amortecedor | G8: 45905 | H8: Hillary | I8: Manutenção | J8: Corretiva | K8: Aprovado | N8: =VLOOKUP(C8,'Base Cadastro '!A:M,13,FALSE) -> SRS1 | O8: MERCADO LIVRE | P8: Em Manutenção | Q8: 45924 | R8: 45922 | S8: 17 | T8: Fora do Prazo | U8: Safety Car | V8: EVAILTON | W8: Set
C9: SGH9G33 | D9: I/FORD TRANSIT 350 FL | F9: pastilha de freio e correia alternador | G9: 45912 | H9: Hillary | I9: Manutenção | J9: Corretiva | K9: Aprovado | N9: =VLOOKUP(C9,'Base Cadastro '!A:M,13,FALSE) -> SSP20 | O9: MERCADO LIVRE | P9: Em Manutenção | Q9: 45924 | R9: 45919 | S9: 7 | T9: Fora do Prazo | U9: SM3 | V9: LARIANE | W9: Set
C10: RNJ9C97 | D10: Master Furgão 8m³ | E10: 1521700 | F10: 17/09 Problema eletrico em analise | G10: 45916 | H10: Miriam | I10: Manutenção | J10: Corretiva | K10: Aprovado | N10: =VLOOKUP(C10,'Base Cadastro '!A:M,13,FALSE) -> SPR8 | O10: MERCADO LIVRE | P10: Em Manutenção | Q10: 45924 | R10: 45919 | S10: 3 | T10: Fora do Prazo | U10: FSP | V10: TUANY | W10: Set
C11: RUM2B25 | D11: Fiorino Endurance Evo 1.4 2P | F11: veiculo guinchado por aquecimento | G11: 45914 | H11: Hillary | I11: Manutenção | J11: Corretiva | K11: Aprovado | N11: =VLOOKUP(C11,'Base Cadastro '!A:M,13,FALSE) -> SSP20 | O11: MERCADO LIVRE | P11: Em Manutenção | Q11: 45924 | R11: 45922 | S11: 8 | T11: Fora do Prazo | U11: SM3 | V11: LARIANE | W11: Set
A12: 45852 | B12: 6843992 | C12: EOA8G93 | D12: Partner Rapid Business Pack 1.4 2P | E12: 76689 | F12: Pane Eletrica | G12: 45841 | H12: Hillary | I12: Manutenção | J12: Corretiva | K12: Aprovado | N12: =VLOOKUP(C12,'Base Cadastro '!A:M,13,FALSE) -> SRS8 | O12: MERCADO LIVRE | P12: Em Manutenção | Q12: 45924 | R12: 45919 | S12: 78 | T12: Fora do Prazo | U12: Nova Lima (Movida) | V12: MICAEL MARCOS | W12: Jul
C13: RTM6B47 | D13: Master Furgão 8m³ | E13: 10000 | F13: vazamento oleo hidraulico e amortecedor lçado passageiro estourado | G13: 45913 | H13: Hillary | I13: Manutenção | J13: Corretiva | K13: Aprovado | N13: =VLOOKUP(C13,'Base Cadastro '!A:M,13,FALSE) -> SRS1 | O13: MERCADO LIVRE | P13: Em Manutenção | Q13: Em Diagnóstico | R13: 45919 | S13: 6 | T13: Fora do Prazo | U13: Safety Car | V13: EVAILTON | W13: Set
C14: RNJ9C89 | D14: Master Furgão 8m³ | F14: Arrebentou a Correia do Veículo | G14: 45918 | H14: Hillary | I14: Manutenção | J14: Corretiva | K14: Aprovado | N14: =VLOOKUP(C14,'Base Cadastro '!A:M,13,FALSE) -> SSC2 | O14: MERCADO LIVRE | P14: Em Manutenção | Q14: 45924 | R14: 45922 | S14: 4 | T14: Fora do Prazo | U14: AMS | V14: CARLOS SELL | W14: Set
C15: RNJ9D65 | D15: MASTER FURGAO L1 | E15: 15024732 | F15: CAIXA DE DIREÇÃO | G15: 45912 | H15: Carla | I15: Manutenção | J15: Corretiva | K15: Aprovado | N15: =VLOOKUP(C15,'Base Cadastro '!A:M,13,FALSE) -> SSP3 | O15: MERCADO LIVRE | P15: Em Manutenção | Q15: 45924 | R15: 45919 | S15: 7 | T15: Fora do Prazo | U15: Passos | V15: KAREN | W15: Set
C16: SGL1J04 | D16: TRANSIT FURGÃO | E16: 29123 | F16: pane | G16: 45916 | H16: Miriam | I16: Manutenção | J16: Corretiva | K16: Aprovado | N16: =VLOOKUP(C16,'Base Cadastro '!A:M,13,FALSE) -> SSP5 | O16: MERCADO LIVRE | P16: Em Manutenção | Q16: 45924 | R16: 45919 | S16: 3 | T16: Fora do Prazo | U16: Estacionamento da Coca/MuriTruck | V16: MARCELO/ISLENE/ERIVELTON | W16: Set
C17: RVD4C77 | D17: Partner Rapid Business Pack 1.4 2P | G17: 45913 | H17: Miriam | I17: Manutenção | J17: Corretiva | K17: Aprovado | N17: =VLOOKUP(C17,'Base Cadastro '!A:M,13,FALSE) -> SSP13 | O17: MERCADO LIVRE | P17: Em Manutenção | Q17: 45924 | R17: 45918 | S17: 5 | T17: Fora do Prazo | U17: Injemec | V17: NAYARA/FLAVIA | W17: Set
C18: RUX2J08 | D18: Partner Rapid Business Pack 1.4 2P | F18: embreagem | G18: 45913 | H18: Hillary | I18: Manutenção | J18: Corretiva | K18: Aprovado | N18: =VLOOKUP(C18,'Base Cadastro '!A:M,13,FALSE) -> SMG5 | O18: MERCADO LIVRE | P18: Em Manutenção | Q18: 45924 | R18: 45919 | S18: 6 | T18: Fora do Prazo | U18: centro automotivo full pneus | V18: CAMILA | W18: Set
C19: RNG5A20 | D19: Master Furgão 8m³ | F19: embreagem | G19: 45913 | H19: Hillary | I19: Manutenção | J19: Corretiva | K19: Aprovado | N19: =VLOOKUP(C19,'Base Cadastro '!A:M,13,FALSE) -> SSP20 | O19: MERCADO LIVRE | P19: Em Manutenção | Q19: 45924 | R19: 45922 | S19: 9 | T19: Fora do Prazo | U19: SM3 | V19: LARIANE | W19: Set
A20: 45909 | B20: 6775281 | C20: SDT9G93 | D20: E-Jumpy Furgão 2P | E20: 64412.329 | F20: Veículo elétrico não carrega | G20: 45861 | H20: Carla | I20: Manutenção | J20: Corretiva | K20: Aprovado | N20: =VLOOKUP(C20,'Base Cadastro '!A:M,13,FALSE) -> SSP12 | O20: MERCADO LIVRE | P20: Em Manutenção | Q20: 45924 | R20: 45918 | S20: 57 | T20: Fora do Prazo | U20: LUMIERE (CITROEN) | V20: GABRIEL | W20: Jul
C21: JCI8F75 | D21: DELIVERY 9.180 | F21: radiador avariado | G21: 45912 | H21: Hillary | I21: Manutenção | J21: Corretiva | K21: Aprovado | N21: =VLOOKUP(C21,'Base Cadastro '!A:M,13,FALSE) -> SSP20 | O21: MERCADO LIVRE | P21: Em Manutenção | Q21: 45924 | R21: 45922 | S21: 10 | T21: Fora do Prazo | U21: SM3 SOROCABA | V21: LARIANE | W21: Set
C22: RUM3C04 | D22: Fiorino Endurance Evo 1.4 2P | F22: pane eletrica | G22: 45914 | H22: Miriam | I22: Manutenção | J22: Corretiva | K22: Aprovado | N22: =VLOOKUP(C22,'Base Cadastro '!A:M,13,FALSE) -> EMS4 | O22: MERCADO LIVRE | P22: Em Manutenção | Q22: 45924 | R22: 45919 | S22: 5 | T22: Fora do Prazo | U22: Master tech | V22: MARIANE | W22: Set
A23: 45786 | B23: 6594053 | C23: SDT9F66 | D23: E-Jumpy Furgão 2P | E23: 37605 | F23: Veículo elétrico não carrega | G23: 45786 | H23: Miriam | I23: Manutenção | J23: Corretiva | K23: Aprovado | N23: =VLOOKUP(C23,'Base Cadastro '!A:M,13,FALSE) -> SSP21 | O23: MERCADO LIVRE | P23: Em Manutenção | Q23: 45924 | R23: 45919 | S23: 133 | T23: Fora do Prazo | U23: AKTA em Santos (localiza) | V23: JONATHAN | W23: Mai
A24: 45869 | B24: 6756576 | C24: SDP9J05 | D24: E-Jumpy Furgão 2P | E24: 49494 | F24: Veículo elétrico não carrega | G24: 45869 | H24: Khetlyn | I24: Manutenção | J24: Corretiva | K24: Aprovado | N24: =VLOOKUP(C24,'Base Cadastro '!A:M,13,FALSE) -> SCE1 | O24: MERCADO LIVRE | P24: Em Manutenção | Q24: 45924 | R24: 45916 | S24: 47 | T24: Fora do Prazo | U24: PIGALLE VEICULOS PEC (Localiza) | V24: GLEUMA | W24: Jul
A25: 45877 | B25: 6670135 | C25: SDQ3A32 | D25: Kangoo Z.E. MAXI 5 Lugares 2P | E25: 59013.494 | F25: Preventiva, estralando a Homocêntrica | G25: 45870 | H25: Carla | I25: Manutenção | J25: Corretiva | K25: Aprovado | N25: =VLOOKUP(C25,'Base Cadastro '!A:M,13,FALSE) -> SSP4 | O25: MERCADO LIVRE | P25: Em Manutenção | Q25: 45924 | R25: 45919 | S25: 49 | T25: Fora do Prazo | U25: EURO RP VEICULOS ( Localiza ) | V25: DEBORAH | W25: Ago
A26: 45869 | B26: 17148246 | C26: RHO5B26 | D26: JAC iEV1200T AT 4x2 2P | E26: 35760.542 | F26: fazendo barulho na roda dianteira muito forte (Homocinetica) | G26: 45838 | H26: Carla | I26: Manutenção | J26: Corretiva | K26: Aprovado | N26: =VLOOKUP(C26,'Base Cadastro '!A:M,13,FALSE) -> SSP30 | O26: MERCADO LIVRE | P26: Em Manutenção | Q26: 45924 | R26: 45919 | S26: 81 | T26: Fora do Prazo | U26: TICKET LOG MANUTENCA ( LOCALIZA ) | V26: CLAUDIA | W26: Jun
C27: SJT9A40 | D27: DELIVERY 9.180 | E27: 62294 | F27: Vazamento/ veículo sem Força/ Cambio | G27: 45901 | H27: Luana | I27: Manutenção | J27: Corretiva | K27: Negociando | N27: SSP5 | O27: MERCADO LIVRE | P27: Em Manutenção | Q27: Em Diagnóstico | R27: 45924 | S27: 23 | T27: Fora do Prazo | U27: Dircan | V27: MARCELO/ISLENE/ERIVELTON | W27: Set
C28: RTF0B76 | D28: Master Furgão 8m³ | F28: veiculo encaminhado de guincho nao da partida | G28: 45913 | H28: Luana | I28: Manutenção | J28: Corretiva | K28: Negociando | N28: SSP5 | O28: MERCADO LIVRE | P28: Em Manutenção | Q28: Em Diagnóstico | R28: 45924 | S28: 11 | T28: Fora do Prazo | U28: Estacionamento da Coca/MuriTruck | V28: MARCELO/ISLENE/ERIVELTON | W28: Set
A29: 0 | C29: SJT5G88 | D29: DELIVERY 9.180 | E29: 56843 | F29: cx de direção | G29: 45916 | H29: Luana | I29: Manutenção | J29: Corretiva | K29: Negociando | N29: SSP5 | O29: MERCADO LIVRE | P29: Em Manutenção | Q29: Em Diagnóstico | R29: 45924 | S29: 8 | T29: Fora do Prazo | U29: Dircan | V29: MARCELO/ISLENE/ERIVELTON | W29: Set
C30: UGH4A00 | D30: FIAT/FIORINO ENDURANCE | F30: Veículo sofreu uma colisão na porta esquerda. | G30: 45924 | H30: Julia | I30: Sinistro | J30: Corretiva | K30: Aprovado | N30: PTL02 | O30: PET LOVE | P30: Sinistro | Q30: 45925 | R30: 45925 | S30: 1 | T30: Dentro do Prazo | U30: Garage Helena Maria | V30: GABRIELI | W30: Set
C31: SGI8G86 | D31: TRANSIT CHASSI | E31: 38402 | F31: 16/09 revisão | G31: 45898 | H31: Carla | I31: Manutenção | J31: Corretiva | K31: Aprovado | N31: =VLOOKUP(#REF!,'Base Cadastro '!#REF!,13,FALSE) -> #REF! | O31: MERCADO LIVRE | P31: Em Manutenção | Q31: Em Diagnóstico | R31: 45926 | S31: =IFERROR(DATEDIF(#REF!,#REF!,"D"),DATEDIF(#REF!,TODAY(),"D")) -> #REF! | T31: =IF(#REF!<=2,"Dentro do Prazo","Fora do Prazo") -> #REF! | U31: Ford Studio Guarulhos | V31: CLAUDIA | W31: Ago
A32: 0 | C32: STO0I02 | D32: =IFERROR(VLOOKUP(#REF!,'Base Cadastro '!#REF!,2,FALSE)," ") | E32: 69002 | F32: pneus soltou a recapagem | G32: 45916 | H32: Khetlyn | I32: Manutenção | J32: Corretiva | K32: Aprovado | N32: =VLOOKUP(#REF!,'Base Cadastro '!#REF!,13,FALSE) -> #REF! | O32: MERCADO LIVRE | P32: Em Manutenção | Q32: Em Diagnóstico | R32: 45926 | S32: =IFERROR(DATEDIF(#REF!,#REF!,"D"),DATEDIF(#REF!,TODAY(),"D")) -> #REF! | T32: =IF(#REF!<=2,"Dentro do Prazo","Fora do Prazo") -> #REF! | U32: Estacionamento da base | V32: KAREN | W32: Set
C33: GIG3B72 | D33: VW/EXPRESS DRC 4X2 | E33: 100 | F33: REVISÃO | G33: 45924 | H33: Luana | I33: Manutenção | J33: Corretiva | K33: Aprovado | N33: =VLOOKUP(#REF!,'Base Cadastro '!#REF!,13,FALSE) -> #REF! | O33: MERCADO LIVRE | P33: Em Manutenção | Q33: Em Diagnóstico | R33: 45926 | S33: =IFERROR(DATEDIF(#REF!,#REF!,"D"),DATEDIF(#REF!,TODAY(),"D")) -> #REF! | T33: =IF(#REF!<=2,"Dentro do Prazo","Fora do Prazo") -> #REF! | U33: Estacionamento da Muritruck | W33: Set
C34: TAO5A38 | D34: IVECO 35S1 | E34: 100 | F34: Foi fazer freio ontem e ainda não foi liberado, está na MuriTruck | G34: 45924 | H34: Luana | I34: Manutenção | J34: Corretiva | K34: Aprovado | N34: =VLOOKUP(#REF!,'Base Cadastro '!#REF!,13,FALSE) -> #REF! | O34: MERCADO LIVRE | P34: Em Manutenção | Q34: Em Diagnóstico | R34: 45926 | S34: =IFERROR(DATEDIF(#REF!,#REF!,"D"),DATEDIF(#REF!,TODAY(),"D")) -> #REF! | T34: =IF(#REF!<=2,"Dentro do Prazo","Fora do Prazo") -> #REF! | U34: Estacionamento da Muritruck | W34: Set
C35: TOE7D29 | D35: =IFERROR(VLOOKUP(#REF!,'Base Cadastro '!#REF!,2,FALSE)," ") | F35: dificuldade de passar marcha | G35: 45916 | H35: Julia | I35: Manutenção | J35: Corretiva | K35: Aprovado | N35: =VLOOKUP(#REF!,'Base Cadastro '!#REF!,13,FALSE) -> #REF! | O35: MADEIRA MADEIRA | P35: Em Manutenção | Q35: Em Diagnóstico | R35: 45926 | S35: =IFERROR(DATEDIF(#REF!,#REF!,"D"),DATEDIF(#REF!,TODAY(),"D")) -> #REF! | T35: =IF(#REF!<=2,"Dentro do Prazo","Fora do Prazo") -> #REF! | U35: Estacionamento da Coca/MuriTruck | V35: RODRIGO | W35: Set
A36: 0 | C36: SJT3D02 | D36: =IFERROR(VLOOKUP(#REF!,'Base Cadastro '!#REF!,2,FALSE)," ") | E36: 76447 | F36: porta travada / solicitação de compra do estribo | G36: 45917 | H36: Khetlyn | I36: Manutenção | J36: Preventiva | K36: Aprovado | N36: =VLOOKUP(#REF!,'Base Cadastro '!#REF!,13,FALSE) -> #REF! | O36: MERCADO LIVRE | P36: Motor | Q36: Em Diagnóstico | R36: 45926 | S36: =IFERROR(DATEDIF(#REF!,#REF!,"D"),DATEDIF(#REF!,TODAY(),"D")) -> #REF! | T36: =IF(#REF!<=2,"Dentro do Prazo","Fora do Prazo") -> #REF! | U36: SM3 | V36: ANA FLAVIA | W36: Set
C37: TOE7D00 | D37: =IFERROR(VLOOKUP(#REF!,'Base Cadastro '!#REF!,2,FALSE)," ") | E37: 5890 | F37: Ela está com vazamento no reservatório | G37: 45919 | H37: Julia | I37: Manutenção | J37: Corretiva | K37: Aprovado | N37: =VLOOKUP(#REF!,'Base Cadastro '!#REF!,13,FALSE) -> #REF! | O37: MERCADO LIVRE | P37: Em Manutenção | Q37: Em Diagnóstico | R37: 45926 | S37: =IFERROR(DATEDIF(#REF!,#REF!,"D"),DATEDIF(#REF!,TODAY(),"D")) -> #REF! | T37: =IF(#REF!<=2,"Dentro do Prazo","Fora do Prazo") -> #REF! | U37: Estacionamento da Coca/MuriTruck | V37: JULIANA | W37: Set
C38: RUX2B97 | D38: Partner Rapid Business Pack 1.4 2P | F38: 12/09/2025 Problema de motor | G38: 45910 | H38: Arthur | I38: Manutenção | J38: Corretiva | K38: Aprovado | L38: R$ 5.576,70 R$ | M38: 5575.7 | N38: SPR1 | O38: MERCADO LIVRE | P38: Em Manutenção | Q38: Aguardando Aprovação | R38: 45925 | S38: 15 | T38: Fora do Prazo | U38: FSP | V38: RENATA | W38: Set
C39: RUX2D04 | D39: Partner Rapid Business Pack 1.4 2P | E39: 140508 | F39: MOTOR- carro liberado ja em operção | G39: 45894 | H39: Hillary | N39: SSC5 | O39: MERCADO LIVRE | R39: 45926 | V39: REGIANE | W39: Ago
C40: RFP9G74 | D40: MASTER FUR L1H1 | E40: 195720 | F40: Trocar as maçanetas e o Semi-Eixo | G40: 45925 | H40: Luana | I40: Manutenção | J40: Corretiva | K40: Aprovado | L40: 2552.8 | M40: 2425.16 | N40: SSP28 | O40: MERCADO LIVRE | P40: Em Manutenção | Q40: 45926 | R40: 45926 | S40: 1 | T40: Dentro do Prazo | U40: Oficina LS | W40: Set
C41: RNN0C21 | D41: Master Furgão 8m³ | E41: 129428 | F41: veiculo sem força | G41: 45910 | H41: Julia | I41: Manutenção | J41: Corretiva | K41: Aprovado | N41: SSP34 | O41: MERCADO LIVRE | P41: Em Manutenção | Q41: 45924 | R41: 45924 | S41: 14 | T41: Fora do Prazo | U41: Estacionamento da Base | V41: Tainá | W41: Set
C42: RTE0I43 | D42: Master Furgão 8m³ | E42: 130142 | F42: Obs: 25/09 enviado email para oficina cobrando prazo. 16/09/25 cabeçote apos diagnostico do DUDU | G42: 45911 | H42: Luana | I42: Manutenção | J42: Corretiva | K42: Aprovado | N42: SSP5 | O42: MERCADO LIVRE | P42: Em Manutenção | Q42: 45924 | R42: 45924 | S42: 13 | T42: Fora do Prazo | U42: Estacionamento da Coca/MuriTruck | V42: MARCELO/ISLENE/ERIVELTON | W42: Set
C43: RND8C38 | D43: Master Furgão 8m³ | E43: 139984 | F43: Polia do virabrequim | G43: 45922 | H43: Arthur | I43: Manutenção | J43: Corretiva | K43: Aprovado | L43: 2318.9 | M43: 2318.9 | N43: SPR8 | O43: MERCADO LIVRE | P43: Em Manutenção | Q43: 45925 | R43: 45925 | S43: 3 | T43: Fora do Prazo | U43: FSP | V43: Renata | W43: Set
C44: RNJ9C66 | D44: Master Furgão 8m³ | E44: 136248 | F44: sumindo a água do arrefecimento | G44: 45917 | H44: Julia | I44: Manutenção | J44: Corretiva | K44: Aprovado | N44: SSP34 | O44: MERCADO LIVRE | P44: Em Manutenção | Q44: Em Diagnóstico | R44: 45925 | S44: 8 | T44: Fora do Prazo | U44: Estacionamento da Coca/MuriTruck | V44: Taina | W44: Set
C45: RNB5I56 | D45: Master Furgão 8m³ | E45: 170010 | F45: COXIM motor | G45: 45908 | H45: Khetlyn | I45: Manutenção | J45: Corretiva | K45: Aprovado | N45: SSP25 | O45: MERCADO LIVRE | P45: Em Manutenção | Q45: 45929 | R45: 45926 | S45: 18 | T45: Fora do Prazo | U45: Estacionamento da Coca/MuriTruck | V45: LEANDRO | W45: Set
C46: RNJ9C80 | D46: Master Furgão 8m³ | E46: 129733 | F46: Trizeta | G46: 45923 | H46: Arthur | I46: Manutenção | J46: Corretiva | K46: Aprovado | L46: 409.9 | M46: 409.9 | N46: SPR8 | O46: MERCADO LIVRE | P46: Em Manutenção | Q46: 45930 | R46: 45924 | S46: 1 | T46: Dentro do Prazo | U46: FSP | V46: Renata | W46: Set
C47: SUP5G29 | D47: MASTER FURGAO L1 | F47: freios dt e ts | G47: 45915 | H47: Arthur | I47: Manutenção | J47: Corretiva | K47: Aprovado | L47: 5878.2 | M47: 5500 | N47: SPR8 | O47: MERCADO LIVRE | P47: Em Manutenção | Q47: 45925 | R47: 45925 | S47: 10 | T47: Fora do Prazo | U47: FSP | V47: Renata | W47: Set
C48: RFU2E28 | D48: Master Grand Furgão 11m³ | E48: 131640 | F48: 10/09 veiculo arrefecimento | G48: 45910 | H48: Julia | I48: Manutenção | J48: Corretiva | K48: Aprovado | N48: SSP34 | O48: MERCADO LIVRE | P48: Em Manutenção | Q48: 45922 | R48: 45922 | S48: 12 | T48: Fora do Prazo | U48: Estacionamento da Coca/MuriTruck | V48: Tainá | W48: Set
C49: FJG5F03 | D49: Sprinter 313 | E49: 99784 | F49: Pane elétrica | G49: 45880 | H49: Sara | I49: Manutenção | J49: Corretiva | K49: Negociando | N49: GP01 | O49: GRUPO PEREIRA | P49: Em Manutenção | Q49: Em Diagnóstico | R49: 45926 | S49: 46 | T49: Fora do Prazo | U49: De Nigris (São Bernado dos Campos) | V49: Adriano | W49: Ago
A50: 45910 | C50: GFX6D91 | D50: Sprinter 313 | E50: 220642 | F50: Correia | G50: 45910 | H50: Luana | I50: Manutenção | J50: Corretiva | K50: Negociando | N50: SSP8 | O50: MERCADO LIVRE | P50: Em Manutenção | Q50: Em Diagnóstico | R50: 45927 | S50: 17 | T50: Fora do Prazo | U50: 0 | V50: GABRIELE | W50: Set
C51: SGI8H03 | D51: TRANSIT FURGÃO | E51: 397005 | F51: Revisão | G51: 45904 | H51: Khetlyn | I51: Manutenção | J51: Corretiva | K51: Negociando | N51: SSP20 | O51: MERCADO LIVRE | P51: Em Manutenção | Q51: Em Diagnóstico | R51: 45926 | S51: 22 | T51: Fora do Prazo | U51: Ford Andretta | V51: LARIANE | W51: Set
C52: TOE7D00 | D52: TRANSIT FURGÃO | F52: Identificados danos causados por colisão na parte inferior dianteira. A colisão afetou diversos componentes essenciais do sistema de arrefecimento e ventilação do motor, resultando em vazamento de água e superaquecimento. Foram danificados os seguintes itens: radiador , condensador, eletro ventilador/motor + hélice, hélice do radiador, suporte inferior do radiador , proteção inferior do motor, defletores de ar e aditivo de arrefecimento. | G52: 45842 | I52: Manutenção | J52: Corretiva | K52: Negociando | L52: 15404.35 | N52: SSP6 | O52: MERCADO LIVRE | P52: Em Manutenção | Q52: Aguardando aprovação | R52: 45925 | S52: 83 | T52: Fora do Prazo | U52: CAOA FORD JABAQUARA
C53: SDT9F44 | D53: =IFERROR(VLOOKUP(#REF!,'Base Cadastro '!#REF!,2,FALSE)," ") | E53: 94119 | F53: Freios peneus | G53: 45915 | H53: Hillary | I53: Manutenção | J53: Corretiva | K53: Negociando | L53: 2530 | M53: 2530 | N53: =VLOOKUP(#REF!,'Base Cadastro '!#REF!,13,FALSE) -> #REF! | O53: MERCADO LIVRE | P53: Em Manutenção | Q53: 45926 | R53: 45926 | S53: =IFERROR(DATEDIF(#REF!,#REF!,"D"),DATEDIF(#REF!,TODAY(),"D")) -> #REF! | T53: =IF(#REF!<=2,"Dentro do Prazo","Fora do Prazo") -> #REF! | U53: AMS | V53: CARLOS SELL | W53: Set
C54: RUL7F48 | D54: =IFERROR(VLOOKUP(#REF!,'Base Cadastro '!#REF!,2,FALSE)," ") | E54: 71034 | F54: 16/07 motor | G54: 45831 | H54: Julia | I54: Manutenção | J54: Corretiva | K54: Aprovado | N54: =VLOOKUP(#REF!,'Base Cadastro '!#REF!,13,FALSE) -> #REF! | O54: MERCADO LIVRE | P54: Motor | Q54: 45931 | R54: 45929 | S54: =IFERROR(DATEDIF(#REF!,#REF!,"D"),DATEDIF(#REF!,TODAY(),"D")) -> #REF! | T54: =IF(#REF!<=2,"Dentro do Prazo","Fora do Prazo") -> #REF! | U54: Nova Elite Retifica | V54: JHENIFFER | W54: Jun
C55: SDQ4A29 | D55: =IFERROR(VLOOKUP(#REF!,'Base Cadastro '!#REF!,2,FALSE)," ") | E55: 292435 | F55: Colisão lateral direita | G55: 45915 | H55: Hillary | I55: Sinistro | J55: Corretiva | K55: Aprovado | L55: 9810 | M55: 9810 | N55: =VLOOKUP(#REF!,'Base Cadastro '!#REF!,13,FALSE) -> #REF! | O55: MERCADO LIVRE | P55: Sinistro | Q55: 45930 | R55: 45930 | S55: =IFERROR(DATEDIF(#REF!,#REF!,"D"),DATEDIF(#REF!,TODAY(),"D")) -> #REF! | T55: =IF(#REF!<=2,"Dentro do Prazo","Fora do Prazo") -> #REF! | U55: Passos | W55: Set
A56: 0 | C56: GCX2D35 | D56: =IFERROR(VLOOKUP(#REF!,'Base Cadastro '!#REF!,2,FALSE)," ") | E56: 119264 | F56: Falta de arla | G56: 45891 | H56: Sara | I56: Manutenção | J56: Corretiva | K56: Negociando | N56: =VLOOKUP(#REF!,'Base Cadastro '!#REF!,13,FALSE) -> #REF! | O56: GRUPO PEREIRA | P56: Em Manutenção | Q56: Em Diagnóstico | R56: 45930 | S56: =IFERROR(DATEDIF(#REF!,#REF!,"D"),DATEDIF(#REF!,TODAY(),"D")) -> #REF! | T56: =IF(#REF!<=2,"Dentro do Prazo","Fora do Prazo") -> #REF! | U56: De Nigris (São Bernado dos Campos) | V56: RENATO | W56: Ago
C57: SFV0D67 | D57: =IFERROR(VLOOKUP(#REF!,'Base Cadastro '!#REF!,2,FALSE)," ") | E57: 85063 | F57: Placa falhando - aguardando a outra placa ficar pronta para enviarmos a mesma 28/08/2025 | G57: 45894 | H57: Luana | I57: Manutenção | J57: Corretiva | K57: Negociando | N57: =VLOOKUP(#REF!,'Base Cadastro '!#REF!,13,FALSE) -> #REF! | O57: MERCADO LIVRE | P57: Em Manutenção | Q57: Em Diagnóstico | R57: 45930 | S57: =IFERROR(DATEDIF(#REF!,#REF!,"D"),DATEDIF(#REF!,TODAY(),"D")) -> #REF! | T57: =IF(#REF!<=2,"Dentro do Prazo","Fora do Prazo") -> #REF! | U57: Estacionamento da Base | V57: EDUARDO | W57: Ago
C58: SGI8I95 | D58: =IFERROR(VLOOKUP(#REF!,'Base Cadastro '!#REF!,2,FALSE)," ") | E58: 56930 | F58: 16/09/25 Troca de correia do alternador e polia | G58: 45916 | H58: Khetlyn | I58: Manutenção | J58: Corretiva | K58: Negociando | N58: =VLOOKUP(#REF!,'Base Cadastro '!#REF!,13,FALSE) -> #REF! | O58: MERCADO LIVRE | P58: Em Manutenção | Q58: 45929 | R58: 45929 | S58: =IFERROR(DATEDIF(#REF!,#REF!,"D"),DATEDIF(#REF!,TODAY(),"D")) -> #REF! | T58: =IF(#REF!<=2,"Dentro do Prazo","Fora do Prazo") -> #REF! | U58: Oficina Atibaia Ford | V58: LEANDRO | W58: Set
C59: SGK7E24 | D59: =IFERROR(VLOOKUP(#REF!,'Base Cadastro '!#REF!,2,FALSE)," ") | E59: 9829 | F59: Veículo sofreu colisão com uma árvore. | G59: 45888 | H59: Carla | I59: Sinistro | J59: Corretiva | K59: Aprovado | L59: 6000 | M59: 6000 | N59: =VLOOKUP(#REF!,'Base Cadastro '!#REF!,13,FALSE) -> #REF! | O59: MERCADO LIVRE | P59: Sinistro | Q59: 45930 | R59: 45929 | S59: =IFERROR(DATEDIF(#REF!,#REF!,"D"),DATEDIF(#REF!,TODAY(),"D")) -> #REF! | T59: =IF(#REF!<=2,"Dentro do Prazo","Fora do Prazo") -> #REF! | U59: André Funilaria | V59: KARINA | W59: Set
C60: RNH7H50 | D60: =IFERROR(VLOOKUP(#REF!,'Base Cadastro '!#REF!,2,FALSE)," ") | F60: 16/09 - Veículo dará parada na Central Truck. 15/09 - Veículo sofreu uma colisão na porta esquerda. | G60: 45915 | H60: Luana | I60: Manutenção | J60: Corretiva | K60: Negociando | N60: =VLOOKUP(#REF!,'Base Cadastro '!#REF!,13,FALSE) -> #REF! | O60: MERCADO LIVRE | P60: Em Manutenção | Q60: Em Diagnóstico | R60: 45929 | S60: =IFERROR(DATEDIF(#REF!,#REF!,"D"),DATEDIF(#REF!,TODAY(),"D")) -> #REF! | T60: =IF(#REF!<=2,"Dentro do Prazo","Fora do Prazo") -> #REF! | U60: Estacionamento da Coca/MuriTruck | V60: MARCELO/ISLENE/ERIVELTON | W60: Set
C61: FJG5F03 | D61: Sprinter 313 | E61: 99.784.0 | F61: Problema no sistema elétrico | G61: 45926 | H61: Sara | I61: Manutenção | J61: Corretiva | K61: Aprovado | N61: GP01 | O61: GRUPO PEREIRA | P61: Em Manutenção | Q61: 45930 | R61: 45930 | S61: =IFERROR(DATEDIF(#REF!,#REF!,"D"),DATEDIF(#REF!,TODAY(),"D")) -> #REF! | T61: =IF(#REF!<=2,"Dentro do Prazo","Fora do Prazo") -> #REF! | U61: Denigris | V61: ADRIANO | W61: Set
C62: RTM6B70 | D62: =IFERROR(VLOOKUP(#REF!,'Base Cadastro '!#REF!,2,FALSE)," ") | F62: Veículo realizando funilaria na oficina GR Car | G62: 45870 | H62: Julia | I62: Sinistro | J62: Corretiva | K62: Aprovado | L62: 3100 | M62: 3100 | N62: =VLOOKUP(#REF!,'Base Cadastro '!#REF!,13,FALSE) -> #REF! | O62: MERCADO LIVRE | P62: Sinistro | Q62: Em Diagnóstico | R62: 45930 | S62: =IFERROR(DATEDIF(#REF!,#REF!,"D"),DATEDIF(#REF!,TODAY(),"D")) -> #REF! | T62: =IF(#REF!<=2,"Dentro do Prazo","Fora do Prazo") -> #REF! | U62: GR Car | V62: IGOR | W62: Set
C63: SGH1B19 | D63: =IFERROR(VLOOKUP(#REF!,'Base Cadastro '!#REF!,2,FALSE)," ") | E63: 56616 | F63: Freio | G63: 45901 | H63: Hillary | I63: Manutenção | J63: Corretiva | K63: Negociando | N63: =VLOOKUP(#REF!,'Base Cadastro '!#REF!,13,FALSE) -> #REF! | O63: MERCADO LIVRE | P63: Em Manutenção | Q63: Em Diagnóstico | R63: 45930 | S63: =IFERROR(DATEDIF(#REF!,#REF!,"D"),DATEDIF(#REF!,TODAY(),"D")) -> #REF! | T63: =IF(#REF!<=2,"Dentro do Prazo","Fora do Prazo") -> #REF! | U63: Amazon NH | V63: ALESSANDRA | W63: Set
C64: RVD4C91 | D64: =IFERROR(VLOOKUP(#REF!,'Base Cadastro '!#REF!,2,FALSE)," ") | F64: 02/07/2025 -Veiculo fazendo motor. 26/06/2025 - Aguardando retorno sobre a mesma. 18/06 - Descobriu trinca no cabeçote e aguardo de novas previsões. 01/04/2025 - Vazou todo óleo do motor - trincou o cabeçote 16/06/2025 | G64: 45744 | H64: Luana | I64: Manutenção | J64: Corretiva | K64: Negociando | N64: =VLOOKUP(#REF!,'Base Cadastro '!#REF!,13,FALSE) -> #REF! | O64: MERCADO LIVRE | P64: Em Manutenção | Q64: 45931 | R64: 45931 | S64: =IFERROR(DATEDIF(#REF!,#REF!,"D"),DATEDIF(#REF!,TODAY(),"D")) -> #REF! | T64: =IF(#REF!<=2,"Dentro do Prazo","Fora do Prazo") -> #REF! | U64: Fernandes Alto Center | V64: EDUARDO | W64: Mar
C65: GEW1I64 | D65: =IFERROR(VLOOKUP(#REF!,'Base Cadastro '!#REF!,2,FALSE)," ") | E65: 100.0 | F65: em operação | G65: 45692 | H65: Sara | I65: Manutenção | J65: Corretiva | N65: =VLOOKUP(#REF!,'Base Cadastro '!#REF!,13,FALSE) -> #REF! | O65: SHOPEE | Q65: em operação | R65: 45931 | V65: GEOVANA | W65: Fev
C66: SDU2D26 | D66: =IFERROR(VLOOKUP(#REF!,'Base Cadastro '!#REF!,2,FALSE)," ") | E66: 47510 | F66: Colisão no para-lama direito | G66: 45915 | H66: Hillary | I66: Sinistro | J66: Corretiva | K66: Aprovado | L66: 3636 | M66: 3636 | N66: =VLOOKUP(#REF!,'Base Cadastro '!#REF!,13,FALSE) -> #REF! | O66: MERCADO LIVRE | P66: Sinistro | Q66: 45932 | R66: 45931 | S66: =IFERROR(DATEDIF(#REF!,#REF!,"D"),DATEDIF(#REF!,TODAY(),"D")) -> #REF! | T66: =IF(#REF!<=2,"Dentro do Prazo","Fora do Prazo") -> #REF! | U66: FSP | V66: RENATA | W66: Set
C67: SGF8J08 | D67: =IFERROR(VLOOKUP(#REF!,'Base Cadastro '!#REF!,2,FALSE)," ") | E67: 64570 | F67: Motor | G67: 45924 | H67: Luana | I67: Manutenção | J67: Corretiva | K67: Negociando | N67: SSP10 | O67: MERCADO LIVRE | P67: Em Manutenção | Q67: 45931 | R67: 45931 | S67: =IFERROR(DATEDIF(#REF!,#REF!,"D"),DATEDIF(#REF!,TODAY(),"D")) -> #REF! | T67: =IF(#REF!<=2,"Dentro do Prazo","Fora do Prazo") -> #REF! | V67: NAGMA | W67: Set
C68: SGI8J30 | D68: =IFERROR(VLOOKUP(#REF!,'Base Cadastro '!#REF!,2,FALSE)," ") | E68: 5004432 | F68: troca de pneus | G68: 45879 | H68: Khetlyn | I68: Manutenção | J68: Preventiva | K68: Negociando | N68: =VLOOKUP(#REF!,'Base Cadastro '!#REF!,13,FALSE) -> #REF! | O68: MERCADO LIVRE | P68: Em Manutenção | Q68: Em Diagnóstico | R68: 45931 | S68: =IFERROR(DATEDIF(#REF!,#REF!,"D"),DATEDIF(#REF!,TODAY(),"D")) -> #REF! | T68: =IF(#REF!<=2,"Dentro do Prazo","Fora do Prazo") -> #REF! | U68: CAOA CAMPINAS | V68: ANA FLAVIA | W68: Ago
C69: SFW0A75 | D69: =IFERROR(VLOOKUP(#REF!,'Base Cadastro '!#REF!,2,FALSE)," ") | E69: 526581 | F69: troca de pneus | G69: 45879 | H69: Khetlyn | I69: Manutenção | J69: Preventiva | K69: Negociando | N69: =VLOOKUP(#REF!,'Base Cadastro '!#REF!,13,FALSE) -> #REF! | O69: MERCADO LIVRE | P69: Em Manutenção | Q69: Em Diagnóstico | R69: 45931 | S69: =IFERROR(DATEDIF(#REF!,#REF!,"D"),DATEDIF(#REF!,TODAY(),"D")) -> #REF! | T69: =IF(#REF!<=2,"Dentro do Prazo","Fora do Prazo") -> #REF! | U69: CAOA CAMPINAS | V69: ANA FLAVIA | W69: Ago
A70: 0 | C70: SFT5B03 | D70: =IFERROR(VLOOKUP(#REF!,'Base Cadastro '!#REF!,2,FALSE)," ") | E70: 48672 | F70: Pane Eletrica | G70: 45902 | H70: Luana | I70: Manutenção | J70: Corretiva | K70: Negociando | N70: =VLOOKUP(#REF!,'Base Cadastro '!#REF!,13,FALSE) -> #REF! | O70: MERCADO LIVRE | P70: Em Manutenção | Q70: Aguardando Aprovação | R70: 45931 | S70: =IFERROR(DATEDIF(#REF!,#REF!,"D"),DATEDIF(#REF!,TODAY(),"D")) -> #REF! | T70: =IF(#REF!<=2,"Dentro do Prazo","Fora do Prazo") -> #REF! | U70: Ford Caminho Prudente | V70: FERNANDO | W70: Set
C71: SGI8H40 | D71: =IFERROR(VLOOKUP(#REF!,'Base Cadastro '!#REF!,2,FALSE)," ") | E71: 41234 | F71: pane eletrica | G71: 45902 | H71: Khetlyn | I71: Manutenção | J71: Corretiva | K71: Negociando | N71: =VLOOKUP(#REF!,'Base Cadastro '!#REF!,13,FALSE) -> #REF! | O71: MERCADO LIVRE | P71: Em Manutenção | Q71: Em Diagnóstico | R71: 45931 | S71: =IFERROR(DATEDIF(#REF!,#REF!,"D"),DATEDIF(#REF!,TODAY(),"D")) -> #REF! | T71: =IF(#REF!<=2,"Dentro do Prazo","Fora do Prazo") -> #REF! | U71: Ford Caoa Campinas | V71: ANA FLAVIA | W71: Set
C72: SFT5A78 | D72: =IFERROR(VLOOKUP(#REF!,'Base Cadastro '!#REF!,2,FALSE)," ") | E72: 534401 | F72: 17/09 quebrou a presilha do feixo de mola | G72: 45917 | H72: Luana | I72: Manutenção | J72: Corretiva | K72: Negociando | N72: =VLOOKUP(#REF!,'Base Cadastro '!#REF!,13,FALSE) -> #REF! | O72: MERCADO LIVRE | P72: Em Manutenção | Q72: Em Diagnóstico | R72: 45931 | S72: =IFERROR(DATEDIF(#REF!,#REF!,"D"),DATEDIF(#REF!,TODAY(),"D")) -> #REF! | T72: =IF(#REF!<=2,"Dentro do Prazo","Fora do Prazo") -> #REF! | U72: Oficina Ford | V72: FERNANDO | W72: Set
C73: RVC0J86 | D73: =IFERROR(VLOOKUP(#REF!,'Base Cadastro '!#REF!,2,FALSE)," ") | F73: Bateria | G73: 45929 | H73: Luana | I73: Manutenção | J73: Corretiva | K73: Negociando | O73: MERCADO LIVRE | P73: Em Manutenção | Q73: Aguardando socorro | R73: 45931 | S73: =IFERROR(DATEDIF(#REF!,#REF!,"D"),DATEDIF(#REF!,TODAY(),"D")) -> #REF! | T73: =IF(#REF!<=2,"Dentro do Prazo","Fora do Prazo") -> #REF! | U73: Localiza | V73: BRUNO/ERIVELTON | W73: Set
C74: GCX2D35 | D74: Sprinter 313 | F74: Pane eletrica, não da partida. | G74: 45930 | H74: Sara | I74: Manutenção | J74: Corretiva | K74: Negociando | N74: GP02 | O74: GRUPO PEREIRA | P74: Em Manutenção | Q74: Em Diagnóstico | R74: 45931 | S74: =IFERROR(DATEDIF(#REF!,#REF!,"D"),DATEDIF(#REF!,TODAY(),"D")) -> #REF! | T74: =IF(#REF!<=2,"Dentro do Prazo","Fora do Prazo") -> #REF! | U74: Mercedes | V74: RENATO
C75: RUM2B46 | D75: Fiorino Endurance Evo 1.4 2P | F75: embreagem | G75: 45930 | H75: Khetlyn | I75: Manutenção | J75: Corretiva | K75: Negociando | N75: SSP20 | O75: MERCADO LIVRE | P75: Em Manutenção | Q75: 45931 | R75: 45931 | S75: =IFERROR(DATEDIF(#REF!,#REF!,"D"),DATEDIF(#REF!,TODAY(),"D")) -> #REF! | T75: =IF(#REF!<=2,"Dentro do Prazo","Fora do Prazo") -> #REF! | U75: SM3 | V75: LARIANE | W75: Set
C76: GDY7B23 | D76: Sprinter 313 | F76: Pane elétrica | G76: 45932 | H76: Sara | I76: Manutenção | J76: Corretiva | K76: Negociando | N76: GP01 | O76: GRUPO PEREIRA | P76: Em Manutenção | Q76: Em Diagnóstico | R76: 45932 | S76: 0 | T76: Dentro do Prazo | U76: Estacionamento da Coca/MuriTruck | V76: ADRIANO | W76: Out
C77: RNZ3H57 | D77: DELIVERY 9.180 | E77: 142355 | F77: 15/07 - aquecimento constante da temperatura, trocas dos pivôs da suspensão dianteira buchas das bandeja dianteira/ | G77: 45812 | H77: Luana | I77: Manutenção | J77: Corretiva | K77: Negociando | N77: SSP5 | O77: MERCADO LIVRE | P77: Em Manutenção | Q77: Em Diagnóstico | R77: 45932 | S77: 120 | T77: Fora do Prazo | U77: Estacionamento da Coca/MuriTruck | V77: KAREN | W77: Jun
C78: SWH3G65 | D78: DELIVERY 9.180 | E78: 68772 | F78: Estourou um parafuso do baú | G78: 45923 | H78: Arthur | I78: Manutenção | J78: Corretiva | K78: Negociando | N78: SSP42 | O78: MERCADO LIVRE | P78: Em Manutenção | Q78: Em Diagnóstico | R78: 45932 | S78: 9 | T78: Fora do Prazo | W78: Set
C79: RVD9A40 | D79: Fiorino Endurance Evo 1.4 2P | E79: 134467 | F79: Pane életrica | G79: 45871 | H79: Hillary | I79: Manutenção | J79: Corretiva | K79: Aprovado | N79: SRS10 | O79: MERCADO LIVRE | P79: Em Manutenção | Q79: Em Diagnóstico | R79: 45932 | S79: 61 | T79: Fora do Prazo | U79: Safety Car | V79: FERNANDA | W79: Ago
C80: RUM2B35 | D80: Fiorino Endurance Evo 1.4 2P | E80: 1841240 | F80: Motor | G80: 45922 | H80: Khetlyn | I80: Manutenção | J80: Corretiva | K80: Negociando | N80: SSP25 | O80: MERCADO LIVRE | P80: Motor | Q80: Em Diagnóstico | R80: 45932 | S80: 10 | T80: Fora do Prazo | U80: Estacionamento da Coca/MuriTruck | V80: LEANDRO | W80: Set
C81: SDQ2A67 | D81: Kangoo Z.E. MAXI 5 Lugares 2P | E81: 48665 | F81: Veiculo pronto pra | G81: 45911 | H81: Julia | I81: Manutenção | J81: Corretiva | K81: Negociando | N81: SDF1 | O81: MERCADO LIVRE | P81: Em Manutenção | Q81: Em Diagnóstico | R81: 45932 | S81: 21 | T81: Fora do Prazo | U81: BR FRANCE (Localiza) | V81: Ercy netto | W81: Set
C82: RNC5H11 | D82: Master Furgão 8m³ | E82: 232976 | F82: Pane Eletrica | G82: 45888 | H82: Julia | I82: Manutenção | J82: Corretiva | K82: Negociando | N82: SSP36 | O82: MERCADO LIVRE | P82: Em Manutenção | Q82: Em Diagnóstico | R82: 45932 | S82: 44 | T82: Fora do Prazo | U82: Vegas Truck | V82: JULIANA | W82: Ago
C83: RNE7C83 | D83: MASTER FURGAO L1 | E83: 100 | F83: Veículo guinchado para a MuriTruck | G83: 45923 | H83: Luana | I83: Manutenção | J83: Corretiva | K83: Negociando | N83: BRRC01 | O83: MERCADO LIVRE | P83: Em Manutenção | Q83: Em Diagnóstico | R83: 45932 | S83: 9 | T83: Fora do Prazo | U83: Estacionamento da Muritruck | V83: BRUNO/ERIVELTON | W83: Set
C84: GJE0D54 | D84: Sprinter 313 | E84: 91953 | F84: Freios. | G84: 45887 | H84: Sara | I84: Manutenção | J84: Corretiva | K84: Negociando | N84: GP01 | O84: GRUPO PEREIRA | P84: Em Manutenção | Q84: Em Diagnóstico | R84: 45932 | S84: 45 | T84: Fora do Prazo | U84: De Nigris (São Bernado dos Campos) | V84: Adriano | W84: Ago
C85: SGH8H48 | D85: TRANSIT FURGÃO | E85: 77599 | F85: Vazamento no Motor- Problema no ABS/Pastilhas | G85: 45887 | H85: Hillary | I85: Manutenção | J85: Corretiva | K85: Negociando | N85: SRS3 | O85: MERCADO LIVRE | P85: Em Manutenção | Q85: Em Diagnóstico | R85: 45932 | S85: 45 | T85: Fora do Prazo | U85: Ford SuperAuto | V85: DEIVES | W85: Ago
C86: SGH8H55 | D86: TRANSIT FURGÃO | E86: 83296 | G86: 45908 | H86: Hillary | I86: Manutenção | J86: Corretiva | K86: Negociando | N86: SRS10 | O86: MERCADO LIVRE | P86: Em Manutenção | Q86: Em Diagnóstico | R86: 45932 | S86: 24 | T86: Fora do Prazo | U86: Safety Car | V86: FERNANDA | W86: Set
C87: SGH6H65 | D87: TRANSIT FURGÃO | E87: 43011 | F87: Veículo está perdendo a Força | G87: 45903 | H87: Hillary | I87: Manutenção | J87: Corretiva | K87: Negociando | N87: SRS8 | O87: MERCADO LIVRE | P87: Em Manutenção | Q87: Em Diagnóstico | R87: 45932 | S87: 29 | T87: Fora do Prazo | U87: Safety Car | V87: ALESSANDRA | W87: Set
C88: SGL2C02 | D88: TRANSIT FURGÃO | E88: 43789 | F88: Pneus e revisão | G88: 45924 | H88: Luana | I88: Manutenção | J88: Corretiva | K88: Negociando | N88: SSP11 | O88: MERCADO LIVRE | P88: Em Manutenção | Q88: Em Diagnóstico | R88: 45932 | S88: 8 | T88: Fora do Prazo | U88: Ford Prudente | V88: FERNANDO | W88: Set
C89: QXJ9E76 | D89: Fiorino Endurance Evo 1.4 2P | E89: 16516 | F89: motor retifiica | G89: 45895 | H89: Julia | I89: Manutenção | J89: Corretiva | K89: Aprovado | L89: 5800 | M89: 5250 | N89: SAM1 | O89: MERCADO LIVRE | P89: Em Manutenção | Q89: 45933 | R89: 45932 | S89: 37 | T89: Fora do Prazo
C90: RUX9G83 | D90: Fiorino Endurance Evo 1.4 2P | E90: 10203 | F90: Caixa de direção e cabo de embreagem | G90: 45926 | H90: Julia | I90: Manutenção | J90: Corretiva | K90: Aprovado | L90: 2090 | N90: SBA1 | O90: MERCADO LIVRE | P90: Em Manutenção | Q90: 45931 | R90: 45932 | S90: 6 | T90: Fora do Prazo | U90: Mecânica Wellington | V90: SARA | W90: Set
C91: RUW5D89 | D91: Partner Rapid Business Pack 1.4 2P | E91: 624870 | F91: Rolamento da roda | G91: 45903 | H91: Julia | I91: Manutenção | J91: Corretiva | K91: Negociando | N91: SMS1 | O91: MERCADO LIVRE | P91: Em Manutenção | Q91: Em Diagnóstico | R91: 45932 | S91: 29 | T91: Fora do Prazo | U91: Bhankar Serviço Automotivo | V91: SAMANTHA | W91: Set
C92: RNF2B74 | D92: Master Furgão 8m³ | G92: 45932 | I92: Manutenção | J92: Corretiva | K92: Negociando | N92: SSP22 | O92: MERCADO LIVRE | P92: EM Manutenção | Q92: 45932 | R92: 45932 | S92: 0 | T92: Dentro do Prazo
C93: GEF8B74 | D93: =IFERROR(VLOOKUP(#REF!,'Base Cadastro '!#REF!,2,FALSE)," ") | E93: 113740 | F93: Pane Elétrica | G93: 45891 | H93: Sara | I93: Manutenção | J93: Corretiva | K93: Negociando | N93: =VLOOKUP(#REF!,'Base Cadastro '!#REF!,13,FALSE) -> #REF! | O93: GRUPO PEREIRA | P93: Em Manutenção | Q93: 45933 | R93: 45933 | S93: =IFERROR(DATEDIF(#REF!,#REF!,"D"),DATEDIF(#REF!,TODAY(),"D")) -> #REF! | T93: =IF(#REF!<=2,"Dentro do Prazo","Fora do Prazo") -> #REF! | U93: Estacionamento da Coca/MuriTruck | V93: Adriano | W93: Ago
C94: RNE0J08 | D94: =IFERROR(VLOOKUP(#REF!,'Base Cadastro '!#REF!,2,FALSE)," ") | E94: 217296 | F94: embreagem | G94: 45930 | H94: Khetlyn | I94: Manutenção | J94: Corretiva | K94: Negociando | N94: SSP20 | O94: MERCADO LIVRE | P94: Em Manutenção | Q94: Em Diagnóstico | R94: 45932 | S94: =IFERROR(DATEDIF(#REF!,#REF!,"D"),DATEDIF(#REF!,TODAY(),"D")) -> #REF! | T94: =IF(#REF!<=2,"Dentro do Prazo","Fora do Prazo") -> #REF! | U94: MuriTruck | V94: LARIANE | W94: Set
C95: SGF9B40 | D95: =IFERROR(VLOOKUP(#REF!,'Base Cadastro '!#REF!,2,FALSE)," ") | E95: N/E | F95: Troca de pastilha | G95: 45930 | H95: Sara | I95: Manutenção | J95: Corretiva | K95: Aprovado | N95: =VLOOKUP(#REF!,'Base Cadastro '!#REF!,13,FALSE) -> #REF! | O95: SHOPEE | P95: Em Manutenção | Q95: Em Diagnóstico | R95: 45933 | S95: =IFERROR(DATEDIF(#REF!,#REF!,"D"),DATEDIF(#REF!,TODAY(),"D")) -> #REF! | T95: =IF(#REF!<=2,"Dentro do Prazo","Fora do Prazo") -> #REF! | U95: Estacionamento da Coca/MuriTruck
A96: 45784 | B96: 6588048 | C96: SDT9G94 | D96: E-Jumpy Furgão 2P | E96: 49542 | F96: Pneus/ Freios e Pane | G96: 45863 | H96: Hillary | I96: Manutenção | J96: Corretiva | K96: Aprovado | N96: SSP12 | O96: MERCADO LIVRE | P96: C/Reserva | Q96: 45930 | R96: 45932 | S96: 69 | T96: Fora do Prazo | U96: A J DE AMORIM E CIA (Localiza) | V96: GABRIEL | W96: Ago
C97: SFW0A73 | D97: TRANSIT FURGÃO | E97: 59845 | F97: freio | G97: 45914 | H97: Hillary | I97: Manutenção | J97: Corretiva | K97: Aprovado | N97: SSP22 | O97: MERCADO LIVRE | P97: Em Manutenção | Q97: 45933 | R97: 45933 | S97: 19 | T97: Fora do Prazo | U97: Lanzotti | V97: MAURICIO | W97: Set
C98: RUX9F74 | D98: Fiorino Endurance Evo 1.4 2P | E98: 10203 | F98: Alternador e radiador | G98: 45924 | H98: Julia | I98: Manutenção | J98: Corretiva | K98: Aprovado | N98: SBA1 | O98: MERCADO LIVRE | P98: Em Manutenção | Q98: 45932 | R98: 45932 | S98: 8 | T98: Fora do Prazo | U98: Mecânica Wellington | V98: SARA | W98: Set
C99: RTM6B70 | D99: Master Furgão 8m³ | E99: 70000 | F99: desgate natural da porta do baú | G99: 45882 | H99: Julia | I99: Sinistro | J99: Corretiva | K99: Aprovado | N99: SSP17 | O99: MERCADO LIVRE | P99: Em Manutenção | Q99: 45960 | R99: 45930 | S99: 48 | T99: Fora do Prazo | U99: GR Car | V99: IGOR | W99: Set
C100: SFW0A73 | D100: TRANSIT FURGÃO | E100: 598450 | F100: Bomba de combustivel | G100: 45926 | H100: Khetlyn | I100: Manutenção | J100: Corretiva | K100: Negociando | N100: SSP22 | O100: MERCADO LIVRE | P100: Em Manutenção | Q100: Em Diagnóstico | R100: 45932 | S100: 6 | T100: Fora do Prazo | U100: Estacionamento da Base | V100: MAURICIO | W100: Set
...

Sheet Geral Frota Antiga 
A1: Placa | B1: Prefixo | C1: Modelo | D1: Perfil cadastro | E1: Locadora | F1: Rastreador | G1: Status Rastreador | H1: Ano | I1: Estado | J1: SVC | K1: Base | L1: Operação | M1: Focal | N1: Líder | O1: Regional | P1: BIP | Q1: Dias S/ Rodar | R1: Status DDS | S1: Status final | T1: Protocolo | U1: Data da abertura | V1: Data de parada | W1: Observação | X1: Status | Y1: Prazo | Z1: Oficina | AA1: Reserva | AB1: Modelo Reseerva | AC1: Utimo Bip Reserva | AD1: Dias sem Rodar | AE1: Tratativa força tarefa | AF1: Data Solicitada | AG1: Contato | AH1: Dias em manutenção | AI1: SLA | AJ1: Desmobilização
A2: SVL8C61 | C2: ACCELO 1016 | D2: VUC | E2: Maroni | F2: COBLI | H2: 2023 | I2: SP | J2: FMS09 | K2: FMS09 SÃO PAULO (SP) | L2: SHOPEE | M2: Sara | N2: KIMBERLLY | O2: DANIEL SHOPEE | P2: =IFERROR(VLOOKUP(DadosViagem5[[#This Row],[Placa]],BIP!A:E,5,FALSE),"") -> 45977 | Q2: =DATEDIF(DadosViagem5[[#This Row],[BIP]],TODAY(),"D") -> 1 | R2: =IFERROR(VLOOKUP(DadosViagem5[[#This Row],[Placa]],DDS!B:C,2,FALSE),"Verificar cadastro") -> Carregado | S2: Veículo Ativo | AD2: =IFERROR(DATEDIF(DadosViagem5[[#This Row],[Utimo Bip Reserva]],TODAY(),"D"),"") | AH2: 45807 | AI2: =IF(DadosViagem5[[#This Row],[Dias em manutenção ]]<5,"Dentro do Prazo","Fora do Prazo") -> Fora do Prazo | AJ2: #REF!
A3: GJG8C81 | C3: Sprinter 313 | D3: VAN | E3: Denigris | F3: COBLI | H3: 2022 | I3: SP | J3: FMS09 | K3: FMS09 SÃO PAULO (SP) | L3: SHOPEE | M3: Sara | N3: KIMBERLLY | O3: DANIEL SHOPEE | P3: =IFERROR(VLOOKUP(DadosViagem5[[#This Row],[Placa]],BIP!A:E,5,FALSE),"") -> 0 | Q3: =DATEDIF(DadosViagem5[[#This Row],[BIP]],TODAY(),"D") -> 45978 | R3: =IFERROR(VLOOKUP(DadosViagem5[[#This Row],[Placa]],DDS!B:C,2,FALSE),"Verificar cadastro") | S3: Veículo Ativo | AD3: =IFERROR(DATEDIF(DadosViagem5[[#This Row],[Utimo Bip Reserva]],TODAY(),"D"),"") | AH3: 45807 | AI3: =IF(DadosViagem5[[#This Row],[Dias em manutenção ]]<5,"Dentro do Prazo","Fora do Prazo") -> Fora do Prazo | AJ3: #REF!
A4: GEW1I64 | C4: ACCELO 1016 | D4: VUC | E4: Murici | F4: COBLI | H4: 2022 | I4: SP | J4: BRRC01 | K4: SC (FULL FILMENTE) FULL | L4: MERCADO LIVRE | M4: Luana | N4: BRUNO/ERIVELTON | O4: VITOR | P4: =IFERROR(VLOOKUP(DadosViagem5[[#This Row],[Placa]],BIP!A:E,5,FALSE),"") -> 0 | Q4: =DATEDIF(DadosViagem5[[#This Row],[BIP]],TODAY(),"D") -> 45978 | R4: =IFERROR(VLOOKUP(DadosViagem5[[#This Row],[Placa]],DDS!B:C,2,FALSE),"Verificar cadastro") | S4: Veículo Ativo | V4: 45692 | W4: Veiculo precisa fazer o Diferencial - irá para o alair 07/02/2025 - 18/03 - aguardando volante do motor, 28/05 - Alguma coisa corta o combustível de ir pros bicos, 02/05 - aguardando | X4: Corretiva | Y4: Aguardando Aprovação | Z4: De Nigris (São Bernado dos Campos) | AD4: =IFERROR(DATEDIF(DadosViagem5[[#This Row],[Utimo Bip Reserva]],TODAY(),"D"),"") | AE4: Foi solicitado a remoção do rastreador da placa, Dudu irá remover - 09/05 | AF4: 45705 | AH4: 115 | AI4: =IF(DadosViagem5[[#This Row],[Dias em manutenção ]]<5,"Dentro do Prazo","Fora do Prazo") -> Fora do Prazo | AJ4: #REF!
A5: GDL9E85 | C5: ACCELO 1016 | D5: VUC | E5: Murici | F5: COBLI | H5: 2021 | I5: SP | J5: FMS09 | K5: FMS09 SÃO PAULO (SP) | L5: SHOPEE | M5: Sara | N5: KIMBERLLY | O5: DANIEL SHOPEE | P5: =IFERROR(VLOOKUP(DadosViagem5[[#This Row],[Placa]],BIP!A:E,5,FALSE),"") -> 0 | Q5: =DATEDIF(DadosViagem5[[#This Row],[BIP]],TODAY(),"D") -> 45978 | R5: =IFERROR(VLOOKUP(DadosViagem5[[#This Row],[Placa]],DDS!B:C,2,FALSE),"Verificar cadastro") | S5: Veículo Ativo | AD5: =IFERROR(DATEDIF(DadosViagem5[[#This Row],[Utimo Bip Reserva]],TODAY(),"D"),"") | AH5: 2 | AI5: =IF(DadosViagem5[[#This Row],[Dias em manutenção ]]<5,"Dentro do Prazo","Fora do Prazo") -> Dentro do Prazo | AJ5: #REF!
A6: SVN3B68 | C6: DELIVERY 9.180 | D6: VUC | E6: Dibracan | F6: COBLI | H6: 2023 | I6: SP | J6: FMS09 | K6: FMS09 SÃO PAULO (SP) | L6: SHOPEE | M6: Sara | N6: KIMBERLLY | O6: DANIEL SHOPEE | P6: =IFERROR(VLOOKUP(DadosViagem5[[#This Row],[Placa]],BIP!A:E,5,FALSE),"") -> 45977 | Q6: =DATEDIF(DadosViagem5[[#This Row],[BIP]],TODAY(),"D") -> 1 | R6: =IFERROR(VLOOKUP(DadosViagem5[[#This Row],[Placa]],DDS!B:C,2,FALSE),"Verificar cadastro") -> Carregado | S6: Veículo Ativo | AD6: =IFERROR(DATEDIF(DadosViagem5[[#This Row],[Utimo Bip Reserva]],TODAY(),"D"),"") | AH6: 45807 | AI6: =IF(DadosViagem5[[#This Row],[Dias em manutenção ]]<5,"Dentro do Prazo","Fora do Prazo") -> Fora do Prazo | AJ6: #REF!
A7: SGL2C89 | C7: I/FORD TRANSIT 350 FL | D7: VAN | E7: Ford Go | F7: ITURAN | H7: 2024 | I7: SP | J7: FMS09 | K7: FMS09 SÃO PAULO (SP) | L7: SHOPEE | M7: Hillary | N7: GEOVANA | O7: DANIEL SHOPEE | P7: =IFERROR(VLOOKUP(DadosViagem5[[#This Row],[Placa]],BIP!A:E,5,FALSE),"") -> 0 | Q7: =DATEDIF(DadosViagem5[[#This Row],[BIP]],TODAY(),"D") -> 45978 | R7: =IFERROR(VLOOKUP(DadosViagem5[[#This Row],[Placa]],DDS!B:C,2,FALSE),"Verificar cadastro") | S7: Veículo Ativo | AH7: 20 | AI7: =IF(DadosViagem5[[#This Row],[Dias em manutenção ]]<5,"Dentro do Prazo","Fora do Prazo") -> Fora do Prazo | AJ7: #REF!
A8: GFS7F11 | C8: Sprinter 313 | D8: VAN | E8: Denigris | F8: COBLI | H8: 2023 | I8: SP | J8: FMS09 | K8: FMS09 SÃO PAULO (SP) | L8: SHOPEE | M8: Sara | N8: KIMBERLLY | O8: DANIEL SHOPEE | P8: =IFERROR(VLOOKUP(DadosViagem5[[#This Row],[Placa]],BIP!A:E,5,FALSE),"") -> 45977 | Q8: =DATEDIF(DadosViagem5[[#This Row],[BIP]],TODAY(),"D") -> 1 | R8: =IFERROR(VLOOKUP(DadosViagem5[[#This Row],[Placa]],DDS!B:C,2,FALSE),"Verificar cadastro") -> Operando | S8: Veículo Ativo | AD8: =IFERROR(DATEDIF(DadosViagem5[[#This Row],[Utimo Bip Reserva]],TODAY(),"D"),"") | AH8: 9 | AI8: =IF(DadosViagem5[[#This Row],[Dias em manutenção ]]<5,"Dentro do Prazo","Fora do Prazo") -> Fora do Prazo | AJ8: #REF!
A9: SGL2D40 | C9: I/FORD TRANSIT 350 FL | D9: VAN | E9: Ford Go | F9: ITURAN | H9: 2024 | I9: SP | J9: FMS09 | K9: FMS09 SÃO PAULO (SP) | L9: SHOPEE | M9: Hillary | N9: GEOVANA | O9: DANIEL SHOPEE | P9: =IFERROR(VLOOKUP(DadosViagem5[[#This Row],[Placa]],BIP!A:E,5,FALSE),"") -> 0 | Q9: =DATEDIF(DadosViagem5[[#This Row],[BIP]],TODAY(),"D") -> 45978 | R9: =IFERROR(VLOOKUP(DadosViagem5[[#This Row],[Placa]],DDS!B:C,2,FALSE),"Verificar cadastro") -> Falta Motorista | S9: Veículo Ativo | W9: Conferido pelo BIP - 05/09/2025 | AH9: 45807 | AI9: =IF(DadosViagem5[[#This Row],[Dias em manutenção ]]<5,"Dentro do Prazo","Fora do Prazo") -> Fora do Prazo | AJ9: #REF!
A10: GBV9I35 | C10: Sprinter 313 | D10: VAN | E10: Denigris | F10: COBLI | H10: 2023 | I10: SP | J10: FMS09 | K10: FMS09 SÃO PAULO (SP) | L10: SHOPEE | M10: Sara | N10: KIMBERLLY | O10: DANIEL SHOPEE | P10: =IFERROR(VLOOKUP(DadosViagem5[[#This Row],[Placa]],BIP!A:E,5,FALSE),"") -> 45977 | Q10: =DATEDIF(DadosViagem5[[#This Row],[BIP]],TODAY(),"D") -> 1 | R10: =IFERROR(VLOOKUP(DadosViagem5[[#This Row],[Placa]],DDS!B:C,2,FALSE),"Verificar cadastro") -> Carregado | S10: Veículo Ativo | AE10: Aguardando a oficina enviar o orçamento 17/04 | AH10: 88 | AI10: =IF(DadosViagem5[[#This Row],[Dias em manutenção ]]<5,"Dentro do Prazo","Fora do Prazo") -> Fora do Prazo | AJ10: #REF!
A11: SGL1J11 | C11: I/FORD TRANSIT 350 FL | D11: VAN | E11: Ford Go | F11: ITURAN | H11: 2024 | I11: SP | J11: FMS09 | K11: FMS09 SÃO PAULO (SP) | L11: SHOPEE | M11: Hillary | N11: GEOVANA | O11: DANIEL SHOPEE | P11: =IFERROR(VLOOKUP(DadosViagem5[[#This Row],[Placa]],BIP!A:E,5,FALSE),"") | Q11: =DATEDIF(DadosViagem5[[#This Row],[BIP]],TODAY(),"D") -> #VALUE! | R11: =IFERROR(VLOOKUP(DadosViagem5[[#This Row],[Placa]],DDS!B:C,2,FALSE),"Verificar cadastro") -> Carregado | S11: Veículo Ativo | W11: Conferido pelo gestor 20/08 | AH11: 23 | AI11: =IF(DadosViagem5[[#This Row],[Dias em manutenção ]]<5,"Dentro do Prazo","Fora do Prazo") -> Fora do Prazo | AJ11: #REF!
A12: GFX3I74 | C12: Sprinter 313 | D12: VAN | E12: Denigris | F12: COBLI | H12: 2023 | I12: SP | J12: FMS09 | K12: FMS09 SÃO PAULO (SP) | L12: SHOPEE | M12: Sara | N12: KIMBERLLY | O12: DANIEL SHOPEE | P12: =IFERROR(VLOOKUP(DadosViagem5[[#This Row],[Placa]],BIP!A:E,5,FALSE),"") -> 45977 | Q12: =DATEDIF(DadosViagem5[[#This Row],[BIP]],TODAY(),"D") -> 1 | R12: =IFERROR(VLOOKUP(DadosViagem5[[#This Row],[Placa]],DDS!B:C,2,FALSE),"Verificar cadastro") -> Operando | S12: Veículo Ativo | AD12: =IFERROR(DATEDIF(DadosViagem5[[#This Row],[Utimo Bip Reserva]],TODAY(),"D"),"") | AH12: 45807 | AI12: =IF(DadosViagem5[[#This Row],[Dias em manutenção ]]<5,"Dentro do Prazo","Fora do Prazo") -> Fora do Prazo | AJ12: #REF!
A13: STT3B07 | C13: MASTER FURGAO L1 | D13: VAN | E13: Murici | F13: COBLI | H13: 2023 | I13: SP | J13: FMS09 | K13: FMS09 SÃO PAULO (SP) | L13: SHOPEE | M13: Sara | N13: KIMBERLLY | O13: DANIEL SHOPEE | P13: =IFERROR(VLOOKUP(DadosViagem5[[#This Row],[Placa]],BIP!A:E,5,FALSE),"") -> 0 | Q13: =DATEDIF(DadosViagem5[[#This Row],[BIP]],TODAY(),"D") -> 45978 | R13: =IFERROR(VLOOKUP(DadosViagem5[[#This Row],[Placa]],DDS!B:C,2,FALSE),"Verificar cadastro") | S13: Veículo Ativo | AD13: =IFERROR(DATEDIF(DadosViagem5[[#This Row],[Utimo Bip Reserva]],TODAY(),"D"),"") | AH13: 45807 | AI13: =IF(DadosViagem5[[#This Row],[Dias em manutenção ]]<5,"Dentro do Prazo","Fora do Prazo") -> Fora do Prazo | AJ13: #REF!
A14: SVB7B38 | C14: DELIVERY 9.180 | D14: VUC | E14: Dibracan | F14: COBLI | H14: 2023 | I14: SP | J14: FMS09 | K14: FMS09 SÃO PAULO (SP) | L14: SHOPEE | M14: Sara | N14: KIMBERLLY | O14: DANIEL SHOPEE | P14: =IFERROR(VLOOKUP(DadosViagem5[[#This Row],[Placa]],BIP!A:E,5,FALSE),"") -> 45977 | Q14: =DATEDIF(DadosViagem5[[#This Row],[BIP]],TODAY(),"D") -> 1 | R14: =IFERROR(VLOOKUP(DadosViagem5[[#This Row],[Placa]],DDS!B:C,2,FALSE),"Verificar cadastro") -> Carregado | S14: Veículo Ativo | AD14: =IFERROR(DATEDIF(DadosViagem5[[#This Row],[Utimo Bip Reserva]],TODAY(),"D"),"") | AH14: 45807 | AI14: =IF(DadosViagem5[[#This Row],[Dias em manutenção ]]<5,"Dentro do Prazo","Fora do Prazo") -> Fora do Prazo | AJ14: #REF!
A15: GJN9E64 | C15: Sprinter 313 | D15: VAN | E15: Denigris | F15: COBLI | H15: 2022 | I15: SP | J15: FMS09 | K15: FMS09 SÃO PAULO (SP) | L15: SHOPEE | M15: Sara | N15: KIMBERLLY | O15: DANIEL SHOPEE | P15: =IFERROR(VLOOKUP(DadosViagem5[[#This Row],[Placa]],BIP!A:E,5,FALSE),"") -> 45977 | Q15: =DATEDIF(DadosViagem5[[#This Row],[BIP]],TODAY(),"D") -> 1 | S15: Veículo Ativo | AD15: =IFERROR(DATEDIF(DadosViagem5[[#This Row],[Utimo Bip Reserva]],TODAY(),"D"),"") | AE15: Aguardando a oficina enviar o orçamento 17/04 | AG15: Abner | AH15: 45807 | AI15: =IF(DadosViagem5[[#This Row],[Dias em manutenção ]]<5,"Dentro do Prazo","Fora do Prazo") -> Fora do Prazo | AJ15: #REF!
A16: SGF9B40 | C16: I/FORD TRANSIT 350 FL | D16: VAN | E16: Ford Go | F16: ITURAN | H16: 2023 | I16: SP | J16: FMS09 | K16: MM01 (CAJAMAR) | L16: SHOPEE | M16: Hillary | N16: GEOVANA | O16: DANIEL SHOPEE | P16: =IFERROR(VLOOKUP(DadosViagem5[[#This Row],[Placa]],BIP!A:E,5,FALSE),"") -> 45977 | Q16: =DATEDIF(DadosViagem5[[#This Row],[BIP]],TODAY(),"D") -> 1 | R16: =IFERROR(VLOOKUP(DadosViagem5[[#This Row],[Placa]],DDS!B:C,2,FALSE),"Verificar cadastro") -> Carregado | S16: Veículo Ativo | AD16: =IFERROR(DATEDIF(DadosViagem5[[#This Row],[Utimo Bip Reserva]],TODAY(),"D"),"") | AH16: 45807 | AI16: =IF(DadosViagem5[[#This Row],[Dias em manutenção ]]<5,"Dentro do Prazo","Fora do Prazo") -> Fora do Prazo | AJ16: #REF!
A17: SVI2E40 | C17: DELIVERY 9.180 | D17: VUC | E17: Dibracan | F17: COBLI | H17: 2023 | I17: SP | J17: FMS09 | K17: FMS09 SÃO PAULO (SP) | L17: SHOPEE | M17: Sara | N17: KIMBERLLY | O17: DANIEL SHOPEE | P17: =IFERROR(VLOOKUP(DadosViagem5[[#This Row],[Placa]],BIP!A:E,5,FALSE),"") -> 45977 | Q17: =DATEDIF(DadosViagem5[[#This Row],[BIP]],TODAY(),"D") -> 1 | R17: =IFERROR(VLOOKUP(DadosViagem5[[#This Row],[Placa]],DDS!B:C,2,FALSE),"Verificar cadastro") -> Carregado | S17: Veículo Ativo | AD17: =IFERROR(DATEDIF(DadosViagem5[[#This Row],[Utimo Bip Reserva]],TODAY(),"D"),"") | AH17: 45807 | AI17: =IF(DadosViagem5[[#This Row],[Dias em manutenção ]]<5,"Dentro do Prazo","Fora do Prazo") -> Fora do Prazo | AJ17: #REF!
A18: GEZ5H13 | C18: Sprinter 313 | D18: VAN | E18: Denigris | F18: COBLI | H18: 2023 | I18: SP | J18: FMS09 | K18: FMS09 SÃO PAULO (SP) | L18: SHOPEE | M18: Sara | N18: KIMBERLLY | O18: DANIEL SHOPEE | P18: =IFERROR(VLOOKUP(DadosViagem5[[#This Row],[Placa]],BIP!A:E,5,FALSE),"") -> 0 | Q18: =DATEDIF(DadosViagem5[[#This Row],[BIP]],TODAY(),"D") -> 45978 | R18: =IFERROR(VLOOKUP(DadosViagem5[[#This Row],[Placa]],DDS!B:C,2,FALSE),"Verificar cadastro") | S18: Veículo Ativo | AD18: =IFERROR(DATEDIF(DadosViagem5[[#This Row],[Utimo Bip Reserva]],TODAY(),"D"),"") | AH18: 45807 | AI18: =IF(DadosViagem5[[#This Row],[Dias em manutenção ]]<5,"Dentro do Prazo","Fora do Prazo") -> Fora do Prazo | AJ18: #REF!
A19: SWH0G90 | C19: ACCELO 817 | D19: CAMINHÃO | E19: Denigris | F19: COBLI | H19: 2023 | I19: SP | J19: FMS09 | K19: FMS09 SÃO PAULO (SP) | L19: SHOPEE | M19: Sara | N19: KIMBERLLY | O19: DANIEL SHOPEE | P19: =IFERROR(VLOOKUP(DadosViagem5[[#This Row],[Placa]],BIP!A:E,5,FALSE),"") -> 45977 | Q19: =DATEDIF(DadosViagem5[[#This Row],[BIP]],TODAY(),"D") -> 1 | R19: =IFERROR(VLOOKUP(DadosViagem5[[#This Row],[Placa]],DDS!B:C,2,FALSE),"Verificar cadastro") -> Carregado | S19: Veículo Ativo | AD19: =IFERROR(DATEDIF(DadosViagem5[[#This Row],[Utimo Bip Reserva]],TODAY(),"D"),"") | AH19: 45807 | AI19: =IF(DadosViagem5[[#This Row],[Dias em manutenção ]]<5,"Dentro do Prazo","Fora do Prazo") -> Fora do Prazo | AJ19: #REF!
A20: SVI6D65 | C20: ACCELO 1016 | D20: VUC | E20: Maroni | F20: COBLI | H20: 2023 | I20: SP | J20: FMS09 | K20: FMS09 SÃO PAULO (SP) | L20: SHOPEE | M20: Sara | N20: KIMBERLLY | O20: DANIEL SHOPEE | P20: =IFERROR(VLOOKUP(DadosViagem5[[#This Row],[Placa]],BIP!A:E,5,FALSE),"") -> 45977 | Q20: =DATEDIF(DadosViagem5[[#This Row],[BIP]],TODAY(),"D") -> 1 | R20: =IFERROR(VLOOKUP(DadosViagem5[[#This Row],[Placa]],DDS!B:C,2,FALSE),"Verificar cadastro") -> Carregado | S20: Veículo Ativo | AD20: =IFERROR(DATEDIF(DadosViagem5[[#This Row],[Utimo Bip Reserva]],TODAY(),"D"),"") | AH20: 45807 | AI20: =IF(DadosViagem5[[#This Row],[Dias em manutenção ]]<5,"Dentro do Prazo","Fora do Prazo") -> Fora do Prazo | AJ20: #REF!
A21: SWS5G99 | C21: DELIVERY 9.180 | D21: VUC | E21: Dibracan | F21: COBLI | H21: 2023 | I21: SP | J21: FMS09 | K21: FMS09 SÃO PAULO (SP) | L21: SHOPEE | M21: Sara | N21: KIMBERLLY | O21: DANIEL SHOPEE | P21: =IFERROR(VLOOKUP(DadosViagem5[[#This Row],[Placa]],BIP!A:E,5,FALSE),"") -> 45977 | Q21: =DATEDIF(DadosViagem5[[#This Row],[BIP]],TODAY(),"D") -> 1 | R21: =IFERROR(VLOOKUP(DadosViagem5[[#This Row],[Placa]],DDS!B:C,2,FALSE),"Verificar cadastro") -> Carregado | S21: Veículo Ativo | AD21: =IFERROR(DATEDIF(DadosViagem5[[#This Row],[Utimo Bip Reserva]],TODAY(),"D"),"") | AH21: 45807 | AI21: =IF(DadosViagem5[[#This Row],[Dias em manutenção ]]<5,"Dentro do Prazo","Fora do Prazo") -> Fora do Prazo | AJ21: #REF!
A22: GAC8H65 | C22: Sprinter 313 | D22: VAN | E22: Denigris | F22: COBLI | H22: 2022 | I22: SP | J22: FMS09 | K22: FMS09 SÃO PAULO (SP) | L22: SHOPEE | M22: Sara | N22: KIMBERLLY | O22: DANIEL SHOPEE | P22: =IFERROR(VLOOKUP(DadosViagem5[[#This Row],[Placa]],BIP!A:E,5,FALSE),"") -> 45977 | Q22: =DATEDIF(DadosViagem5[[#This Row],[BIP]],TODAY(),"D") -> 1 | R22: =IFERROR(VLOOKUP(DadosViagem5[[#This Row],[Placa]],DDS!B:C,2,FALSE),"Verificar cadastro") -> Carregado | S22: Veículo Ativo | AD22: =IFERROR(DATEDIF(DadosViagem5[[#This Row],[Utimo Bip Reserva]],TODAY(),"D"),"") | AH22: 45807 | AI22: =IF(DadosViagem5[[#This Row],[Dias em manutenção ]]<5,"Dentro do Prazo","Fora do Prazo") -> Fora do Prazo | AJ22: #REF!
A23: GDN9I61 | C23: Sprinter 313 | D23: VAN | E23: Denigris | F23: COBLI | H23: 2023 | I23: SP | J23: FMS09 | K23: FMS09 SÃO PAULO (SP) | L23: SHOPEE | M23: Sara | N23: KIMBERLLY | O23: DANIEL SHOPEE | P23: =IFERROR(VLOOKUP(DadosViagem5[[#This Row],[Placa]],BIP!A:E,5,FALSE),"") -> 45977 | Q23: =DATEDIF(DadosViagem5[[#This Row],[BIP]],TODAY(),"D") -> 1 | R23: =IFERROR(VLOOKUP(DadosViagem5[[#This Row],[Placa]],DDS!B:C,2,FALSE),"Verificar cadastro") -> Operando | S23: Veículo Ativo | AD23: =IFERROR(DATEDIF(DadosViagem5[[#This Row],[Utimo Bip Reserva]],TODAY(),"D"),"") | AH23: 45807 | AI23: =IF(DadosViagem5[[#This Row],[Dias em manutenção ]]<5,"Dentro do Prazo","Fora do Prazo") -> Fora do Prazo | AJ23: #REF!
A24: GCI0A64 | C24: Sprinter 313 | D24: VAN | E24: Denigris | F24: COBLI | H24: 2023 | I24: SP | J24: FMS09 | K24: FMS09 SÃO PAULO (SP) | L24: SHOPEE | M24: Sara | N24: KIMBERLLY | O24: DANIEL SHOPEE | P24: =IFERROR(VLOOKUP(DadosViagem5[[#This Row],[Placa]],BIP!A:E,5,FALSE),"") -> 0 | Q24: =DATEDIF(DadosViagem5[[#This Row],[BIP]],TODAY(),"D") -> 45978 | R24: =IFERROR(VLOOKUP(DadosViagem5[[#This Row],[Placa]],DDS!B:C,2,FALSE),"Verificar cadastro") | S24: Veículo Ativo | AD24: =IFERROR(DATEDIF(DadosViagem5[[#This Row],[Utimo Bip Reserva]],TODAY(),"D"),"") | AH24: 45807 | AI24: =IF(DadosViagem5[[#This Row],[Dias em manutenção ]]<5,"Dentro do Prazo","Fora do Prazo") -> Fora do Prazo | AJ24: #REF!
A25: GBJ3A92 | C25: Sprinter 313 | D25: VAN | E25: Denigris | F25: COBLI | H25: 2023 | I25: SP | J25: FMS09 | K25: FMS09 SÃO PAULO (SP) | L25: SHOPEE | M25: Sara | N25: KIMBERLLY | O25: DANIEL SHOPEE | P25: =IFERROR(VLOOKUP(DadosViagem5[[#This Row],[Placa]],BIP!A:E,5,FALSE),"") -> 45977 | Q25: =DATEDIF(DadosViagem5[[#This Row],[BIP]],TODAY(),"D") -> 1 | R25: =IFERROR(VLOOKUP(DadosViagem5[[#This Row],[Placa]],DDS!B:C,2,FALSE),"Verificar cadastro") -> Operando | S25: Veículo Ativo | AD25: =IFERROR(DATEDIF(DadosViagem5[[#This Row],[Utimo Bip Reserva]],TODAY(),"D"),"") | AH25: 45807 | AI25: =IF(DadosViagem5[[#This Row],[Dias em manutenção ]]<5,"Dentro do Prazo","Fora do Prazo") -> Fora do Prazo | AJ25: #REF!
A26: SWI8D46 | C26: ACCELO 1016 | D26: VUC | E26: Maroni | F26: Wrsat | H26: 2023 | I26: SP | J26: FMS09 | K26: FMS09 SÃO PAULO (SP) | L26: SHOPEE | M26: Sara | N26: KIMBERLLY | O26: DANIEL SHOPEE | P26: =IFERROR(VLOOKUP(DadosViagem5[[#This Row],[Placa]],BIP!A:E,5,FALSE),"") -> 0 | Q26: =DATEDIF(DadosViagem5[[#This Row],[BIP]],TODAY(),"D") -> 45978 | R26: =IFERROR(VLOOKUP(DadosViagem5[[#This Row],[Placa]],DDS!B:C,2,FALSE),"Verificar cadastro") | S26: Veículo Ativo | AD26: =IFERROR(DATEDIF(DadosViagem5[[#This Row],[Utimo Bip Reserva]],TODAY(),"D"),"") | AH26: 45807 | AI26: =IF(DadosViagem5[[#This Row],[Dias em manutenção ]]<5,"Dentro do Prazo","Fora do Prazo") -> Fora do Prazo | AJ26: #REF!
A27: FDX3G43 | C27: DELIVERY 9.180 | D27: CAMINHÃO | E27: Maroni | F27: Wrsat | H27: 2021 | I27: SP | J27: FMS09 | K27: FMS09 SÃO PAULO (SP) | L27: SHOPEE | M27: Sara | N27: KIMBERLLY | O27: DANIEL SHOPEE | P27: =IFERROR(VLOOKUP(DadosViagem5[[#This Row],[Placa]],BIP!A:E,5,FALSE),"") -> 0 | Q27: =DATEDIF(DadosViagem5[[#This Row],[BIP]],TODAY(),"D") -> 45978 | R27: =IFERROR(VLOOKUP(DadosViagem5[[#This Row],[Placa]],DDS!B:C,2,FALSE),"Verificar cadastro") | S27: Veículo Ativo | AD27: =IFERROR(DATEDIF(DadosViagem5[[#This Row],[Utimo Bip Reserva]],TODAY(),"D"),"") | AH27: #VALUE! | AI27: =IF(DadosViagem5[[#This Row],[Dias em manutenção ]]<5,"Dentro do Prazo","Fora do Prazo") -> #VALUE! | AJ27: #REF!
A28: SUZ9D42 | C28: ACCELO 1016 | D28: VUC | E28: Maroni | F28: Wrsat | H28: 2023 | I28: SP | J28: FMS09 | K28: FMS09 SÃO PAULO (SP) | L28: SHOPEE | M28: Sara | N28: KIMBERLLY | O28: DANIEL SHOPEE | P28: =IFERROR(VLOOKUP(DadosViagem5[[#This Row],[Placa]],BIP!A:E,5,FALSE),"") -> 45977 | Q28: =DATEDIF(DadosViagem5[[#This Row],[BIP]],TODAY(),"D") -> 1 | R28: =IFERROR(VLOOKUP(DadosViagem5[[#This Row],[Placa]],DDS!B:C,2,FALSE),"Verificar cadastro") -> Carregado | S28: Veículo Ativo | AD28: =IFERROR(DATEDIF(DadosViagem5[[#This Row],[Utimo Bip Reserva]],TODAY(),"D"),"") | AH28: 45807 | AI28: =IF(DadosViagem5[[#This Row],[Dias em manutenção ]]<5,"Dentro do Prazo","Fora do Prazo") -> Fora do Prazo | AJ28: #REF!
A29: SVD7A43 | C29: ACCELO 1016 | D29: VUC | E29: Maroni | F29: Wrsat | H29: 2024 | I29: SP | J29: FMS09 | K29: FMS09 SÃO PAULO (SP) | L29: SHOPEE | M29: Sara | N29: KIMBERLLY | O29: DANIEL SHOPEE | P29: =IFERROR(VLOOKUP(DadosViagem5[[#This Row],[Placa]],BIP!A:E,5,FALSE),"") -> 45977 | Q29: =DATEDIF(DadosViagem5[[#This Row],[BIP]],TODAY(),"D") -> 1 | R29: =IFERROR(VLOOKUP(DadosViagem5[[#This Row],[Placa]],DDS!B:C,2,FALSE),"Verificar cadastro") -> Carregado | S29: Veículo Ativo | AD29: =IFERROR(DATEDIF(DadosViagem5[[#This Row],[Utimo Bip Reserva]],TODAY(),"D"),"") | AH29: 45807 | AI29: =IF(DadosViagem5[[#This Row],[Dias em manutenção ]]<5,"Dentro do Prazo","Fora do Prazo") -> Fora do Prazo | AJ29: #REF!
A30: SVJ3F95 | C30: ACCELO 1016 | D30: VUC | E30: Maroni | F30: COBLI | H30: 2023 | I30: SP | J30: FMS09 | K30: FMS09 SÃO PAULO (SP) | L30: SHOPEE | M30: Sara | N30: KIMBERLLY | O30: DANIEL SHOPEE | P30: =IFERROR(VLOOKUP(DadosViagem5[[#This Row],[Placa]],BIP!A:E,5,FALSE),"") -> 45977 | Q30: =DATEDIF(DadosViagem5[[#This Row],[BIP]],TODAY(),"D") -> 1 | R30: =IFERROR(VLOOKUP(DadosViagem5[[#This Row],[Placa]],DDS!B:C,2,FALSE),"Verificar cadastro") -> Carregado | S30: Veículo Ativo | AD30: =IFERROR(DATEDIF(DadosViagem5[[#This Row],[Utimo Bip Reserva]],TODAY(),"D"),"") | AE30: Aguardando espaço na oficina 10/04 | AH30: 45807 | AI30: =IF(DadosViagem5[[#This Row],[Dias em manutenção ]]<5,"Dentro do Prazo","Fora do Prazo") -> Fora do Prazo | AJ30: #REF!
A31: SUW8J92 | C31: ACCELO 1016 | D31: VUC | E31: Maroni | F31: Wrsat | H31: 2024 | I31: SP | J31: FMS09 | K31: FMS09 SÃO PAULO (SP) | L31: SHOPEE | M31: Sara | N31: KIMBERLLY | O31: DANIEL SHOPEE | P31: =IFERROR(VLOOKUP(DadosViagem5[[#This Row],[Placa]],BIP!A:E,5,FALSE),"") -> 45977 | Q31: =DATEDIF(DadosViagem5[[#This Row],[BIP]],TODAY(),"D") -> 1 | R31: =IFERROR(VLOOKUP(DadosViagem5[[#This Row],[Placa]],DDS!B:C,2,FALSE),"Verificar cadastro") -> Carregado | S31: Veículo Ativo | AD31: =IFERROR(DATEDIF(DadosViagem5[[#This Row],[Utimo Bip Reserva]],TODAY(),"D"),"") | AH31: 45807 | AI31: =IF(DadosViagem5[[#This Row],[Dias em manutenção ]]<5,"Dentro do Prazo","Fora do Prazo") -> Fora do Prazo | AJ31: #REF!
A32: RTM9F09 | C32: DELIVERY 9.180 | D32: VUC | E32: Localiza | F32: GEOTAB | H32: 2021 | I32: SP | J32: FMS09 | K32: FMS09 SÃO PAULO (SP) | L32: SHOPEE | M32: Sara | N32: KIMBERLLY | O32: DANIEL SHOPEE | P32: =IFERROR(VLOOKUP(DadosViagem5[[#This Row],[Placa]],BIP!A:E,5,FALSE),"") -> 45977 | Q32: =DATEDIF(DadosViagem5[[#This Row],[BIP]],TODAY(),"D") -> 1 | R32: =IFERROR(VLOOKUP(DadosViagem5[[#This Row],[Placa]],DDS!B:C,2,FALSE),"Verificar cadastro") -> Operando | S32: Veículo Ativo | AD32: =IFERROR(DATEDIF(DadosViagem5[[#This Row],[Utimo Bip Reserva]],TODAY(),"D"),"") | AH32: 45807 | AI32: =IF(DadosViagem5[[#This Row],[Dias em manutenção ]]<5,"Dentro do Prazo","Fora do Prazo") -> Fora do Prazo | AJ32: #REF!
A33: SGL2C88 | C33: I/FORD TRANSIT 350 FL | D33: VAN | E33: Ford Go | F33: ITURAN | H33: 2023 | I33: SP | J33: FMS09 | K33: FMS09 SÃO PAULO (SP) | L33: SHOPEE | M33: Hillary | N33: GEOVANA | O33: DANIEL SHOPEE | P33: =IFERROR(VLOOKUP(DadosViagem5[[#This Row],[Placa]],BIP!A:E,5,FALSE),"") -> 45977 | Q33: =DATEDIF(DadosViagem5[[#This Row],[BIP]],TODAY(),"D") -> 1 | R33: =IFERROR(VLOOKUP(DadosViagem5[[#This Row],[Placa]],DDS!B:C,2,FALSE),"Verificar cadastro") -> Carregado | S33: Veículo Ativo | AD33: =IFERROR(DATEDIF(DadosViagem5[[#This Row],[Utimo Bip Reserva]],TODAY(),"D"),"") | AH33: 45807 | AI33: =IF(DadosViagem5[[#This Row],[Dias em manutenção ]]<5,"Dentro do Prazo","Fora do Prazo") -> Fora do Prazo | AJ33: #REF!
A34: SGL2C26 | C34: I/FORD TRANSIT 350 FL | D34: VAN | E34: Ford Go | F34: ITURAN | H34: 2023 | I34: SP | J34: FMS09 | K34: FMS09 SÃO PAULO (SP) | L34: SHOPEE | M34: Hillary | N34: GEOVANA | O34: DANIEL SHOPEE | P34: =IFERROR(VLOOKUP(DadosViagem5[[#This Row],[Placa]],BIP!A:E,5,FALSE),"") -> 45977 | Q34: =DATEDIF(DadosViagem5[[#This Row],[BIP]],TODAY(),"D") -> 1 | R34: =IFERROR(VLOOKUP(DadosViagem5[[#This Row],[Placa]],DDS!B:C,2,FALSE),"Verificar cadastro") -> Carregado | S34: Veículo Ativo | AD34: =IFERROR(DATEDIF(DadosViagem5[[#This Row],[Utimo Bip Reserva]],TODAY(),"D"),"") | AH34: 45807 | AI34: =IF(DadosViagem5[[#This Row],[Dias em manutenção ]]<5,"Dentro do Prazo","Fora do Prazo") -> Fora do Prazo | AJ34: #REF!
A35: SGL1J13 | C35: I/FORD TRANSIT 350 FL | D35: VAN | E35: Ford Go | F35: ITURAN | H35: 2024 | I35: SP | J35: FMS09 | K35: FMS09 SÃO PAULO (SP) | L35: SHOPEE | M35: Hillary | N35: GEOVANA | O35: DANIEL SHOPEE | P35: =IFERROR(VLOOKUP(DadosViagem5[[#This Row],[Placa]],BIP!A:E,5,FALSE),"") -> 45977 | Q35: =DATEDIF(DadosViagem5[[#This Row],[BIP]],TODAY(),"D") -> 1 | R35: =IFERROR(VLOOKUP(DadosViagem5[[#This Row],[Placa]],DDS!B:C,2,FALSE),"Verificar cadastro") -> Operando | S35: Veículo Ativo | AH35: 45807 | AI35: =IF(DadosViagem5[[#This Row],[Dias em manutenção ]]<5,"Dentro do Prazo","Fora do Prazo") -> Fora do Prazo | AJ35: #REF!
A36: SUJ9H28 | C36: ACCELO 1016 | D36: VUC | E36: Maroni | F36: Wrsat | H36: 2024 | I36: SP | J36: FMS09 | K36: FMS09 SÃO PAULO (SP) | L36: SHOPEE | M36: Sara | N36: KIMBERLLY | O36: DANIEL SHOPEE | P36: =IFERROR(VLOOKUP(DadosViagem5[[#This Row],[Placa]],BIP!A:E,5,FALSE),"") -> 45977 | Q36: =DATEDIF(DadosViagem5[[#This Row],[BIP]],TODAY(),"D") -> 1 | R36: =IFERROR(VLOOKUP(DadosViagem5[[#This Row],[Placa]],DDS!B:C,2,FALSE),"Verificar cadastro") -> Carregado | S36: Veículo Ativo | W36: Conferido pelo gestor 20/08 | AD36: =IFERROR(DATEDIF(DadosViagem5[[#This Row],[Utimo Bip Reserva]],TODAY(),"D"),"") | AE36: Aguardando oficina encaminhar informação - 17/04 | AH36: 45807 | AI36: =IF(DadosViagem5[[#This Row],[Dias em manutenção ]]<5,"Dentro do Prazo","Fora do Prazo") -> Fora do Prazo | AJ36: #REF!
A37: RTM7G82 | C37: DELIVERY 9.180 | D37: VUC | E37: Localiza | F37: GEOTAB | H37: 2021 | I37: SP | J37: FMS09 | K37: FMS09 SÃO PAULO (SP) | L37: SHOPEE | M37: Sara | N37: KIMBERLLY | O37: DANIEL SHOPEE | P37: =IFERROR(VLOOKUP(DadosViagem5[[#This Row],[Placa]],BIP!A:E,5,FALSE),"") -> 45977 | Q37: =DATEDIF(DadosViagem5[[#This Row],[BIP]],TODAY(),"D") -> 1 | R37: =IFERROR(VLOOKUP(DadosViagem5[[#This Row],[Placa]],DDS!B:C,2,FALSE),"Verificar cadastro") -> Carregado | S37: Veículo Ativo | W37: Conferido pelo BIP 20/08 | AD37: =IFERROR(DATEDIF(DadosViagem5[[#This Row],[Utimo Bip Reserva]],TODAY(),"D"),"") | AH37: 45807 | AI37: =IF(DadosViagem5[[#This Row],[Dias em manutenção ]]<5,"Dentro do Prazo","Fora do Prazo") -> Fora do Prazo | AJ37: #REF!
A38: RTM7G83 | C38: DELIVERY 9.180 | D38: VUC | E38: Localiza | F38: GEOTAB | H38: 2021 | I38: SP | J38: FMS09 | K38: FMS09 SÃO PAULO (SP) | L38: SHOPEE | M38: Sara | N38: KIMBERLLY | O38: DANIEL SHOPEE | P38: =IFERROR(VLOOKUP(DadosViagem5[[#This Row],[Placa]],BIP!A:E,5,FALSE),"") -> 0 | Q38: =DATEDIF(DadosViagem5[[#This Row],[BIP]],TODAY(),"D") -> 45978 | R38: =IFERROR(VLOOKUP(DadosViagem5[[#This Row],[Placa]],DDS!B:C,2,FALSE),"Verificar cadastro") | S38: Veículo Ativo | AD38: =IFERROR(DATEDIF(DadosViagem5[[#This Row],[Utimo Bip Reserva]],TODAY(),"D"),"") | AH38: 45807 | AI38: =IF(DadosViagem5[[#This Row],[Dias em manutenção ]]<5,"Dentro do Prazo","Fora do Prazo") -> Fora do Prazo | AJ38: #REF!
A39: TOE7D26 | B39: 774 | C39: I/FORD TRANSIT 350 FL | D39: VAN | E39: Ford Go | F39: ITURAN | H39: 2024 | I39: SP | J39: FMS09 | K39: FMS09 SÃO PAULO (SP) | L39: SHOPEE | M39: Hillary | N39: GEOVANA | O39: DANIEL SHOPEE | P39: =IFERROR(VLOOKUP(DadosViagem5[[#This Row],[Placa]],BIP!A:E,5,FALSE),"") | Q39: =DATEDIF(DadosViagem5[[#This Row],[BIP]],TODAY(),"D") -> #VALUE! | R39: =IFERROR(VLOOKUP(DadosViagem5[[#This Row],[Placa]],DDS!B:C,2,FALSE),"Verificar cadastro") -> Carregado | S39: Veículo Ativo | AH39: 45807 | AI39: =IF(DadosViagem5[[#This Row],[Dias em manutenção ]]<5,"Dentro do Prazo","Fora do Prazo") -> Fora do Prazo | AJ39: #REF!
A40: TOE7D05 | B40: 769 | C40: I/FORD TRANSIT 350 FL | D40: VAN | E40: Ford Go | F40: ITURAN | H40: 2023 | I40: SP | J40: FMS09 | K40: FMS09 SÃO PAULO (SP) | L40: SHOPEE | M40: Hillary | N40: GEOVANA | O40: DANIEL SHOPEE | P40: =IFERROR(VLOOKUP(DadosViagem5[[#This Row],[Placa]],BIP!A:E,5,FALSE),"") | Q40: =DATEDIF(DadosViagem5[[#This Row],[BIP]],TODAY(),"D") -> #VALUE! | R40: =IFERROR(VLOOKUP(DadosViagem5[[#This Row],[Placa]],DDS!B:C,2,FALSE),"Verificar cadastro") -> Carregado | S40: Veículo Ativo | AH40: 45807 | AI40: =IF(DadosViagem5[[#This Row],[Dias em manutenção ]]<5,"Dentro do Prazo","Fora do Prazo") -> Fora do Prazo | AJ40: #REF!
A41: TOE7D03 | B41: 773 | C41: I/FORD TRANSIT 350 FL | D41: VAN | E41: Ford Go | F41: ITURAN | H41: 2023 | I41: SP | J41: FMS09 | K41: FMS09 SÃO PAULO (SP) | L41: SHOPEE | M41: Hillary | N41: GEOVANA | O41: DANIEL SHOPEE | P41: =IFERROR(VLOOKUP(DadosViagem5[[#This Row],[Placa]],BIP!A:E,5,FALSE),"") | Q41: =DATEDIF(DadosViagem5[[#This Row],[BIP]],TODAY(),"D") -> #VALUE! | R41: =IFERROR(VLOOKUP(DadosViagem5[[#This Row],[Placa]],DDS!B:C,2,FALSE),"Verificar cadastro") | S41: Veículo Ativo | AH41: 45807 | AI41: =IF(DadosViagem5[[#This Row],[Dias em manutenção ]]<5,"Dentro do Prazo","Fora do Prazo") -> Fora do Prazo | AJ41: #REF!
A42: TOE7C88 | C42: I/FORD TRANSIT 350 FL | D42: VAN | E42: Ford Go | F42: COBLI | H42: 2024 | I42: SP | J42: FMS09 | K42: FMS09 SÃO PAULO (SP) | L42: SHOPEE | M42: Hillary | N42: GEOVANA | O42: DANIEL SHOPEE | P42: =IFERROR(VLOOKUP(DadosViagem5[[#This Row],[Placa]],BIP!A:E,5,FALSE),"") | Q42: =DATEDIF(DadosViagem5[[#This Row],[BIP]],TODAY(),"D") -> #VALUE! | R42: =IFERROR(VLOOKUP(DadosViagem5[[#This Row],[Placa]],DDS!B:C,2,FALSE),"Verificar cadastro") -> Carregado | S42: Veículo Ativo | W42: Falta de motorista 24/08 | AH42: 45807 | AI42: =IF(DadosViagem5[[#This Row],[Dias em manutenção ]]<5,"Dentro do Prazo","Fora do Prazo") -> Fora do Prazo | AJ42: #REF!
A43: TOE7C95 | C43: I/FORD TRANSIT 350 FL | D43: VUC | E43: Ford Go | F43: COBLI | H43: 2024 | I43: SP | J43: FMS09 | K43: FMS09 SÃO PAULO (SP) | L43: SHOPEE | M43: Hillary | N43: GEOVANA | O43: DANIEL SHOPEE | P43: =IFERROR(VLOOKUP(DadosViagem5[[#This Row],[Placa]],BIP!A:E,5,FALSE),"") | Q43: =DATEDIF(DadosViagem5[[#This Row],[BIP]],TODAY(),"D") -> #VALUE! | R43: =IFERROR(VLOOKUP(DadosViagem5[[#This Row],[Placa]],DDS!B:C,2,FALSE),"Verificar cadastro") | S43: Veículo Ativo | AH43: 45807 | AI43: =IF(DadosViagem5[[#This Row],[Dias em manutenção ]]<5,"Dentro do Prazo","Fora do Prazo") -> Fora do Prazo | AJ43: #REF!
A44: SVC9F75 | C44: Fiorino Endurance Evo 1.4 2P | D44: UTILITARIO | E44: Murici | F44: COBLI | H44: 2025 | I44: SP | J44: FMS09 | K44: FMS09 SÃO PAULO (SP) | L44: SHOPEE | M44: Sara | N44: KIMBERLLY | O44: DANIEL SHOPEE | P44: =IFERROR(VLOOKUP(DadosViagem5[[#This Row],[Placa]],BIP!A:E,5,FALSE),"") | Q44: =DATEDIF(DadosViagem5[[#This Row],[BIP]],TODAY(),"D") -> #VALUE! | R44: =IFERROR(VLOOKUP(DadosViagem5[[#This Row],[Placa]],DDS!B:C,2,FALSE),"Verificar cadastro") | S44: Veículo Ativo | W44: Conferido pelo gestor 20/08 | AD44: =IFERROR(DATEDIF(DadosViagem5[[#This Row],[Utimo Bip Reserva]],TODAY(),"D"),"") | AE44: Aguardando oficina encaminhar informação - 17/04 | AH44: 45807 | AI44: =IF(DadosViagem5[[#This Row],[Dias em manutenção ]]<5,"Dentro do Prazo","Fora do Prazo") -> Fora do Prazo | AJ44: #REF!
A45: SWU9J57 | C45: Fiorino Endurance Evo 1.4 2P | D45: UTILITARIO | E45: Murici | F45: COBLI | H45: 2025 | I45: SP | J45: FMS09 | K45: FMS09 SÃO PAULO (SP) | L45: SHOPEE | M45: Sara | N45: KIMBERLLY | O45: DANIEL SHOPEE | P45: =IFERROR(VLOOKUP(DadosViagem5[[#This Row],[Placa]],BIP!A:E,5,FALSE),"") | Q45: =DATEDIF(DadosViagem5[[#This Row],[BIP]],TODAY(),"D") -> #VALUE! | R45: =IFERROR(VLOOKUP(DadosViagem5[[#This Row],[Placa]],DDS!B:C,2,FALSE),"Verificar cadastro") -> Verificar cadastro | S45: Veículo Ativo | W45: Conferido pelo Gestor - 05/08/2025 | AD45: =IFERROR(DATEDIF(DadosViagem5[[#This Row],[Utimo Bip Reserva]],TODAY(),"D"),"") | AE45: Aguardando oficina encaminhar informação - 17/04 | AH45: 45807 | AI45: =IF(DadosViagem5[[#This Row],[Dias em manutenção ]]<5,"Dentro do Prazo","Fora do Prazo") -> Fora do Prazo | AJ45: #REF!
A46: TLK9H18 | C46: Fiorino Endurance Evo 1.4 2P | D46: UTILITARIO | E46: Murici | F46: COBLI | H46: 2025 | I46: SP | J46: FMS09 | K46: FMS09 SÃO PAULO (SP) | L46: SHOPEE | M46: Sara | N46: KIMBERLLY | O46: DANIEL SHOPEE | P46: =IFERROR(VLOOKUP(DadosViagem5[[#This Row],[Placa]],BIP!A:E,5,FALSE),"") | Q46: =DATEDIF(DadosViagem5[[#This Row],[BIP]],TODAY(),"D") -> #VALUE! | R46: =IFERROR(VLOOKUP(DadosViagem5[[#This Row],[Placa]],DDS!B:C,2,FALSE),"Verificar cadastro") -> Operando | S46: Veículo Ativo | W46: Conferido pelo gestor 20/08 | AD46: =IFERROR(DATEDIF(DadosViagem5[[#This Row],[Utimo Bip Reserva]],TODAY(),"D"),"") | AE46: Aguardando oficina encaminhar informação - 17/04 | AH46: 45807 | AI46: =IF(DadosViagem5[[#This Row],[Dias em manutenção ]]<5,"Dentro do Prazo","Fora do Prazo") -> Fora do Prazo | AJ46: #REF!
A47: TLZ6J18 | C47: Fiorino Endurance Evo 1.4 2P | D47: UTILITARIO | E47: Murici | F47: COBLI | H47: 2025 | I47: SC | J47: SSC5 | K47: SC (CRICIUMA) SSC5 | L47: MERCADO LIVRE | M47: Natallia | N47: REGIANE | O47: DIEGO | P47: 0 | Q47: 45950 | R47: =IFERROR(VLOOKUP(DadosViagem5[[#This Row],[Placa]],DDS!B:C,2,FALSE),"Verificar cadastro") -> Verificar cadastro | S47: Veículo Ativo | W47: Conferido pelo Gestor - 05/08/2025 | AD47: =IFERROR(DATEDIF(DadosViagem5[[#This Row],[Utimo Bip Reserva]],TODAY(),"D"),"") | AE47: Aguardando oficina encaminhar informação - 17/04 | AH47: 45807 | AI47: =IF(DadosViagem5[[#This Row],[Dias em manutenção ]]<5,"Dentro do Prazo","Fora do Prazo") -> Fora do Prazo | AJ47: #REF!
A48: GEF8B74 | C48: Sprinter 313 | D48: VAN | E48: Denigris | F48: COBLI | H48: 2023 | I48: SP | J48: GP01 | K48: GP01 VARGEM GRANDE (GRUPO PEREIRA) | L48: GRUPO PEREIRA | M48: Sara | N48: Adriano | O48: GUILHERME | P48: =IFERROR(VLOOKUP(DadosViagem5[[#This Row],[Placa]],BIP!A:E,5,FALSE),"") -> 45977 | Q48: =DATEDIF(DadosViagem5[[#This Row],[BIP]],TODAY(),"D") -> 1 | R48: =IFERROR(VLOOKUP(DadosViagem5[[#This Row],[Placa]],DDS!B:C,2,FALSE),"Verificar cadastro") -> Carregado | S48: Veículo Ativo | W48: Disponibilizado para a Base - 28/10/2025 | AD48: =IFERROR(DATEDIF(DadosViagem5[[#This Row],[Utimo Bip Reserva]],TODAY(),"D"),"") | AH48: 45807 | AI48: =IF(DadosViagem5[[#This Row],[Dias em manutenção ]]<5,"Dentro do Prazo","Fora do Prazo") -> Fora do Prazo | AJ48: #REF!
A49: FJG5F03 | C49: Sprinter 313 | D49: VAN | E49: Denigris | F49: COBLI | H49: 2023 | I49: SP | J49: GP01 | K49: GP01 VARGEM GRANDE (GRUPO PEREIRA) | L49: GRUPO PEREIRA | M49: Sara | N49: Adriano | O49: GUILHERME | P49: =IFERROR(VLOOKUP(DadosViagem5[[#This Row],[Placa]],BIP!A:E,5,FALSE),"") -> 0 | Q49: =DATEDIF(DadosViagem5[[#This Row],[BIP]],TODAY(),"D") -> 45978 | R49: =IFERROR(VLOOKUP(DadosViagem5[[#This Row],[Placa]],DDS!B:C,2,FALSE),"Verificar cadastro") -> Manutenção | S49: Veículo Ativo | AD49: =IFERROR(DATEDIF(DadosViagem5[[#This Row],[Utimo Bip Reserva]],TODAY(),"D"),"") | AH49: 45807 | AI49: =IF(DadosViagem5[[#This Row],[Dias em manutenção ]]<5,"Dentro do Prazo","Fora do Prazo") -> Fora do Prazo | AJ49: #REF!
A50: GJE0D54 | C50: Sprinter 313 | D50: VAN | E50: Denigris | F50: COBLI | H50: 2022 | I50: SP | J50: GP01 | K50: GP01 VARGEM GRANDE (GRUPO PEREIRA) | L50: GRUPO PEREIRA | M50: Sara | N50: Adriano | O50: GUILHERME | P50: =IFERROR(VLOOKUP(DadosViagem5[[#This Row],[Placa]],BIP!A:E,5,FALSE),"") -> 45977 | Q50: =DATEDIF(DadosViagem5[[#This Row],[BIP]],TODAY(),"D") -> 1 | R50: =IFERROR(VLOOKUP(DadosViagem5[[#This Row],[Placa]],DDS!B:C,2,FALSE),"Verificar cadastro") -> Carregado | S50: Veículo Ativo | W50: disponibilizado para base 24/09 | AD50: =IFERROR(DATEDIF(DadosViagem5[[#This Row],[Utimo Bip Reserva]],TODAY(),"D"),"") | AG50: Motor | AH50: 73 | AI50: =IF(DadosViagem5[[#This Row],[Dias em manutenção ]]<5,"Dentro do Prazo","Fora do Prazo") -> Fora do Prazo | AJ50: #REF!
A51: GGQ9J34 | C51: Sprinter 313 | D51: VAN | E51: Denigris | F51: COBLI | H51: 2022 | I51: SP | J51: GP01 | K51: GP01 VARGEM GRANDE (GRUPO PEREIRA) | L51: GRUPO PEREIRA | M51: Sara | N51: Adriano | O51: GUILHERME | P51: =IFERROR(VLOOKUP(DadosViagem5[[#This Row],[Placa]],BIP!A:E,5,FALSE),"") -> 0 | Q51: =DATEDIF(DadosViagem5[[#This Row],[BIP]],TODAY(),"D") -> 45978 | R51: =IFERROR(VLOOKUP(DadosViagem5[[#This Row],[Placa]],DDS!B:C,2,FALSE),"Verificar cadastro") -> Manutenção | S51: Veículo Ativo | W51: conferido pelo bip 24/09 | AD51: =IFERROR(DATEDIF(DadosViagem5[[#This Row],[Utimo Bip Reserva]],TODAY(),"D"),"") | AH51: 45807 | AI51: =IF(DadosViagem5[[#This Row],[Dias em manutenção ]]<5,"Dentro do Prazo","Fora do Prazo") -> Fora do Prazo | AJ51: #REF!
A52: GBZ4B11 | C52: Sprinter 313 | D52: VAN | E52: Denigris | F52: COBLI | H52: 2023 | I52: SP | J52: GP01 | K52: GP01 VARGEM GRANDE (GRUPO PEREIRA) | L52: GRUPO PEREIRA | M52: Sara | N52: Adriano | O52: GUILHERME | P52: =IFERROR(VLOOKUP(DadosViagem5[[#This Row],[Placa]],BIP!A:E,5,FALSE),"") -> 45977 | Q52: =DATEDIF(DadosViagem5[[#This Row],[BIP]],TODAY(),"D") -> 1 | S52: Veículo Ativo | AD52: =IFERROR(DATEDIF(DadosViagem5[[#This Row],[Utimo Bip Reserva]],TODAY(),"D"),"") | AH52: 45807 | AI52: =IF(DadosViagem5[[#This Row],[Dias em manutenção ]]<5,"Dentro do Prazo","Fora do Prazo") -> Fora do Prazo | AJ52: #REF!
A53: GCP5D34 | C53: Sprinter 313 | D53: VAN | E53: Denigris | F53: COBLI | H53: 2023 | I53: SP | J53: GP01 | K53: GP01 VARGEM GRANDE (GRUPO PEREIRA) | L53: GRUPO PEREIRA | M53: Sara | N53: Adriano | O53: GUILHERME | P53: =IFERROR(VLOOKUP(DadosViagem5[[#This Row],[Placa]],BIP!A:E,5,FALSE),"") -> 45977 | Q53: =DATEDIF(DadosViagem5[[#This Row],[BIP]],TODAY(),"D") -> 1 | R53: =IFERROR(VLOOKUP(DadosViagem5[[#This Row],[Placa]],DDS!B:C,2,FALSE),"Verificar cadastro") -> Carregado | S53: Veículo Ativo | V53: 45875 | W53: veiculo guinchado com problema de arla | X53: Corretiva | Y53: Em Diagnóstico | Z53: De Nigris (São Bernado dos Campos) | AD53: =IFERROR(DATEDIF(DadosViagem5[[#This Row],[Utimo Bip Reserva]],TODAY(),"D"),"") | AH53: 45807 | AI53: =IF(DadosViagem5[[#This Row],[Dias em manutenção ]]<5,"Dentro do Prazo","Fora do Prazo") -> Fora do Prazo | AJ53: #REF!
A54: GEZ7B46 | C54: Sprinter 313 | D54: VAN | E54: Denigris | F54: COBLI | H54: 2023 | I54: SP | J54: GP01 | K54: GP01 VARGEM GRANDE (GRUPO PEREIRA) | L54: GRUPO PEREIRA | M54: Sara | N54: Adriano | O54: GUILHERME | P54: =IFERROR(VLOOKUP(DadosViagem5[[#This Row],[Placa]],BIP!A:E,5,FALSE),"") -> 45977 | Q54: =DATEDIF(DadosViagem5[[#This Row],[BIP]],TODAY(),"D") -> 1 | R54: =IFERROR(VLOOKUP(DadosViagem5[[#This Row],[Placa]],DDS!B:C,2,FALSE),"Verificar cadastro") -> Carregado | S54: Veículo Ativo | AD54: =IFERROR(DATEDIF(DadosViagem5[[#This Row],[Utimo Bip Reserva]],TODAY(),"D"),"") | AH54: 45807 | AI54: =IF(DadosViagem5[[#This Row],[Dias em manutenção ]]<5,"Dentro do Prazo","Fora do Prazo") -> Fora do Prazo | AJ54: #REF!
A55: GEN8H43 | C55: Sprinter 313 | D55: VAN | E55: Denigris | F55: COBLI | H55: 2022 | I55: SP | J55: GP01 | K55: GP01 VARGEM GRANDE (GRUPO PEREIRA) | L55: GRUPO PEREIRA | M55: Sara | N55: Adriano | O55: GUILHERME | P55: =IFERROR(VLOOKUP(DadosViagem5[[#This Row],[Placa]],BIP!A:E,5,FALSE),"") -> 45977 | Q55: =DATEDIF(DadosViagem5[[#This Row],[BIP]],TODAY(),"D") -> 1 | R55: =IFERROR(VLOOKUP(DadosViagem5[[#This Row],[Placa]],DDS!B:C,2,FALSE),"Verificar cadastro") -> Carregado | S55: Veículo Ativo | AD55: =IFERROR(DATEDIF(DadosViagem5[[#This Row],[Utimo Bip Reserva]],TODAY(),"D"),"") | AH55: 45807 | AI55: =IF(DadosViagem5[[#This Row],[Dias em manutenção ]]<5,"Dentro do Prazo","Fora do Prazo") -> Fora do Prazo | AJ55: #REF!
A56: SGL4D18 | C56: I/FORD TRANSIT 350 FL | D56: VAN | E56: Ford Go | F56: ITURAN | H56: 2023 | I56: SP | J56: GP01 | K56: GP01 VARGEM GRANDE (GRUPO PEREIRA) | L56: GRUPO PEREIRA | M56: Hillary | N56: Adriano | O56: GUILHERME | P56: =IFERROR(VLOOKUP(DadosViagem5[[#This Row],[Placa]],BIP!A:E,5,FALSE),"") -> 0 | Q56: =DATEDIF(DadosViagem5[[#This Row],[BIP]],TODAY(),"D") -> 45978 | R56: =IFERROR(VLOOKUP(DadosViagem5[[#This Row],[Placa]],DDS!B:C,2,FALSE),"Verificar cadastro") -> Manutenção | S56: Veículo Ativo | AH56: 45807 | AI56: =IF(DadosViagem5[[#This Row],[Dias em manutenção ]]<5,"Dentro do Prazo","Fora do Prazo") -> Fora do Prazo | AJ56: #REF!
A57: SGL2C38 | C57: I/FORD TRANSIT 350 FL | D57: VAN | E57: Ford Go | F57: ITURAN | H57: 2023 | I57: SP | J57: GP01 | K57: GP01 VARGEM GRANDE (GRUPO PEREIRA) | L57: GRUPO PEREIRA | M57: Hillary | N57: Adriano | O57: GUILHERME | P57: =IFERROR(VLOOKUP(DadosViagem5[[#This Row],[Placa]],BIP!A:E,5,FALSE),"") -> 0 | Q57: =DATEDIF(DadosViagem5[[#This Row],[BIP]],TODAY(),"D") -> 45978 | R57: =IFERROR(VLOOKUP(DadosViagem5[[#This Row],[Placa]],DDS!B:C,2,FALSE),"Verificar cadastro") | S57: Veículo Ativo | AD57: =IFERROR(DATEDIF(DadosViagem5[[#This Row],[Utimo Bip Reserva]],TODAY(),"D"),"") | AH57: 45807 | AI57: =IF(DadosViagem5[[#This Row],[Dias em manutenção ]]<5,"Dentro do Prazo","Fora do Prazo") -> Fora do Prazo | AJ57: #REF!
A58: GEV8B15 | C58: Sprinter 313 | D58: VAN | E58: Denigris | F58: COBLI | H58: 2023 | I58: SP | J58: GP01 | K58: GP01 VARGEM GRANDE (GRUPO PEREIRA) | L58: GRUPO PEREIRA | M58: Sara | N58: Adriano | O58: GUILHERME | P58: =IFERROR(VLOOKUP(DadosViagem5[[#This Row],[Placa]],BIP!A:E,5,FALSE),"") -> 45977 | Q58: =DATEDIF(DadosViagem5[[#This Row],[BIP]],TODAY(),"D") -> 1 | R58: =IFERROR(VLOOKUP(DadosViagem5[[#This Row],[Placa]],DDS!B:C,2,FALSE),"Verificar cadastro") -> Carregado | S58: Veículo Ativo | AD58: =IFERROR(DATEDIF(DadosViagem5[[#This Row],[Utimo Bip Reserva]],TODAY(),"D"),"") | AG58: Abner | AH58: 45807 | AI58: =IF(DadosViagem5[[#This Row],[Dias em manutenção ]]<5,"Dentro do Prazo","Fora do Prazo") -> Fora do Prazo | AJ58: #REF!
A59: GDY7B23 | C59: Sprinter 313 | D59: VAN | E59: Denigris | F59: COBLI | H59: 2022 | I59: SP | J59: GP01 | K59: GP01 VARGEM GRANDE (GRUPO PEREIRA) | L59: GRUPO PEREIRA | M59: Sara | N59: Adriano | O59: GUILHERME | P59: =IFERROR(VLOOKUP(DadosViagem5[[#This Row],[Placa]],BIP!A:E,5,FALSE),"") -> 45977 | Q59: =DATEDIF(DadosViagem5[[#This Row],[BIP]],TODAY(),"D") -> 1 | R59: =IFERROR(VLOOKUP(DadosViagem5[[#This Row],[Placa]],DDS!B:C,2,FALSE),"Verificar cadastro") -> Carregado | S59: Veículo Ativo | W59: disponibilizado para base 24/09 | AD59: =IFERROR(DATEDIF(DadosViagem5[[#This Row],[Utimo Bip Reserva]],TODAY(),"D"),"") | AH59: 45807 | AI59: =IF(DadosViagem5[[#This Row],[Dias em manutenção ]]<5,"Dentro do Prazo","Fora do Prazo") -> Fora do Prazo | AJ59: #REF!
A60: GEI7B15 | C60: Sprinter 313 | D60: VAN | E60: Denigris | F60: COBLI | H60: 2022 | I60: SP | J60: GP01 | K60: GP01 VARGEM GRANDE (GRUPO PEREIRA) | L60: GRUPO PEREIRA | M60: Sara | N60: Adriano | O60: GUILHERME | P60: =IFERROR(VLOOKUP(DadosViagem5[[#This Row],[Placa]],BIP!A:E,5,FALSE),"") -> 45977 | Q60: =DATEDIF(DadosViagem5[[#This Row],[BIP]],TODAY(),"D") -> 1 | R60: =IFERROR(VLOOKUP(DadosViagem5[[#This Row],[Placa]],DDS!B:C,2,FALSE),"Verificar cadastro") -> Carregado | S60: Veículo Ativo | AD60: =IFERROR(DATEDIF(DadosViagem5[[#This Row],[Utimo Bip Reserva]],TODAY(),"D"),"") | AH60: 45807 | AI60: =IF(DadosViagem5[[#This Row],[Dias em manutenção ]]<5,"Dentro do Prazo","Fora do Prazo") -> Fora do Prazo | AJ60: #REF!
A61: GCL2D74 | C61: Sprinter 313 | D61: VAN | E61: Denigris | F61: COBLI | H61: 2023 | I61: SP | J61: GP01 | K61: GP01 VARGEM GRANDE (GRUPO PEREIRA) | L61: GRUPO PEREIRA | M61: Sara | N61: Adriano | O61: GUILHERME | P61: =IFERROR(VLOOKUP(DadosViagem5[[#This Row],[Placa]],BIP!A:E,5,FALSE),"") -> 0 | Q61: =DATEDIF(DadosViagem5[[#This Row],[BIP]],TODAY(),"D") -> 45978 | R61: =IFERROR(VLOOKUP(DadosViagem5[[#This Row],[Placa]],DDS!B:C,2,FALSE),"Verificar cadastro") -> Manutenção | S61: Veículo Ativo | AD61: =IFERROR(DATEDIF(DadosViagem5[[#This Row],[Utimo Bip Reserva]],TODAY(),"D"),"") | AH61: 45807 | AI61: =IF(DadosViagem5[[#This Row],[Dias em manutenção ]]<5,"Dentro do Prazo","Fora do Prazo") -> Fora do Prazo | AJ61: #REF!
A62: FUP1A85 | C62: Sprinter 313 | D62: VAN | E62: Denigris | F62: COBLI | H62: 2022 | I62: SP | J62: GP01 | K62: GP01 VARGEM GRANDE (GRUPO PEREIRA) | L62: GRUPO PEREIRA | M62: Sara | N62: Adriano | O62: GUILHERME | P62: =IFERROR(VLOOKUP(DadosViagem5[[#This Row],[Placa]],BIP!A:E,5,FALSE),"") -> 45977 | Q62: =DATEDIF(DadosViagem5[[#This Row],[BIP]],TODAY(),"D") -> 1 | R62: =IFERROR(VLOOKUP(DadosViagem5[[#This Row],[Placa]],DDS!B:C,2,FALSE),"Verificar cadastro") -> Carregado | S62: Veículo Ativo | AD62: =IFERROR(DATEDIF(DadosViagem5[[#This Row],[Utimo Bip Reserva]],TODAY(),"D"),"") | AH62: 45807 | AI62: =IF(DadosViagem5[[#This Row],[Dias em manutenção ]]<5,"Dentro do Prazo","Fora do Prazo") -> Fora do Prazo | AJ62: #REF!
A63: GGV1A34 | C63: Sprinter 313 | D63: VAN | E63: Denigris | F63: COBLI | H63: 2023 | I63: SP | J63: GP01 | K63: GP01 VARGEM GRANDE (GRUPO PEREIRA) | L63: GRUPO PEREIRA | M63: Sara | N63: Adriano | O63: GUILHERME | P63: =IFERROR(VLOOKUP(DadosViagem5[[#This Row],[Placa]],BIP!A:E,5,FALSE),"") -> 45977 | Q63: =DATEDIF(DadosViagem5[[#This Row],[BIP]],TODAY(),"D") -> 1 | S63: Veículo Ativo | V63: 45916 | W63: Veículo disponível para a base 31/10 | X63: Corretiva | Y63: Em Diagnóstico | Z63: Estacionamento da Coca/MuriTruck | AD63: =IFERROR(DATEDIF(DadosViagem5[[#This Row],[Utimo Bip Reserva]],TODAY(),"D"),"") | AH63: 45807 | AI63: =IF(DadosViagem5[[#This Row],[Dias em manutenção ]]<5,"Dentro do Prazo","Fora do Prazo") -> Fora do Prazo | AJ63: #REF!
A64: GJN6D04 | C64: Sprinter 313 | D64: VAN | E64: Denigris | F64: COBLI | H64: 2023 | I64: SP | J64: GP01 | K64: GP01 VARGEM GRANDE (GRUPO PEREIRA) | L64: GRUPO PEREIRA | M64: Sara | N64: Adriano | O64: GUILHERME | P64: =IFERROR(VLOOKUP(DadosViagem5[[#This Row],[Placa]],BIP!A:E,5,FALSE),"") -> 45977 | Q64: =DATEDIF(DadosViagem5[[#This Row],[BIP]],TODAY(),"D") -> 1 | R64: =IFERROR(VLOOKUP(DadosViagem5[[#This Row],[Placa]],DDS!B:C,2,FALSE),"Verificar cadastro") -> Carregado | S64: Manutenção Própria | AD64: =IFERROR(DATEDIF(DadosViagem5[[#This Row],[Utimo Bip Reserva]],TODAY(),"D"),"") | AH64: 45807 | AI64: =IF(DadosViagem5[[#This Row],[Dias em manutenção ]]<5,"Dentro do Prazo","Fora do Prazo") -> Fora do Prazo | AJ64: #REF!
A65: SGL1J08 | C65: I/FORD TRANSIT 350 FL | D65: VAN | E65: Ford Go | F65: ITURAN | H65: 2025 | I65: SP | J65: GP01 | K65: GP01 VARGEM GRANDE (GRUPO PEREIRA) | L65: GRUPO PEREIRA | M65: Hillary | N65: Adriano | O65: GUILHERME | P65: =IFERROR(VLOOKUP(DadosViagem5[[#This Row],[Placa]],BIP!A:E,5,FALSE),"") -> 45977 | Q65: =DATEDIF(DadosViagem5[[#This Row],[BIP]],TODAY(),"D") -> 1 | R65: =IFERROR(VLOOKUP(DadosViagem5[[#This Row],[Placa]],DDS!B:C,2,FALSE),"Verificar cadastro") -> Carregado | S65: Veículo Ativo | AD65: =IFERROR(DATEDIF(DadosViagem5[[#This Row],[Utimo Bip Reserva]],TODAY(),"D"),"") | AH65: 45807 | AI65: =IF(DadosViagem5[[#This Row],[Dias em manutenção ]]<5,"Dentro do Prazo","Fora do Prazo") -> Fora do Prazo | AJ65: #REF!
A66: SGL2C80 | C66: I/FORD TRANSIT 350 FL | D66: VAN | E66: Ford Go | F66: ITURAN | H66: 2023 | I66: SP | J66: GP01 | K66: GP01 VARGEM GRANDE (GRUPO PEREIRA) | L66: GRUPO PEREIRA | M66: Hillary | N66: Adriano | O66: GUILHERME | P66: =IFERROR(VLOOKUP(DadosViagem5[[#This Row],[Placa]],BIP!A:E,5,FALSE),"") -> 45977 | Q66: =DATEDIF(DadosViagem5[[#This Row],[BIP]],TODAY(),"D") -> 1 | R66: =IFERROR(VLOOKUP(DadosViagem5[[#This Row],[Placa]],DDS!B:C,2,FALSE),"Verificar cadastro") -> Carregado | S66: Veículo Ativo | AD66: =IFERROR(DATEDIF(DadosViagem5[[#This Row],[Utimo Bip Reserva]],TODAY(),"D"),"") | AH66: 45807 | AI66: =IF(DadosViagem5[[#This Row],[Dias em manutenção ]]<5,"Dentro do Prazo","Fora do Prazo") -> Fora do Prazo | AJ66: #REF!
A67: GII1D53 | C67: Sprinter 313 | D67: VAN | E67: Denigris | F67: COBLI | H67: 2022 | I67: SP | J67: GP01 | K67: GP01 VARGEM GRANDE (GRUPO PEREIRA) | L67: GRUPO PEREIRA | M67: Sara | N67: Adriano | O67: GUILHERME | P67: =IFERROR(VLOOKUP(DadosViagem5[[#This Row],[Placa]],BIP!A:E,5,FALSE),"") -> 45977 | Q67: =DATEDIF(DadosViagem5[[#This Row],[BIP]],TODAY(),"D") -> 1 | R67: =IFERROR(VLOOKUP(DadosViagem5[[#This Row],[Placa]],DDS!B:C,2,FALSE),"Verificar cadastro") -> Carregado | S67: Veículo Ativo | AD67: =IFERROR(DATEDIF(DadosViagem5[[#This Row],[Utimo Bip Reserva]],TODAY(),"D"),"") | AE67: 09/05 sem previsão | AH67: 45807 | AI67: =IF(DadosViagem5[[#This Row],[Dias em manutenção ]]<5,"Dentro do Prazo","Fora do Prazo") -> Fora do Prazo | AJ67: #REF!
A68: GGF8H51 | C68: Sprinter 313 | D68: VAN | E68: Denigris | F68: COBLI | H68: 2023 | I68: SP | J68: GP01 | K68: GP01 VARGEM GRANDE (GRUPO PEREIRA) | L68: GRUPO PEREIRA | M68: Sara | N68: Adriano | O68: GUILHERME | P68: =IFERROR(VLOOKUP(DadosViagem5[[#This Row],[Placa]],BIP!A:E,5,FALSE),"") -> 45977 | Q68: =DATEDIF(DadosViagem5[[#This Row],[BIP]],TODAY(),"D") -> 1 | R68: =IFERROR(VLOOKUP(DadosViagem5[[#This Row],[Placa]],DDS!B:C,2,FALSE),"Verificar cadastro") -> Carregado | S68: Veículo Ativo | AD68: =IFERROR(DATEDIF(DadosViagem5[[#This Row],[Utimo Bip Reserva]],TODAY(),"D"),"") | AH68: 45807 | AI68: =IF(DadosViagem5[[#This Row],[Dias em manutenção ]]<5,"Dentro do Prazo","Fora do Prazo") -> Fora do Prazo | AJ68: #REF!
A69: TOE7D25 | B69: 768 | C69: I/FORD TRANSIT 350 FL | D69: VAN | E69: Ford Go | F69: ITURAN | H69: 2023 | I69: SP | J69: GP01 | K69: GP01 VARGEM GRANDE (GRUPO PEREIRA) | L69: GRUPO PEREIRA | M69: Hillary | N69: Adriano | O69: GUILHERME | P69: =IFERROR(VLOOKUP(DadosViagem5[[#This Row],[Placa]],BIP!A:E,5,FALSE),"") | Q69: =DATEDIF(DadosViagem5[[#This Row],[BIP]],TODAY(),"D") -> #VALUE! | R69: =IFERROR(VLOOKUP(DadosViagem5[[#This Row],[Placa]],DDS!B:C,2,FALSE),"Verificar cadastro") | S69: Veículo Ativo | AD69: =IFERROR(DATEDIF(DadosViagem5[[#This Row],[Utimo Bip Reserva]],TODAY(),"D"),"") | AH69: 45807 | AI69: =IF(DadosViagem5[[#This Row],[Dias em manutenção ]]<5,"Dentro do Prazo","Fora do Prazo") -> Fora do Prazo | AJ69: #REF!
A70: SGL4D27 | B70: 772 | C70: I/FORD TRANSIT 350 FL | D70: VAN | E70: Ford Go | F70: ITURAN | H70: 2023 | I70: SP | J70: GP01 | K70: GP01 VARGEM GRANDE (GRUPO PEREIRA) | L70: GRUPO PEREIRA | M70: Hillary | N70: Adriano | O70: GUILHERME | P70: =IFERROR(VLOOKUP(DadosViagem5[[#This Row],[Placa]],BIP!A:E,5,FALSE),"") | Q70: =DATEDIF(DadosViagem5[[#This Row],[BIP]],TODAY(),"D") -> #VALUE! | R70: =IFERROR(VLOOKUP(DadosViagem5[[#This Row],[Placa]],DDS!B:C,2,FALSE),"Verificar cadastro") | S70: Veículo Ativo | AH70: 45807 | AI70: =IF(DadosViagem5[[#This Row],[Dias em manutenção ]]<5,"Dentro do Prazo","Fora do Prazo") -> Fora do Prazo | AJ70: #REF!
A71: GHW4C93 | C71: Sprinter 313 | D71: VAN | E71: Denigris | F71: COBLI | H71: 2023 | I71: SP | J71: GP02 | K71: GP02 JACAREI (GRUPO PEREIRA) | L71: GRUPO PEREIRA | M71: Sara | N71: RENATO | O71: GUILHERME | P71: =IFERROR(VLOOKUP(DadosViagem5[[#This Row],[Placa]],BIP!A:E,5,FALSE),"") -> 45977 | Q71: =DATEDIF(DadosViagem5[[#This Row],[BIP]],TODAY(),"D") -> 1 | R71: =IFERROR(VLOOKUP(DadosViagem5[[#This Row],[Placa]],DDS!B:C,2,FALSE),"Verificar cadastro") -> Carregado | S71: Veículo Ativo | AD71: =IFERROR(DATEDIF(DadosViagem5[[#This Row],[Utimo Bip Reserva]],TODAY(),"D"),"") | AH71: 45807 | AI71: =IF(DadosViagem5[[#This Row],[Dias em manutenção ]]<5,"Dentro do Prazo","Fora do Prazo") -> Fora do Prazo | AJ71: #REF!
A72: GFV1C44 | C72: Sprinter 313 | D72: VAN | E72: Denigris | F72: COBLI | H72: 2023 | I72: SP | J72: GP02 | K72: GP02 JACAREI (GRUPO PEREIRA) | L72: GRUPO PEREIRA | M72: Sara | N72: RENATO | O72: GUILHERME | P72: =IFERROR(VLOOKUP(DadosViagem5[[#This Row],[Placa]],BIP!A:E,5,FALSE),"") -> 0 | Q72: =DATEDIF(DadosViagem5[[#This Row],[BIP]],TODAY(),"D") -> 45978 | R72: =IFERROR(VLOOKUP(DadosViagem5[[#This Row],[Placa]],DDS!B:C,2,FALSE),"Verificar cadastro") -> Manutenção | S72: Sinistro Proprio | V72: 45847 | W72: 03/09 - Time reenviou a aprovação ao diretor, onde aguardamos a aprovação. 18/08 - Veículo segue pendente de aprovação. 08/08 - Veículo foi realocado para a oficina GR por falta de espaço. 07/08 - Veículo será retirado de guincho e será encaminhado para a oficina Passos as 13h. 29/07 - Veículo está realizando a funilaria do teto na oficina Vieira. | X72: Sinistro | Y72: Aguardando Aprovação | Z72: GR CAR | AD72: =IFERROR(DATEDIF(DadosViagem5[[#This Row],[Utimo Bip Reserva]],TODAY(),"D"),"") | AH72: 45807 | AI72: =IF(DadosViagem5[[#This Row],[Dias em manutenção ]]<5,"Dentro do Prazo","Fora do Prazo") -> Fora do Prazo | AJ72: #REF!
A73: GHW1G44 | C73: Sprinter 313 | D73: VAN | E73: Denigris | F73: COBLI | H73: 2022 | I73: SP | J73: GP02 | K73: GP02 JACAREI (GRUPO PEREIRA) | L73: GRUPO PEREIRA | M73: Sara | N73: RENATO | O73: GUILHERME | P73: =IFERROR(VLOOKUP(DadosViagem5[[#This Row],[Placa]],BIP!A:E,5,FALSE),"") -> 45977 | Q73: =DATEDIF(DadosViagem5[[#This Row],[BIP]],TODAY(),"D") -> 1 | R73: =IFERROR(VLOOKUP(DadosViagem5[[#This Row],[Placa]],DDS!B:C,2,FALSE),"Verificar cadastro") -> Carregado | S73: Veículo Ativo | W73: Disponibilizado pela base- 24/09 | AD73: =IFERROR(DATEDIF(DadosViagem5[[#This Row],[Utimo Bip Reserva]],TODAY(),"D"),"") | AH73: 45807 | AI73: =IF(DadosViagem5[[#This Row],[Dias em manutenção ]]<5,"Dentro do Prazo","Fora do Prazo") -> Fora do Prazo | AJ73: #REF!
A74: GCX2D35 | C74: Sprinter 313 | D74: VAN | E74: Denigris | F74: COBLI | H74: 2023 | I74: SP | J74: GP02 | K74: GP02 JACAREI (GRUPO PEREIRA) | L74: GRUPO PEREIRA | M74: Sara | N74: RENATO | O74: GUILHERME | P74: =IFERROR(VLOOKUP(DadosViagem5[[#This Row],[Placa]],BIP!A:E,5,FALSE),"") -> 45977 | Q74: =DATEDIF(DadosViagem5[[#This Row],[BIP]],TODAY(),"D") -> 1 | R74: =IFERROR(VLOOKUP(DadosViagem5[[#This Row],[Placa]],DDS!B:C,2,FALSE),"Verificar cadastro") -> Carregado | S74: Veículo Ativo | AD74: =IFERROR(DATEDIF(DadosViagem5[[#This Row],[Utimo Bip Reserva]],TODAY(),"D"),"") | AH74: 45807 | AI74: =IF(DadosViagem5[[#This Row],[Dias em manutenção ]]<5,"Dentro do Prazo","Fora do Prazo") -> Fora do Prazo | AJ74: #REF!
A75: GFS6J84 | C75: Sprinter 313 | D75: VAN | E75: Denigris | F75: COBLI | H75: 2023 | I75: SP | J75: GP02 | K75: GP02 JACAREI (GRUPO PEREIRA) | L75: GRUPO PEREIRA | M75: Sara | N75: RENATO | O75: GUILHERME | P75: =IFERROR(VLOOKUP(DadosViagem5[[#This Row],[Placa]],BIP!A:E,5,FALSE),"") -> 45977 | Q75: =DATEDIF(DadosViagem5[[#This Row],[BIP]],TODAY(),"D") -> 1 | R75: =IFERROR(VLOOKUP(DadosViagem5[[#This Row],[Placa]],DDS!B:C,2,FALSE),"Verificar cadastro") -> Carregado | S75: Veículo Ativo | AD75: =IFERROR(DATEDIF(DadosViagem5[[#This Row],[Utimo Bip Reserva]],TODAY(),"D"),"") | AH75: 45807 | AI75: =IF(DadosViagem5[[#This Row],[Dias em manutenção ]]<5,"Dentro do Prazo","Fora do Prazo") -> Fora do Prazo | AJ75: #REF!
A76: GAX9F44 | C76: Sprinter 313 | D76: VAN | E76: Denigris | F76: COBLI | H76: 2023 | I76: SP | J76: GP02 | K76: GP02 JACAREI (GRUPO PEREIRA) | L76: GRUPO PEREIRA | M76: Sara | N76: RENATO | O76: GUILHERME | P76: =IFERROR(VLOOKUP(DadosViagem5[[#This Row],[Placa]],BIP!A:E,5,FALSE),"") -> 45977 | Q76: =DATEDIF(DadosViagem5[[#This Row],[BIP]],TODAY(),"D") -> 1 | R76: =IFERROR(VLOOKUP(DadosViagem5[[#This Row],[Placa]],DDS!B:C,2,FALSE),"Verificar cadastro") -> Carregado | S76: Veículo Ativo | AD76: =IFERROR(DATEDIF(DadosViagem5[[#This Row],[Utimo Bip Reserva]],TODAY(),"D"),"") | AH76: 28 | AI76: =IF(DadosViagem5[[#This Row],[Dias em manutenção ]]<5,"Dentro do Prazo","Fora do Prazo") -> Fora do Prazo | AJ76: #REF!
A77: GDD8C74 | C77: Sprinter 313 | D77: VAN | E77: Denigris | F77: COBLI | H77: 2023 | I77: SP | J77: GP02 | K77: GP02 JACAREI (GRUPO PEREIRA) | L77: GRUPO PEREIRA | M77: Sara | N77: RENATO | O77: GUILHERME | P77: =IFERROR(VLOOKUP(DadosViagem5[[#This Row],[Placa]],BIP!A:E,5,FALSE),"") -> 45977 | Q77: =DATEDIF(DadosViagem5[[#This Row],[BIP]],TODAY(),"D") -> 1 | R77: =IFERROR(VLOOKUP(DadosViagem5[[#This Row],[Placa]],DDS!B:C,2,FALSE),"Verificar cadastro") -> Carregado | S77: Veículo Ativo | AD77: =IFERROR(DATEDIF(DadosViagem5[[#This Row],[Utimo Bip Reserva]],TODAY(),"D"),"") | AH77: 45807 | AI77: =IF(DadosViagem5[[#This Row],[Dias em manutenção ]]<5,"Dentro do Prazo","Fora do Prazo") -> Fora do Prazo | AJ77: #REF!
A78: GEY9C46 | C78: Sprinter 313 | D78: VAN | E78: Denigris | F78: COBLI | H78: 2022 | I78: SP | J78: GP02 | K78: GP02 JACAREI (GRUPO PEREIRA) | L78: GRUPO PEREIRA | M78: Sara | N78: RENATO | O78: GUILHERME | P78: =IFERROR(VLOOKUP(DadosViagem5[[#This Row],[Placa]],BIP!A:E,5,FALSE),"") -> 45977 | Q78: =DATEDIF(DadosViagem5[[#This Row],[BIP]],TODAY(),"D") -> 1 | R78: =IFERROR(VLOOKUP(DadosViagem5[[#This Row],[Placa]],DDS!B:C,2,FALSE),"Verificar cadastro") -> Carregado | S78: Veículo Ativo | AD78: =IFERROR(DATEDIF(DadosViagem5[[#This Row],[Utimo Bip Reserva]],TODAY(),"D"),"") | AH78: 45807 | AI78: =IF(DadosViagem5[[#This Row],[Dias em manutenção ]]<5,"Dentro do Prazo","Fora do Prazo") -> Fora do Prazo | AJ78: #REF!
A79: GID6J64 | C79: Sprinter 313 | D79: VAN | E79: Denigris | F79: COBLI | H79: 2023 | I79: SP | J79: GP02 | K79: GP02 JACAREI (GRUPO PEREIRA) | L79: GRUPO PEREIRA | M79: Sara | N79: RENATO | O79: GUILHERME | P79: =IFERROR(VLOOKUP(DadosViagem5[[#This Row],[Placa]],BIP!A:E,5,FALSE),"") -> 45977 | Q79: =DATEDIF(DadosViagem5[[#This Row],[BIP]],TODAY(),"D") -> 1 | R79: =IFERROR(VLOOKUP(DadosViagem5[[#This Row],[Placa]],DDS!B:C,2,FALSE),"Verificar cadastro") -> Carregado | S79: Manutenção Própria | AD79: =IFERROR(DATEDIF(DadosViagem5[[#This Row],[Utimo Bip Reserva]],TODAY(),"D"),"") | AH79: 45807 | AI79: =IF(DadosViagem5[[#This Row],[Dias em manutenção ]]<5,"Dentro do Prazo","Fora do Prazo") -> Fora do Prazo | AJ79: #REF!
A80: GGN8H92 | C80: Sprinter 313 | D80: VAN | E80: Denigris | F80: COBLI | H80: 2023 | I80: SP | J80: GP02 | K80: GP02 JACAREI (GRUPO PEREIRA) | L80: GRUPO PEREIRA | M80: Sara | N80: RENATO | O80: GUILHERME | P80: =IFERROR(VLOOKUP(DadosViagem5[[#This Row],[Placa]],BIP!A:E,5,FALSE),"") -> 45977 | Q80: =DATEDIF(DadosViagem5[[#This Row],[BIP]],TODAY(),"D") -> 1 | R80: =IFERROR(VLOOKUP(DadosViagem5[[#This Row],[Placa]],DDS!B:C,2,FALSE),"Verificar cadastro") -> Carregado | S80: Veículo Ativo | AD80: =IFERROR(DATEDIF(DadosViagem5[[#This Row],[Utimo Bip Reserva]],TODAY(),"D"),"") | AH80: 45807 | AI80: =IF(DadosViagem5[[#This Row],[Dias em manutenção ]]<5,"Dentro do Prazo","Fora do Prazo") -> Fora do Prazo | AJ80: #REF!
